Workbook

Sheet Presupuesto
B2: PRESUPUESTO | K2: CONFIGURADOR
B4: Número | C4: PRE-0001 | D4: Fecha | K4: Configuración | L4: FRA MUSE MICR — MUSELINA DAMA [#1]
B5: Cliente | K5: Escala | L5: 1 A 5 DOC
B6: Teléfono | K6: Cantidad | L6: 12
B7: Email
K8: id_receta (auxiliar) | L8: =IFERROR(INDEX(Indice!$A$2:$A$237,MATCH($L$4,Indice!$E$2:$E$237,0)),"") -> 1
B9: ITEM | C9: CANT | D9: DESCRIPCIÓN | E9: COSTO UNIT | F9: TOTAL | H9: Configuración (auxiliar) | I9: Escala (auxiliar) | K9: Descripción | L9: =IFERROR(INDEX(Indice!$B$2:$B$237,MATCH($L$8,Indice!$A$2:$A$237,0))&" — "&INDEX(Indice!$D$2:$D$237,MATCH($L$8,Indice!$A$2:$A$237,0)),"—") -> FRA MUSE MICR — MUSELINA DAMA
K10: Costo interno unitario (USD) | L10: =IFERROR(SUMIFS(M_Recetas!$J$2:$J$2828,M_Recetas!$A$2:$A$2828,$L$8),0) -> 3.6525
K11: Precio unitario (USD) | L11: =IFERROR(INDEX(M_Escalas!$G$2:$G$706,MATCH($L$8&"|"&$L$5,M_Escalas!$I$2:$I$706,0)),"Sin dato — revisar Anomalias") -> 5.844
K12: Margen (USD) | L12: =IF(ISNUMBER($L$11),$L$11-$L$10,"—") -> 2.1915
K13: Margen (%) | L13: =IF(AND(ISNUMBER($L$11),$L$11<>0),$L$12/$L$11,"—") -> 0.375
K15: Desglose del costo interno
K16: Insumo | L16: =IFERROR(SUMIFS(M_Recetas!$J$2:$J$2828,M_Recetas!$A$2:$A$2828,$L$8,M_Recetas!$F$2:$F$2828,"Insumo"),0) -> 2.1025
K17: Proceso | L17: =IFERROR(SUMIFS(M_Recetas!$J$2:$J$2828,M_Recetas!$A$2:$A$2828,$L$8,M_Recetas!$F$2:$F$2828,"Proceso"),0) -> 0.8
K18: Tecnica | L18: =IFERROR(SUMIFS(M_Recetas!$J$2:$J$2828,M_Recetas!$A$2:$A$2828,$L$8,M_Recetas!$F$2:$F$2828,"Tecnica"),0) -> 0
K19: Indirecto | L19: =IFERROR(SUMIFS(M_Recetas!$J$2:$J$2828,M_Recetas!$A$2:$A$2828,$L$8,M_Recetas!$F$2:$F$2828,"Indirecto"),0) -> 0.75
K20: Otro | L20: =IFERROR(SUMIFS(M_Recetas!$J$2:$J$2828,M_Recetas!$A$2:$A$2828,$L$8,M_Recetas!$F$2:$F$2828,"Otro"),0) -> 0
K21: Total (verificación) | L21: =SUM(L16:L20) -> 3.6525
K23: Editar línea Nº (ITEM)
K25: Botones (a asignar tras importar el macro): ① Agregar/Actualizar línea → M01_GestionPresupuesto.AgregarOActualizarItem ② Cargar línea para editar → M01_GestionPresupuesto.CargarItemParaEditar ③ Limpiar configurador → M01_GestionPresupuesto.LimpiarConfigurador ④ Eliminar línea → M01_GestionPresupuesto.EliminarItem
D26: TOTAL A PAGAR | F26: =SUM(F10:F24) -> 0
E27: ABONO:
E28: RESTA: | F28: =F26-F27 -> 0
B30: Términos y condiciones (editable): - Se requiere un abono del 60% del total para dar comienzo al proyecto. - El precio a partir de la talla XL suma un recargo por unidad (definir monto). - La fecha de entrega es estimada. El presupuesto es válido solo para el día especificado.

Sheet M_Recetas
A1: id_receta | B1: hoja | C1: seccion_tecnica | D1: bloque_variante | E1: componente | F1: clasificacion | G1: consumo | H1: precio_unitario | I1: costo_local | J1: costo_usd | K1: origen | L1: formula
A2: 1 | B2: FRA MUSE MICR | C2: MUSELINA DAMA | D2: MUSELINA DAMA | E2: TELA | F2: Insumo | G2: 0.8 | H2: 2.3 | I2: 7360 | J2: 1.84 | K2: FRA MUSE MICR!B4 | L2: fx: 0.8*2.3*E2
A3: 1 | B3: FRA MUSE MICR | C3: MUSELINA DAMA | D3: MUSELINA DAMA | E3: CORTE | F3: Proceso | I3: 700 | J3: 0.175 | K3: FRA MUSE MICR!B5
A4: 1 | B4: FRA MUSE MICR | C4: MUSELINA DAMA | D4: MUSELINA DAMA | E4: COSTURA | F4: Proceso | I4: 2500 | J4: 0.625 | K4: FRA MUSE MICR!B6
A5: 1 | B5: FRA MUSE MICR | C5: MUSELINA DAMA | D5: MUSELINA DAMA | E5: ETIQUETA | F5: Insumo | I5: 200 | J5: 0.05 | K5: FRA MUSE MICR!B7
A6: 1 | B6: FRA MUSE MICR | C6: MUSELINA DAMA | D6: MUSELINA DAMA | E6: BOLSA | F6: Insumo | I6: 100 | J6: 0.025 | K6: FRA MUSE MICR!B8
A7: 1 | B7: FRA MUSE MICR | C7: MUSELINA DAMA | D7: MUSELINA DAMA | E7: MARQUILLA | F7: Insumo | I7: 500 | J7: 0.125 | K7: FRA MUSE MICR!B9
A8: 1 | B8: FRA MUSE MICR | C8: MUSELINA DAMA | D8: MUSELINA DAMA | E8: HILO | F8: Insumo | I8: 250 | J8: 0.0625 | K8: FRA MUSE MICR!B10
A9: 1 | B9: FRA MUSE MICR | C9: MUSELINA DAMA | D9: MUSELINA DAMA | E9: GASTOS OPERATIVOS | F9: Indirecto | I9: 3000 | J9: 0.75 | K9: FRA MUSE MICR!B11
A10: 2 | B10: FRA MUSE MICR | C10: MUSELINA DAMA | D10: MICRO DAMA | E10: TELA | F10: Insumo | G10: 0.8 | H10: 2 | I10: 6400 | J10: 1.6 | K10: FRA MUSE MICR!G4 | L10: fx: 0.8*2*E2
A11: 2 | B11: FRA MUSE MICR | C11: MUSELINA DAMA | D11: MICRO DAMA | E11: CORTE | F11: Proceso | I11: 700 | J11: 0.175 | K11: FRA MUSE MICR!G5
A12: 2 | B12: FRA MUSE MICR | C12: MUSELINA DAMA | D12: MICRO DAMA | E12: COSTURA | F12: Proceso | I12: 2500 | J12: 0.625 | K12: FRA MUSE MICR!G6
A13: 2 | B13: FRA MUSE MICR | C13: MUSELINA DAMA | D13: MICRO DAMA | E13: ETIQUETA | F13: Insumo | I13: 200 | J13: 0.05 | K13: FRA MUSE MICR!G7
A14: 2 | B14: FRA MUSE MICR | C14: MUSELINA DAMA | D14: MICRO DAMA | E14: BOLSA | F14: Insumo | I14: 3000 | J14: 0.75 | K14: FRA MUSE MICR!G8
A15: 2 | B15: FRA MUSE MICR | C15: MUSELINA DAMA | D15: MICRO DAMA | E15: MARQUILLA | F15: Insumo | I15: 500 | J15: 0.125 | K15: FRA MUSE MICR!G9
A16: 2 | B16: FRA MUSE MICR | C16: MUSELINA DAMA | D16: MICRO DAMA | E16: HILO | F16: Insumo | I16: 350 | J16: 0.0875 | K16: FRA MUSE MICR!G10
A17: 2 | B17: FRA MUSE MICR | C17: MUSELINA DAMA | D17: MICRO DAMA | E17: GASTOS OPERATIVOS | F17: Indirecto | I17: 4000 | J17: 1 | K17: FRA MUSE MICR!G11
A18: 3 | B18: FRA MUSE MICR | C18: MUSELINA NIÑO | D18: MUSELINA NIÑO | E18: TELA | F18: Insumo | G18: 0.3 | H18: 1.3 | I18: 1560 | J18: 0.39 | K18: FRA MUSE MICR!B14 | L18: fx: 0.3*1.3*E2
A19: 3 | B19: FRA MUSE MICR | C19: MUSELINA NIÑO | D19: MUSELINA NIÑO | E19: CORTE | F19: Proceso | I19: 500 | J19: 0.125 | K19: FRA MUSE MICR!B15
A20: 3 | B20: FRA MUSE MICR | C20: MUSELINA NIÑO | D20: MUSELINA NIÑO | E20: COSTURA | F20: Proceso | I20: 2000 | J20: 0.5 | K20: FRA MUSE MICR!B16
A21: 3 | B21: FRA MUSE MICR | C21: MUSELINA NIÑO | D21: MUSELINA NIÑO | E21: ETIQUETA | F21: Insumo | I21: 0 | J21: 0 | K21: FRA MUSE MICR!B17
A22: 3 | B22: FRA MUSE MICR | C22: MUSELINA NIÑO | D22: MUSELINA NIÑO | E22: BOLSA | F22: Insumo | I22: 0 | J22: 0 | K22: FRA MUSE MICR!B18
A23: 3 | B23: FRA MUSE MICR | C23: MUSELINA NIÑO | D23: MUSELINA NIÑO | E23: MARQUILLA | F23: Insumo | I23: 0 | J23: 0 | K23: FRA MUSE MICR!B19
A24: 3 | B24: FRA MUSE MICR | C24: MUSELINA NIÑO | D24: MUSELINA NIÑO | E24: HILO | F24: Insumo | I24: 250 | J24: 0.0625 | K24: FRA MUSE MICR!B20
A25: 3 | B25: FRA MUSE MICR | C25: MUSELINA NIÑO | D25: MUSELINA NIÑO | E25: GASTOS OPERATIVOS | F25: Indirecto | I25: 2000 | J25: 0.5 | K25: FRA MUSE MICR!B21
A26: 4 | B26: FRA MUSE MICR | C26: MUSELINA NIÑO | D26: MICRO NIÑO | E26: TELA | F26: Insumo | G26: 0.6 | H26: 2 | I26: 4800 | J26: 1.2 | K26: FRA MUSE MICR!G14 | L26: fx: 0.6*2*E2
A27: 4 | B27: FRA MUSE MICR | C27: MUSELINA NIÑO | D27: MICRO NIÑO | E27: CORTE | F27: Proceso | I27: 700 | J27: 0.175 | K27: FRA MUSE MICR!G15
A28: 4 | B28: FRA MUSE MICR | C28: MUSELINA NIÑO | D28: MICRO NIÑO | E28: COSTURA | F28: Proceso | I28: 3000 | J28: 0.75 | K28: FRA MUSE MICR!G16
A29: 4 | B29: FRA MUSE MICR | C29: MUSELINA NIÑO | D29: MICRO NIÑO | E29: ETIQUETA | F29: Insumo | G29: 0.6 | H29: 12000 | I29: 7200 | J29: 1.8 | K29: FRA MUSE MICR!G17 | L29: fx: 0.6*12000
A30: 4 | B30: FRA MUSE MICR | C30: MUSELINA NIÑO | D30: MICRO NIÑO | E30: BOLSA | F30: Insumo | I30: 0 | J30: 0 | K30: FRA MUSE MICR!G18
A31: 4 | B31: FRA MUSE MICR | C31: MUSELINA NIÑO | D31: MICRO NIÑO | E31: MARQUILLA | F31: Insumo | I31: 0 | J31: 0 | K31: FRA MUSE MICR!G19
A32: 4 | B32: FRA MUSE MICR | C32: MUSELINA NIÑO | D32: MICRO NIÑO | E32: HILO | F32: Insumo | I32: 250 | J32: 0.0625 | K32: FRA MUSE MICR!G20
A33: 4 | B33: FRA MUSE MICR | C33: MUSELINA NIÑO | D33: MICRO NIÑO | E33: GASTOS OPERATIVOS | F33: Indirecto | I33: 0 | J33: 0 | K33: FRA MUSE MICR!G21
A34: 5 | B34: FRA MUSE MICR | C34: MUSELINA CABALLERO | D34: MUSELINA CABALLERO | E34: TELA | F34: Insumo | G34: 0.9 | H34: 1.5 | I34: 5400 | J34: 1.35 | K34: FRA MUSE MICR!B24 | L34: fx: 0.9*1.5*E2
A35: 5 | B35: FRA MUSE MICR | C35: MUSELINA CABALLERO | D35: MUSELINA CABALLERO | E35: CORTE | F35: Proceso | I35: 300 | J35: 0.075 | K35: FRA MUSE MICR!B25
A36: 5 | B36: FRA MUSE MICR | C36: MUSELINA CABALLERO | D36: MUSELINA CABALLERO | E36: COSTURA | F36: Proceso | I36: 1800 | J36: 0.45 | K36: FRA MUSE MICR!B26
A37: 5 | B37: FRA MUSE MICR | C37: MUSELINA CABALLERO | D37: MUSELINA CABALLERO | E37: BORDADO | F37: Proceso | I37: 2500 | J37: 0.625 | K37: FRA MUSE MICR!B27
A38: 5 | B38: FRA MUSE MICR | C38: MUSELINA CABALLERO | D38: MUSELINA CABALLERO | E38: ETIQUETA | F38: Insumo | I38: 50 | J38: 0.0125 | K38: FRA MUSE MICR!B28
A39: 5 | B39: FRA MUSE MICR | C39: MUSELINA CABALLERO | D39: MUSELINA CABALLERO | E39: BOLSA | F39: Insumo | I39: 50 | J39: 0.0125 | K39: FRA MUSE MICR!B29
A40: 5 | B40: FRA MUSE MICR | C40: MUSELINA CABALLERO | D40: MUSELINA CABALLERO | E40: HILO | F40: Insumo | I40: 250 | J40: 0.0625 | K40: FRA MUSE MICR!B30 | L40: fx: B20
A41: 5 | B41: FRA MUSE MICR | C41: MUSELINA CABALLERO | D41: MUSELINA CABALLERO | E41: GASTOS OPERATIVOS | F41: Indirecto | I41: 1000 | J41: 0.25 | K41: FRA MUSE MICR!B31
A42: 6 | B42: FRA MUSE MICR | C42: MUSELINA CABALLERO | D42: MICRO CABALLERO | E42: TELA | F42: Insumo | G42: 1 | H42: 2.3 | I42: 9200 | J42: 2.3 | K42: FRA MUSE MICR!G24 | L42: fx: 1*2.3*E2
A43: 6 | B43: FRA MUSE MICR | C43: MUSELINA CABALLERO | D43: MICRO CABALLERO | E43: CORTE | F43: Proceso | I43: 700 | J43: 0.175 | K43: FRA MUSE MICR!G25
A44: 6 | B44: FRA MUSE MICR | C44: MUSELINA CABALLERO | D44: MICRO CABALLERO | E44: COSTURA | F44: Proceso | I44: 3500 | J44: 0.875 | K44: FRA MUSE MICR!G26
A45: 6 | B45: FRA MUSE MICR | C45: MUSELINA CABALLERO | D45: MICRO CABALLERO | E45: MARQUILLA | F45: Insumo | I45: 200 | J45: 0.05 | K45: FRA MUSE MICR!G27
A46: 6 | B46: FRA MUSE MICR | C46: MUSELINA CABALLERO | D46: MICRO CABALLERO | E46: ETIQUETA | F46: Insumo | I46: 100 | J46: 0.025 | K46: FRA MUSE MICR!G28
A47: 6 | B47: FRA MUSE MICR | C47: MUSELINA CABALLERO | D47: MICRO CABALLERO | E47: BOLSA | F47: Insumo | I47: 11000 | J47: 2.75 | K47: FRA MUSE MICR!G29 | L47: fx: 11000
A48: 6 | B48: FRA MUSE MICR | C48: MUSELINA CABALLERO | D48: MICRO CABALLERO | E48: HILO | F48: Insumo | I48: 250 | J48: 0.0625 | K48: FRA MUSE MICR!G30 | L48: fx: B30
A49: 6 | B49: FRA MUSE MICR | C49: MUSELINA CABALLERO | D49: MICRO CABALLERO | E49: GASTOS OPERATIVOS | F49: Indirecto | I49: 0 | J49: 0 | K49: FRA MUSE MICR!G31
A50: 7 | B50: FRA MUSE MICR | C50: MUSELINA DAMA | D50: MUSELINA DAMA | E50: TELA | F50: Insumo | I50: 0 | J50: 0 | K50: FRA MUSE MICR!B37
A51: 7 | B51: FRA MUSE MICR | C51: MUSELINA DAMA | D51: MUSELINA DAMA | E51: CORTE | F51: Proceso | I51: 700 | J51: 0.175 | K51: FRA MUSE MICR!B38
A52: 7 | B52: FRA MUSE MICR | C52: MUSELINA DAMA | D52: MUSELINA DAMA | E52: COSTURA | F52: Proceso | I52: 2500 | J52: 0.625 | K52: FRA MUSE MICR!B39
A53: 7 | B53: FRA MUSE MICR | C53: MUSELINA DAMA | D53: MUSELINA DAMA | E53: PLANCHA | F53: Proceso | I53: 1000 | J53: 0.25 | K53: FRA MUSE MICR!B40
A54: 7 | B54: FRA MUSE MICR | C54: MUSELINA DAMA | D54: MUSELINA DAMA | E54: VINIL 15 CMS | F54: Tecnica | I54: 5000 | J54: 1.25 | K54: FRA MUSE MICR!B41
A55: 7 | B55: FRA MUSE MICR | C55: MUSELINA DAMA | D55: MUSELINA DAMA | E55: CORTE DEL PLOTTER | F55: Tecnica | I55: 200 | J55: 0.05 | K55: FRA MUSE MICR!B42
A56: 7 | B56: FRA MUSE MICR | C56: MUSELINA DAMA | D56: MUSELINA DAMA | E56: DEPILADA | F56: Proceso | I56: 500 | J56: 0.125 | K56: FRA MUSE MICR!B43
A57: 7 | B57: FRA MUSE MICR | C57: MUSELINA DAMA | D57: MUSELINA DAMA | E57: ETIQUETA | F57: Insumo | I57: 200 | J57: 0.05 | K57: FRA MUSE MICR!B44
A58: 7 | B58: FRA MUSE MICR | C58: MUSELINA DAMA | D58: MUSELINA DAMA | E58: BOLSA | F58: Insumo | I58: 100 | J58: 0.025 | K58: FRA MUSE MICR!B45
A59: 7 | B59: FRA MUSE MICR | C59: MUSELINA DAMA | D59: MUSELINA DAMA | E59: HILO | F59: Insumo | I59: 250 | J59: 0.0625 | K59: FRA MUSE MICR!B46
A60: 7 | B60: FRA MUSE MICR | C60: MUSELINA DAMA | D60: MUSELINA DAMA | E60: MARQUILLA | F60: Insumo | I60: 100 | J60: 0.025 | K60: FRA MUSE MICR!B47
A61: 7 | B61: FRA MUSE MICR | C61: MUSELINA DAMA | D61: MUSELINA DAMA | E61: GASTOS OPERATIVOS | F61: Indirecto | I61: 4000 | J61: 1 | K61: FRA MUSE MICR!B48
A62: 8 | B62: FRA MUSE MICR | C62: MUSELINA DAMA | D62: MUSELINA NIÑO | E62: TELA | F62: Insumo | G62: 0.8 | H62: 1.8 | I62: 5760 | J62: 1.44 | K62: FRA MUSE MICR!G37 | L62: fx: 0.8*1.8*4000
A63: 8 | B63: FRA MUSE MICR | C63: MUSELINA DAMA | D63: MUSELINA NIÑO | E63: CORTE | F63: Proceso | I63: 700 | J63: 0.175 | K63: FRA MUSE MICR!G38
A64: 8 | B64: FRA MUSE MICR | C64: MUSELINA DAMA | D64: MUSELINA NIÑO | E64: COSTURA | F64: Proceso | I64: 3500 | J64: 0.875 | K64: FRA MUSE MICR!G39
A65: 8 | B65: FRA MUSE MICR | C65: MUSELINA DAMA | D65: MUSELINA NIÑO | E65: PLANCHA | F65: Proceso | I65: 1000 | J65: 0.25 | K65: FRA MUSE MICR!G40
A66: 8 | B66: FRA MUSE MICR | C66: MUSELINA DAMA | D66: MUSELINA NIÑO | E66: VINIL 15 CMS | F66: Tecnica | I66: 700 | J66: 0.175 | K66: FRA MUSE MICR!G41
A67: 8 | B67: FRA MUSE MICR | C67: MUSELINA DAMA | D67: MUSELINA NIÑO | E67: CORTE DEL PLOTTER | F67: Tecnica | I67: 0 | J67: 0 | K67: FRA MUSE MICR!G42
A68: 8 | B68: FRA MUSE MICR | C68: MUSELINA DAMA | D68: MUSELINA NIÑO | E68: DEPILADA | F68: Proceso | I68: 0 | J68: 0 | K68: FRA MUSE MICR!G43
A69: 8 | B69: FRA MUSE MICR | C69: MUSELINA DAMA | D69: MUSELINA NIÑO | E69: ETIQUETA | F69: Insumo | I69: 50 | J69: 0.0125 | K69: FRA MUSE MICR!G44
A70: 8 | B70: FRA MUSE MICR | C70: MUSELINA DAMA | D70: MUSELINA NIÑO | E70: BOLSA | F70: Insumo | I70: 100 | J70: 0.025 | K70: FRA MUSE MICR!G45
A71: 8 | B71: FRA MUSE MICR | C71: MUSELINA DAMA | D71: MUSELINA NIÑO | E71: HILO | F71: Insumo | I71: 250 | J71: 0.0625 | K71: FRA MUSE MICR!G46
A72: 8 | B72: FRA MUSE MICR | C72: MUSELINA DAMA | D72: MUSELINA NIÑO | E72: MARQUILLA | F72: Insumo | I72: 50 | J72: 0.0125 | K72: FRA MUSE MICR!G47
A73: 8 | B73: FRA MUSE MICR | C73: MUSELINA DAMA | D73: MUSELINA NIÑO | E73: GASTOS OPERATIVOS | F73: Indirecto | I73: 4000 | J73: 1 | K73: FRA MUSE MICR!G48
A74: 9 | B74: FRA MUSE MICR | C74: MICRO DAMA | D74: MICRO DAMA | E74: TELA | F74: Insumo | G74: 0.8 | H74: 2.3 | I74: 7360 | J74: 1.84 | K74: FRA MUSE MICR!B52 | L74: fx: 0.8*2.3*E2
A75: 9 | B75: FRA MUSE MICR | C75: MICRO DAMA | D75: MICRO DAMA | E75: CORTE | F75: Proceso | I75: 700 | J75: 0.175 | K75: FRA MUSE MICR!B53
A76: 9 | B76: FRA MUSE MICR | C76: MICRO DAMA | D76: MICRO DAMA | E76: COSTURA | F76: Proceso | I76: 2500 | J76: 0.625 | K76: FRA MUSE MICR!B54
A77: 9 | B77: FRA MUSE MICR | C77: MICRO DAMA | D77: MICRO DAMA | E77: DISEÑO | F77: Proceso | I77: 1000 | J77: 0.25 | K77: FRA MUSE MICR!B55
A78: 9 | B78: FRA MUSE MICR | C78: MICRO DAMA | D78: MICRO DAMA | E78: PLANCHA | F78: Proceso | I78: 0 | J78: 0 | K78: FRA MUSE MICR!B56
A79: 9 | B79: FRA MUSE MICR | C79: MICRO DAMA | D79: MICRO DAMA | E79: VINIL 15 CMS | F79: Tecnica | I79: 3000 | J79: 0.75 | K79: FRA MUSE MICR!B57
A80: 9 | B80: FRA MUSE MICR | C80: MICRO DAMA | D80: MICRO DAMA | E80: CORTE DEL PLOTTER | F80: Tecnica | I80: 200 | J80: 0.05 | K80: FRA MUSE MICR!B58
A81: 9 | B81: FRA MUSE MICR | C81: MICRO DAMA | D81: MICRO DAMA | E81: DEPILADA | F81: Proceso | I81: 200 | J81: 0.05 | K81: FRA MUSE MICR!B59
A82: 9 | B82: FRA MUSE MICR | C82: MICRO DAMA | D82: MICRO DAMA | E82: ETIQUETA | F82: Insumo | I82: 100 | J82: 0.025 | K82: FRA MUSE MICR!B60
A83: 9 | B83: FRA MUSE MICR | C83: MICRO DAMA | D83: MICRO DAMA | E83: BOLSA | F83: Insumo | I83: 100 | J83: 0.025 | K83: FRA MUSE MICR!B61
A84: 9 | B84: FRA MUSE MICR | C84: MICRO DAMA | D84: MICRO DAMA | E84: HILO | F84: Insumo | I84: 250 | J84: 0.0625 | K84: FRA MUSE MICR!B62 | L84: fx: B46
A85: 9 | B85: FRA MUSE MICR | C85: MICRO DAMA | D85: MICRO DAMA | E85: MARQUILLA | F85: Insumo | I85: 500 | J85: 0.125 | K85: FRA MUSE MICR!B63
A86: 9 | B86: FRA MUSE MICR | C86: MICRO DAMA | D86: MICRO DAMA | E86: GASTOS OPERATIVOS | F86: Indirecto | I86: 3700 | J86: 0.925 | K86: FRA MUSE MICR!B64
A87: 10 | B87: FRA MUSE MICR | C87: MICRO DAMA | D87: MICRO NIÑO | E87: TELA | F87: Insumo | G87: 0.6 | H87: 2 | I87: 4800 | J87: 1.2 | K87: FRA MUSE MICR!G52 | L87: fx: 0.6*2*E2
A88: 10 | B88: FRA MUSE MICR | C88: MICRO DAMA | D88: MICRO NIÑO | E88: CORTE | F88: Proceso | I88: 700 | J88: 0.175 | K88: FRA MUSE MICR!G53
A89: 10 | B89: FRA MUSE MICR | C89: MICRO DAMA | D89: MICRO NIÑO | E89: COSTURA | F89: Proceso | I89: 3500 | J89: 0.875 | K89: FRA MUSE MICR!G54
A90: 10 | B90: FRA MUSE MICR | C90: MICRO DAMA | D90: MICRO NIÑO | E90: DISEÑO | F90: Proceso | I90: 0 | J90: 0 | K90: FRA MUSE MICR!G55
A91: 10 | B91: FRA MUSE MICR | C91: MICRO DAMA | D91: MICRO NIÑO | E91: PLANCHA | F91: Proceso | I91: 1000 | J91: 0.25 | K91: FRA MUSE MICR!G56
A92: 10 | B92: FRA MUSE MICR | C92: MICRO DAMA | D92: MICRO NIÑO | E92: VINIL 15 CMS | F92: Tecnica | I92: 8000 | J92: 2 | K92: FRA MUSE MICR!G57
A93: 10 | B93: FRA MUSE MICR | C93: MICRO DAMA | D93: MICRO NIÑO | E93: CORTE DEL PLOTTER | F93: Tecnica | I93: 0 | J93: 0 | K93: FRA MUSE MICR!G58
A94: 10 | B94: FRA MUSE MICR | C94: MICRO DAMA | D94: MICRO NIÑO | E94: DEPILADA | F94: Proceso | I94: 0 | J94: 0 | K94: FRA MUSE MICR!G59
A95: 10 | B95: FRA MUSE MICR | C95: MICRO DAMA | D95: MICRO NIÑO | E95: ETIQUETA | F95: Insumo | I95: 200 | J95: 0.05 | K95: FRA MUSE MICR!G60
A96: 10 | B96: FRA MUSE MICR | C96: MICRO DAMA | D96: MICRO NIÑO | E96: BOLSA | F96: Insumo | I96: 500 | J96: 0.125 | K96: FRA MUSE MICR!G61
A97: 10 | B97: FRA MUSE MICR | C97: MICRO DAMA | D97: MICRO NIÑO | E97: HILO | F97: Insumo | I97: 250 | J97: 0.0625 | K97: FRA MUSE MICR!G62 | L97: fx: G46
A98: 10 | B98: FRA MUSE MICR | C98: MICRO DAMA | D98: MICRO NIÑO | E98: MARQUILLA | F98: Insumo | I98: 100 | J98: 0.025 | K98: FRA MUSE MICR!G63
A99: 10 | B99: FRA MUSE MICR | C99: MICRO DAMA | D99: MICRO NIÑO | E99: GASTOS OPERATIVOS | F99: Indirecto | I99: 3700 | J99: 0.925 | K99: FRA MUSE MICR!G64
A100: 11 | B100: FRA MUSE MICR | C100: MUSE CABALLERO | D100: MUSE CABALLERO | E100: TELA | F100: Insumo | G100: 0.9 | H100: 1.1 | I100: 3960 | J100: 0.99 | K100: FRA MUSE MICR!B68 | L100: fx: 0.9*1.1*E2
...

Sheet M_Escalas
A1: id_receta | B1: hoja | C1: bloque | D1: escala | E1: factor | F1: costo_usd | G1: precio_usd | H1: celda | I1: clave
A2: 1 | B2: FRA MUSE MICR | C2: MUSELINA DAMA | D2: +5 DOC | E2: 1.4 | F2: 3.6525 | G2: 5.1135 | H2: C8 | I2: =A2&"|"&TRIM(D2) -> 1|+5 DOC
A3: 1 | B3: FRA MUSE MICR | C3: MUSELINA DAMA | D3: 1 A 5 DOC | E3: 1.6 | F3: 3.6525 | G3: 5.844 | H3: D8 | I3: =A3&"|"&TRIM(D3) -> 1|1 A 5 DOC
A4: 1 | B4: FRA MUSE MICR | C4: MUSELINA DAMA | D4: DETAL | E4: 1.99 | F4: 3.6525 | G4: 7.268475 | H4: E8 | I4: =A4&"|"&TRIM(D4) -> 1|DETAL
A5: 2 | B5: FRA MUSE MICR | C5: MICRO DAMA | D5: +5 DOC | E5: 1.3 | F5: 4.4125 | G5: 5.73625 | H5: H8 | I5: =A5&"|"&TRIM(D5) -> 2|+5 DOC
A6: 2 | B6: FRA MUSE MICR | C6: MICRO DAMA | D6: 1 A 5 DOC | E6: 1.5 | F6: 4.4125 | G6: 6.61875 | H6: I8 | I6: =A6&"|"&TRIM(D6) -> 2|1 A 5 DOC
A7: 2 | B7: FRA MUSE MICR | C7: MICRO DAMA | D7: DETAL | E7: 1.7 | F7: 4.4125 | G7: 7.50125 | H7: J8 | I7: =A7&"|"&TRIM(D7) -> 2|DETAL
A8: 3 | B8: FRA MUSE MICR | C8: MUSELINA NIÑO | D8: +5 DOC | E8: 1.3 | F8: 1.5775 | G8: 2.05075 | H8: C17 | I8: =A8&"|"&TRIM(D8) -> 3|+5 DOC
A9: 3 | B9: FRA MUSE MICR | C9: MUSELINA NIÑO | D9: 1 A 5 DOC | E9: 1.5 | F9: 1.5775 | G9: 2.36625 | H9: D17 | I9: =A9&"|"&TRIM(D9) -> 3|1 A 5 DOC
A10: 3 | B10: FRA MUSE MICR | C10: MUSELINA NIÑO | D10: DETAL | E10: 1.99 | F10: 1.5775 | G10: 3.139225 | H10: E17 | I10: =A10&"|"&TRIM(D10) -> 3|DETAL
A11: 4 | B11: FRA MUSE MICR | C11: MICRO NIÑO | D11: +5 DOC | E11: 1.4 | F11: 3.9875 | G11: 5.5825 | H11: H17 | I11: =A11&"|"&TRIM(D11) -> 4|+5 DOC
A12: 4 | B12: FRA MUSE MICR | C12: MICRO NIÑO | D12: 1 A 5 DOC | E12: 1.6 | F12: 3.9875 | G12: 6.38 | H12: I17 | I12: =A12&"|"&TRIM(D12) -> 4|1 A 5 DOC
A13: 4 | B13: FRA MUSE MICR | C13: MICRO NIÑO | D13: DETAL | E13: 1.99 | F13: 3.9875 | G13: 7.935125 | H13: J17 | I13: =A13&"|"&TRIM(D13) -> 4|DETAL
... A706: 236 | B706: TOP DAMA | C706: CABALLERO | D706: DETAL | E706: 1.99 | F706: 3.4888889 | G706: 6.9428889 | H706: M39 | I706: =A706&"|"&TRIM(D706) -> 236|DETAL

Sheet M_Insumos
A1: insumo | B1: costo_local | C1: tasa | D1: costo_usd | E1: origen
A2: TELA | B2: 7360 | C2: 4000 | D2: 1.84 | E2: FRA MUSE MICR!B4
A3: TELA | B3: 6400 | C3: 4000 | D3: 1.6 | E3: FRA MUSE MICR!G4
A4: TELA | B4: 1560 | C4: 4000 | D4: 0.39 | E4: FRA MUSE MICR!B14
A5: TELA | B5: 4800 | C5: 4000 | D5: 1.2 | E5: FRA MUSE MICR!G14
A6: TELA | B6: 5400 | C6: 4000 | D6: 1.35 | E6: FRA MUSE MICR!B24
A7: TELA | B7: 9200 | C7: 4000 | D7: 2.3 | E7: FRA MUSE MICR!G24
A8: TELA | B8: 5760 | C8: 4000 | D8: 1.44 | E8: FRA MUSE MICR!G37
A9: TELA | B9: 7360 | C9: 4000 | D9: 1.84 | E9: FRA MUSE MICR!B52
A10: TELA | B10: 4800 | C10: 4000 | D10: 1.2 | E10: FRA MUSE MICR!G52
A11: TELA | B11: 3960 | C11: 4000 | D11: 0.99 | E11: FRA MUSE MICR!B68
A12: TELA | B12: 6400 | C12: 4000 | D12: 1.6 | E12: FRA MUSE MICR!G68
A13: TELA | B13: 4480 | C13: 4000 | D13: 1.12 | E13: FRA MUSE MICR!B86
... A1140: TELA TULL | B1140: 12150 | C1140: 4500 | D1140: 2.7 | E1140: TUTU !B8

Sheet M_Procesos
A1: proceso | B1: tarifa_local | C1: tasa | D1: tarifa_usd | E1: origen
A2: CORTE | B2: 700 | C2: 4000 | D2: 0.175 | E2: FRA MUSE MICR!B5
A3: CORTE | B3: 700 | C3: 4000 | D3: 0.175 | E3: FRA MUSE MICR!G5
A4: CORTE | B4: 500 | C4: 4000 | D4: 0.125 | E4: FRA MUSE MICR!B15
A5: CORTE | B5: 700 | C5: 4000 | D5: 0.175 | E5: FRA MUSE MICR!G15
A6: CORTE | B6: 300 | C6: 4000 | D6: 0.075 | E6: FRA MUSE MICR!B25
A7: CORTE | B7: 700 | C7: 4000 | D7: 0.175 | E7: FRA MUSE MICR!G25
A8: CORTE | B8: 700 | C8: 4000 | D8: 0.175 | E8: FRA MUSE MICR!B38
A9: CORTE | B9: 700 | C9: 4000 | D9: 0.175 | E9: FRA MUSE MICR!G38
A10: CORTE | B10: 700 | C10: 4000 | D10: 0.175 | E10: FRA MUSE MICR!B53
A11: CORTE | B11: 700 | C11: 4000 | D11: 0.175 | E11: FRA MUSE MICR!G53
A12: CORTE | B12: 700 | C12: 4000 | D12: 0.175 | E12: FRA MUSE MICR!B69
A13: CORTE | B13: 700 | C13: 4000 | D13: 0.175 | E13: FRA MUSE MICR!G69
... A1176: DIGITALIZACION | B1176: 3000 | C1176: 4000 | D1176: 0.75 | E1176: CAMISAS !R11

Sheet Anomalias
A1: tipo | B1: hoja | C1: celda | D1: detalle | E1: bloque | F1: gravedad
A2: a) Tasa incrustada distinta | B2: FRA MUSE MICR | C2: G111 | D2: 3800 vs tasa 4000 | E2: MICRO CABALLERO | F2: ALTA
A3: a) Tasa incrustada distinta | B3: FRA MUSE MICR | C3: G253 | D3: 8500 vs tasa 4000 | E3: CABALLERO | F3: ALTA
A4: a) Tasa incrustada distinta | B4: BUZO | C4: J45 | D4: 9500 vs tasa 4000 | E4: BUZO CABALLERO | F4: ALTA
A5: a) Tasa incrustada distinta | B5: CV TASLAN | C5: Y28 | D5: 3700 vs tasa 3900 | E5: CORTA VIENTO CABALLERO | F5: ALTA
A6: a) Tasa incrustada distinta | B6: CV MEMORY | C6: B24 | D6: 3500 vs tasa 4000 | E6: CORTA VIENTO NIÑO | F6: ALTA
A7: a) Tasa incrustada distinta | B7: CV MEMORY | C7: B25 | D7: 6000 vs tasa 4000 | E7: CORTA VIENTO NIÑO | F7: ALTA
A8: a) Tasa incrustada distinta | B8: KSAKAS | C8: B23 | D8: 8500 vs tasa 4000 | E8: KASAKAS SUBLIMACION TOTAL | F8: ALTA
A9: a) Tasa incrustada distinta | B9: UNI FUTBOL | C9: B7 | D9: 8500 vs tasa 4000 | E9: MUSELINA | F9: ALTA
A10: a) Tasa incrustada distinta | B10: UNI FUTBOL | C10: B50 | D10: 9500 vs tasa 4000 | E10: MUSELINA | F10: ALTA
A11: a) Tasa incrustada distinta | B11: UNI FUTBOL | C11: J87 | D11: 4000 vs tasa 3800 | E11: NIÑO | F11: ALTA
A12: a) Tasa incrustada distinta | B12: UNI FUTBOL | C12: J125 | D12: 3800 vs tasa 4000 | E12: CABALLERO | F12: ALTA
... A24: a) Tasa incrustada distinta | B24: FRANELILLAS | C24: B83 | D24: 3800 vs tasa 4000 | E24: MUSE | F24: ALTA
A25: g) Insumo con precios distintos | B25: FRA MUSE MICR | C25: TELA | D25: 104 valores: [840, 950, 1170, 1560, 1800, 2025] | F25: MEDIA
A26: g) Insumo con precios distintos | B26: FRA MUSE MICR | C26: ETIQUETA | D26: 12 valores: [50, 65, 80, 100, 132, 200] | F26: MEDIA
A27: g) Insumo con precios distintos | B27: FRA MUSE MICR | C27: BOLSA | D27: 8 valores: [50, 60, 100, 150, 500, 530] | F27: MEDIA
A28: g) Insumo con precios distintos | B28: FRA MUSE MICR | C28: MARQUILLA | D28: 14 valores: [50, 60, 70, 100, 200, 250] | F28: MEDIA
A29: g) Insumo con precios distintos | B29: FRA MUSE MICR | C29: HILO | D29: 7 valores: [100, 200, 250, 300, 350, 500] | F29: MEDIA
A30: g) Insumo con precios distintos | B30: CHALECOS | C30: CIERRE | D30: 9 valores: [1200, 1300, 1500, 1800, 2000, 2500] | F30: MEDIA
A31: g) Insumo con precios distintos | B31: HODDI MONO | C31: TELA MONO | D31: 11 valores: [7200.0, 7600, 13200.0, 13875, 15000, 16530] | F31: MEDIA
A32: g) Insumo con precios distintos | B32: SUETER | C32: TELA DE MONO | D32: 3 valores: [13680, 16720, 18240] | F32: MEDIA
A33: g) Insumo con precios distintos | B33: SHORT | C33: CAUCHO | D33: 10 valores: [200, 500, 600, 800, 1000, 1100] | F33: MEDIA
A34: g) Insumo con precios distintos | B34: CV TASLAN | C34: TELA TASLAN | D34: 7 valores: [12540.0, 17550, 18000, 20520, 20900, 28500] | F34: MEDIA
A35: g) Insumo con precios distintos | B35: CV MEMORY | C35: TELA MEMORY | D35: 5 valores: [8640, 11400, 12920, 13680, 15200] | F35: MEDIA
A36: g) Insumo con precios distintos | B36: KSAKAS | C36: TELA MALLA | D36: 2 valores: [2400, 2880] | F36: MEDIA
... A62: g) Proceso con precios distintos | B62: BOLSAS POP | C62: DTF | D62: 2 valores: [800, 1500] | F62: MEDIA

Sheet Indice
A1: id_receta | B1: hoja | C1: seccion_tecnica | D1: bloque_variante | E1: Etiqueta
A2: 1 | B2: FRA MUSE MICR | C2: MUSELINA DAMA | D2: MUSELINA DAMA | E2: =TRIM(B2)&" — "&TRIM(D2)&" [#"&A2&"]" -> FRA MUSE MICR — MUSELINA DAMA [#1]
A3: 2 | B3: FRA MUSE MICR | C3: MUSELINA DAMA | D3: MICRO DAMA | E3: =TRIM(B3)&" — "&TRIM(D3)&" [#"&A3&"]" -> FRA MUSE MICR — MICRO DAMA [#2]
A4: 3 | B4: FRA MUSE MICR | C4: MUSELINA NIÑO | D4: MUSELINA NIÑO | E4: =TRIM(B4)&" — "&TRIM(D4)&" [#"&A4&"]" -> FRA MUSE MICR — MUSELINA NIÑO [#3]
A5: 4 | B5: FRA MUSE MICR | C5: MUSELINA NIÑO | D5: MICRO NIÑO | E5: =TRIM(B5)&" — "&TRIM(D5)&" [#"&A5&"]" -> FRA MUSE MICR — MICRO NIÑO [#4]
A6: 5 | B6: FRA MUSE MICR | C6: MUSELINA CABALLERO | D6: MUSELINA CABALLERO | E6: =TRIM(B6)&" — "&TRIM(D6)&" [#"&A6&"]" -> FRA MUSE MICR — MUSELINA CABALLERO [#5]
A7: 6 | B7: FRA MUSE MICR | C7: MUSELINA CABALLERO | D7: MICRO CABALLERO | E7: =TRIM(B7)&" — "&TRIM(D7)&" [#"&A7&"]" -> FRA MUSE MICR — MICRO CABALLERO [#6]
A8: 7 | B8: FRA MUSE MICR | C8: MUSELINA DAMA | D8: MUSELINA DAMA | E8: =TRIM(B8)&" — "&TRIM(D8)&" [#"&A8&"]" -> FRA MUSE MICR — MUSELINA DAMA [#7]
A9: 8 | B9: FRA MUSE MICR | C9: MUSELINA DAMA | D9: MUSELINA NIÑO | E9: =TRIM(B9)&" — "&TRIM(D9)&" [#"&A9&"]" -> FRA MUSE MICR — MUSELINA NIÑO [#8]
A10: 9 | B10: FRA MUSE MICR | C10: MICRO DAMA | D10: MICRO DAMA | E10: =TRIM(B10)&" — "&TRIM(D10)&" [#"&A10&"]" -> FRA MUSE MICR — MICRO DAMA [#9]
A11: 10 | B11: FRA MUSE MICR | C11: MICRO DAMA | D11: MICRO NIÑO | E11: =TRIM(B11)&" — "&TRIM(D11)&" [#"&A11&"]" -> FRA MUSE MICR — MICRO NIÑO [#10]
A12: 11 | B12: FRA MUSE MICR | C12: MUSE CABALLERO | D12: MUSE CABALLERO | E12: =TRIM(B12)&" — "&TRIM(D12)&" [#"&A12&"]" -> FRA MUSE MICR — MUSE CABALLERO [#11]
A13: 12 | B13: FRA MUSE MICR | C13: MUSE CABALLERO | D13: MICRO CABALLERO | E13: =TRIM(B13)&" — "&TRIM(D13)&" [#"&A13&"]" -> FRA MUSE MICR — MICRO CABALLERO [#12]
... A75: 74 | B75: SUETER | C75: SUETER CABALLERO | D75: SUETER CABALLERO | E75: =TRIM(B75)&" — "&TRIM(D75)&" [#"&A75&"]" -> SUETER — SUETER CABALLERO [#74]
A76: 75 | B76: BUZO | D76: BUZO DAMA | E76: =TRIM(B76)&" — "&TRIM(D76)&" [#"&A76&"]" -> BUZO — BUZO DAMA [#75]
A77: 76 | B77: BUZO | D77: BUZO DAMA | E77: =TRIM(B77)&" — "&TRIM(D77)&" [#"&A77&"]" -> BUZO — BUZO DAMA [#76]
A78: 77 | B78: BUZO | D78: BUZO DAMA | E78: =TRIM(B78)&" — "&TRIM(D78)&" [#"&A78&"]" -> BUZO — BUZO DAMA [#77]
A79: 78 | B79: BUZO | D79: BUZO DAMA | E79: =TRIM(B79)&" — "&TRIM(D79)&" [#"&A79&"]" -> BUZO — BUZO DAMA [#78]
A80: 79 | B80: BUZO | D80: BUZO DAMA | E80: =TRIM(B80)&" — "&TRIM(D80)&" [#"&A80&"]" -> BUZO — BUZO DAMA [#79]
A81: 80 | B81: BUZO | D81: BUZO DAMA | E81: =TRIM(B81)&" — "&TRIM(D81)&" [#"&A81&"]" -> BUZO — BUZO DAMA [#80]
A82: 81 | B82: BUZO | D82: BUZO DAMA | E82: =TRIM(B82)&" — "&TRIM(D82)&" [#"&A82&"]" -> BUZO — BUZO DAMA [#81]
A83: 82 | B83: BUZO | D83: BUZO NIÑO | E83: =TRIM(B83)&" — "&TRIM(D83)&" [#"&A83&"]" -> BUZO — BUZO NIÑO [#82]
A84: 83 | B84: BUZO | D84: BUZO NIÑO | E84: =TRIM(B84)&" — "&TRIM(D84)&" [#"&A84&"]" -> BUZO — BUZO NIÑO [#83]
A85: 84 | B85: BUZO | D85: BUZO NIÑO | E85: =TRIM(B85)&" — "&TRIM(D85)&" [#"&A85&"]" -> BUZO — BUZO NIÑO [#84]
A86: 85 | B86: BUZO | D86: BUZO NIÑO | E86: =TRIM(B86)&" — "&TRIM(D86)&" [#"&A86&"]" -> BUZO — BUZO NIÑO [#85]
A87: 86 | B87: BUZO | D87: BUZO NIÑO | E87: =TRIM(B87)&" — "&TRIM(D87)&" [#"&A87&"]" -> BUZO — BUZO NIÑO [#86]
... A98: 97 | B98: SHORT | D98: SHORT NIÑO | E98: =TRIM(B98)&" — "&TRIM(D98)&" [#"&A98&"]" -> SHORT — SHORT NIÑO [#97]
A99: 98 | B99: SHORT | C99: GASTOS OPERATIVOS | D99: SHORT DAMA | E99: =TRIM(B99)&" — "&TRIM(D99)&" [#"&A99&"]" -> SHORT — SHORT DAMA [#98]
A100: 99 | B100: SHORT | C100: SHORT CABALLERO | D100: SHORT CABALLERO | E100: =TRIM(B100)&" — "&TRIM(D100)&" [#"&A100&"]" -> SHORT — SHORT CABALLERO [#99]
A101: 100 | B101: SHORT | C101: GASTOS OPERATIVOS | D101: SHORT NIÑO | E101: =TRIM(B101)&" — "&TRIM(D101)&" [#"&A101&"]" -> SHORT — SHORT NIÑO [#100]
A102: 101 | B102: SHORT | C102: GASTOS OPERATIVOS | D102: SHORT DAMA | E102: =TRIM(B102)&" — "&TRIM(D102)&" [#"&A102&"]" -> SHORT — SHORT DAMA [#101]
A103: 102 | B103: SHORT | C103: SHORT CABALLERO | D103: SHORT CABALLERO | E103: =TRIM(B103)&" — "&TRIM(D103)&" [#"&A103&"]" -> SHORT — SHORT CABALLERO [#102]
A104: 103 | B104: SHORT | C104: GASTOS OPERATIVOS | D104: SHORT NIÑO | E104: =TRIM(B104)&" — "&TRIM(D104)&" [#"&A104&"]" -> SHORT — SHORT NIÑO [#103]
A105: 104 | B105: SHORT | C105: GASTOS OPERATIVOS | D105: SHORT DAMA | E105: =TRIM(B105)&" — "&TRIM(D105)&" [#"&A105&"]" -> SHORT — SHORT DAMA [#104]
A106: 105 | B106: SHORT | C106: SHORT CABALLERO | D106: SHORT CABALLERO | E106: =TRIM(B106)&" — "&TRIM(D106)&" [#"&A106&"]" -> SHORT — SHORT CABALLERO [#105]
A107: 106 | B107: CV TASLAN | C107: CORTA VIENTO DAMA | D107: CORTA VIENTO DAMA | E107: =TRIM(B107)&" — "&TRIM(D107)&" [#"&A107&"]" -> CV TASLAN — CORTA VIENTO DAMA [#106]
A108: 107 | B108: CV TASLAN | C108: CORTA VIENTO DAMA | D108: CORTA VIENTO DAMA | E108: =TRIM(B108)&" — "&TRIM(D108)&" [#"&A108&"]" -> CV TASLAN — CORTA VIENTO DAMA [#107]
A109: 108 | B109: CV TASLAN | C109: CORTA VIENTO CABALLERO | D109: CORTA VIENTO CABALLERO | E109: =TRIM(B109)&" — "&TRIM(D109)&" [#"&A109&"]" -> CV TASLAN — CORTA VIENTO CABALLERO [#108]
A110: 109 | B110: CV TASLAN | C110: CORTA VIENTO CABALLERO | D110: CORTA VIENTO CABALLERO | E110: =TRIM(B110)&" — "&TRIM(D110)&" [#"&A110&"]" -> CV TASLAN — CORTA VIENTO CABALLERO [#109]
... A112: 111 | B112: CV TASLAN | C112: CORTA VIENTO CABALLERO | D112: PANTALON DE MONO | E112: =TRIM(B112)&" — "&TRIM(D112)&" [#"&A112&"]" -> CV TASLAN — PANTALON DE MONO [#111]
A113: 112 | B113: MOUSE | D113: MOUSE | E113: =TRIM(B113)&" — "&TRIM(D113)&" [#"&A113&"]" -> MOUSE — MOUSE [#112]
A114: 113 | B114: CV MEMORY | C114: CORTA VIENTO DAMA | D114: CORTA VIENTO DAMA | E114: =TRIM(B114)&" — "&TRIM(D114)&" [#"&A114&"]" -> CV MEMORY — CORTA VIENTO DAMA [#113]
A115: 114 | B115: CV MEMORY | C115: CORTA VIENTO DAMA | D115: DAMA | E115: =TRIM(B115)&" — "&TRIM(D115)&" [#"&A115&"]" -> CV MEMORY — DAMA [#114]
A116: 115 | B116: CV MEMORY | C116: CORTA VIENTO NIÑO | D116: CORTA VIENTO NIÑO | E116: =TRIM(B116)&" — "&TRIM(D116)&" [#"&A116&"]" -> CV MEMORY — CORTA VIENTO NIÑO [#115]
A117: 116 | B117: CV MEMORY | C117: CORTA VIENTO NIÑO | D117: CORTA VIENTO NIÑO | E117: =TRIM(B117)&" — "&TRIM(D117)&" [#"&A117&"]" -> CV MEMORY — CORTA VIENTO NIÑO [#116]
A118: 117 | B118: CV MEMORY | C118: CORTA VIENTO con Gorro CABALLERO | D118: CORTA VIENTO con Gorro CABALLERO | E118: =TRIM(B118)&" — "&TRIM(D118)&" [#"&A118&"]" -> CV MEMORY — CORTA VIENTO con Gorro CABALLERO [#117]
A119: 118 | B119: CV MEMORY | C119: CORTA VIENTO con Gorro CABALLERO | D119: CORTA VIENTO CABALLERO | E119: =TRIM(B119)&" — "&TRIM(D119)&" [#"&A119&"]" -> CV MEMORY — CORTA VIENTO CABALLERO [#118]
A120: 119 | B120: CV MEMORY | C120: CORTA VIENTO CABALLERO | D120: CORTA VIENTO CABALLERO | E120: =TRIM(B120)&" — "&TRIM(D120)&" [#"&A120&"]" -> CV MEMORY — CORTA VIENTO CABALLERO [#119]
A121: 120 | B121: CV MEMORY | C121: CORTA VIENTO CABALLERO | D121: CORTA VIENTO CABALLERO | E121: =TRIM(B121)&" — "&TRIM(D121)&" [#"&A121&"]" -> CV MEMORY — CORTA VIENTO CABALLERO [#120]
A122: 121 | B122: KSAKAS | C122: KASAKAS SOLO LOGO | D122: KASAKAS SOLO LOGO | E122: =TRIM(B122)&" — "&TRIM(D122)&" [#"&A122&"]" -> KSAKAS — KASAKAS SOLO LOGO [#121]
A123: 122 | B123: KSAKAS | C123: KASAKAS SUBLIMACION TOTAL | D123: KASAKAS SUBLIMACION TOTAL | E123: =TRIM(B123)&" — "&TRIM(D123)&" [#"&A123&"]" -> KSAKAS — KASAKAS SUBLIMACION TOTAL [#122]
A124: 123 | B124: F. SUBLIM 1,3 | D124: CABALLERO | E124: =TRIM(B124)&" — "&TRIM(D124)&" [#"&A124&"]" -> F. SUBLIM 1,3 — CABALLERO [#123]
A125: 124 | B125: F. SUBLIM 1,3 | D125: CABALLERO | E125: =TRIM(B125)&" — "&TRIM(D125)&" [#"&A125&"]" -> F. SUBLIM 1,3 — CABALLERO [#124]
A126: 125 | B126: F. SUBLIM 1,3 | C126: GASTOS OPERATIVOS | D126: DAMA | E126: =TRIM(B126)&" — "&TRIM(D126)&" [#"&A126&"]" -> F. SUBLIM 1,3 — DAMA [#125]
A127: 126 | B127: F. SUBLIM 1,3 | C127: GASTOS OPERATIVOS | D127: DAMA | E127: =TRIM(B127)&" — "&TRIM(D127)&" [#"&A127&"]" -> F. SUBLIM 1,3 — DAMA [#126]
A128: 127 | B128: UNI FUTBOL | C128: TALLAS 6-8-10-12 | D128: MUSELINA | E128: =TRIM(B128)&" — "&TRIM(D128)&" [#"&A128&"]" -> UNI FUTBOL — MUSELINA [#127]
A129: 128 | B129: UNI FUTBOL | C129: TALLAS 6-8-10-12 | D129: MUSELINA | E129: =TRIM(B129)&" — "&TRIM(D129)&" [#"&A129&"]" -> UNI FUTBOL — MUSELINA [#128]
A130: 129 | B130: UNI FUTBOL | C130: GASTOS OPERATIVOS | D130: MUSELINA | E130: =TRIM(B130)&" — "&TRIM(D130)&" [#"&A130&"]" -> UNI FUTBOL — MUSELINA [#129]
A131: 130 | B131: UNI FUTBOL | C131: GASTOS OPERATIVOS | D131: MUSELINA | E131: =TRIM(B131)&" — "&TRIM(D131)&" [#"&A131&"]" -> UNI FUTBOL — MUSELINA [#130]
A132: 131 | B132: UNI FUTBOL | C132: TALLAS 16-S-M | D132: MUSELINA | E132: =TRIM(B132)&" — "&TRIM(D132)&" [#"&A132&"]" -> UNI FUTBOL — MUSELINA [#131]
A133: 132 | B133: UNI FUTBOL | C133: GASTOS OPERATIVOS | D133: MUSELINA | E133: =TRIM(B133)&" — "&TRIM(D133)&" [#"&A133&"]" -> UNI FUTBOL — MUSELINA [#132]
A134: 133 | B134: UNI FUTBOL | C134: GASTOS OPERATIVOS | D134: SHORT NIÑO | E134: =TRIM(B134)&" — "&TRIM(D134)&" [#"&A134&"]" -> UNI FUTBOL — SHORT NIÑO [#133]
A135: 134 | B135: UNI FUTBOL | C135: GASTOS OPERATIVOS | D135: NIÑO | E135: =TRIM(B135)&" — "&TRIM(D135)&" [#"&A135&"]" -> UNI FUTBOL — NIÑO [#134]
A136: 135 | B136: UNI FUTBOL | C136: GASTOS OPERATIVOS | D136: Caballero | E136: =TRIM(B136)&" — "&TRIM(D136)&" [#"&A136&"]" -> UNI FUTBOL — Caballero [#135]
A137: 136 | B137: UNI FUTBOL | C137: GASTOS OPERATIVOS | D137: NIÑO/DAMA | E137: =TRIM(B137)&" — "&TRIM(D137)&" [#"&A137&"]" -> UNI FUTBOL — NIÑO/DAMA [#136]
... A140: 139 | B140: UNI FUTBOL | C140: GASTOS OPERATIVOS | D140: MUSE/ATLE | E140: =TRIM(B140)&" — "&TRIM(D140)&" [#"&A140&"]" -> UNI FUTBOL — MUSE/ATLE [#139]
A141: 140 | B141: FULL SUBLI | D141: MICRO DAMA | E141: =TRIM(B141)&" — "&TRIM(D141)&" [#"&A141&"]" -> FULL SUBLI — MICRO DAMA [#140]
A142: 141 | B142: FULL SUBLI | D142: MICRO NIÑO | E142: =TRIM(B142)&" — "&TRIM(D142)&" [#"&A142&"]" -> FULL SUBLI — MICRO NIÑO [#141]
A143: 142 | B143: FULL SUBLI | C143: MICRO CABALLERO | D143: MICRO CABALLERO | E143: =TRIM(B143)&" — "&TRIM(D143)&" [#"&A143&"]" -> FULL SUBLI — MICRO CABALLERO [#142]
A144: 143 | B144: FULL SUBLI | C144: GASTOS OPERATIVOS | D144: MUSELINA NIÑO | E144: =TRIM(B144)&" — "&TRIM(D144)&" [#"&A144&"]" -> FULL SUBLI — MUSELINA NIÑO [#143]
A145: 144 | B145: FULL SUBLI | C145: MUSELINA DAMA | D145: MUSELINA DAMA | E145: =TRIM(B145)&" — "&TRIM(D145)&" [#"&A145&"]" -> FULL SUBLI — MUSELINA DAMA [#144]
A146: 145 | B146: FULL SUBLI | C146: GASTOS OPERATIVOS | D146: CABALLERO | E146: =TRIM(B146)&" — "&TRIM(D146)&" [#"&A146&"]" -> FULL SUBLI — CABALLERO [#145]
A147: 146 | B147: LICRAS | C147: PANTALON LICRA | D147: NIÑO | E147: =TRIM(B147)&" — "&TRIM(D147)&" [#"&A147&"]" -> LICRAS — NIÑO [#146]
A148: 147 | B148: LICRAS | C148: PANTALON LICRA | D148: NIÑO | E148: =TRIM(B148)&" — "&TRIM(D148)&" [#"&A148&"]" -> LICRAS — NIÑO [#147]
A149: 148 | B149: LICRAS | C149: PANTALON LICRA | D149: NIÑO | E149: =TRIM(B149)&" — "&TRIM(D149)&" [#"&A149&"]" -> LICRAS — NIÑO [#148]
A150: 149 | B150: LICRAS | C150: GASTOS OPERATIVOS | D150: PANTALON LICRA | E150: =TRIM(B150)&" — "&TRIM(D150)&" [#"&A150&"]" -> LICRAS — PANTALON LICRA [#149]
A151: 150 | B151: LICRAS | C151: PANTALON LICRA | D151: PANTALON LICRA | E151: =TRIM(B151)&" — "&TRIM(D151)&" [#"&A151&"]" -> LICRAS — PANTALON LICRA [#150]
A152: 151 | B152: LICRAS | C152: GASTOS OPERATIVOS | D152: CABALLERO | E152: =TRIM(B152)&" — "&TRIM(D152)&" [#"&A152&"]" -> LICRAS — CABALLERO [#151]
A153: 152 | B153: LICRAS | C153: GASTOS OPERATIVOS | D153: NIÑO | E153: =TRIM(B153)&" — "&TRIM(D153)&" [#"&A153&"]" -> LICRAS — NIÑO [#152]
A154: 153 | B154: LICRAS | C154: GASTOS OPERATIVOS | D154: T8 A T16 | E154: =TRIM(B154)&" — "&TRIM(D154)&" [#"&A154&"]" -> LICRAS — T8 A T16 [#153]
... A163: 162 | B163: PIJAMAS | C163: niños pijama pantalon | D163: niños pijama pantalon | E163: =TRIM(B163)&" — "&TRIM(D163)&" [#"&A163&"]" -> PIJAMAS — niños pijama pantalon [#162]
A164: 163 | B164: CHEMIS | D164: DAMA | E164: =TRIM(B164)&" — "&TRIM(D164)&" [#"&A164&"]" -> CHEMIS — DAMA [#163]
A165: 164 | B165: CHEMIS | D165: NIÑO | E165: =TRIM(B165)&" — "&TRIM(D165)&" [#"&A165&"]" -> CHEMIS — NIÑO [#164]
A166: 165 | B166: CHEMIS | C166: GASTOS OPERATIVOS | D166: DAMA | E166: =TRIM(B166)&" — "&TRIM(D166)&" [#"&A166&"]" -> CHEMIS — DAMA [#165]
A167: 166 | B167: CHEMIS | C167: GASTOS OPERATIVOS | D167: NIÑO | E167: =TRIM(B167)&" — "&TRIM(D167)&" [#"&A167&"]" -> CHEMIS — NIÑO [#166]
A168: 167 | B168: CHEMIS | C168: GASTOS OPERATIVOS | D168: CABALLERO | E168: =TRIM(B168)&" — "&TRIM(D168)&" [#"&A168&"]" -> CHEMIS — CABALLERO [#167]
A169: 168 | B169: CHEMIS | C169: GASTOS OPERATIVOS | D169: CABALLERO | E169: =TRIM(B169)&" — "&TRIM(D169)&" [#"&A169&"]" -> CHEMIS — CABALLERO [#168]
A170: 169 | B170: CHEMIS | C170: GASTOS OPERATIVOS | D170: CABALLERO | E170: =TRIM(B170)&" — "&TRIM(D170)&" [#"&A170&"]" -> CHEMIS — CABALLERO [#169]
A171: 170 | B171: BEISBOL | D171: BEISBOL | E171: =TRIM(B171)&" — "&TRIM(D171)&" [#"&A171&"]" -> BEISBOL — BEISBOL [#170]
A172: 171 | B172: VELAS | C172: GASTOS OPERATIVOS | D172: VELAS | E172: =TRIM(B172)&" — "&TRIM(D172)&" [#"&A172&"]" -> VELAS — VELAS [#171]
A173: 172 | B173: BOLSAS POP | D173: BOLSAS POP | E173: =TRIM(B173)&" — "&TRIM(D173)&" [#"&A173&"]" -> BOLSAS POP — BOLSAS POP [#172]
A174: 173 | B174: CAMISAS | C174: CAMISA TIPO COLUMBIA MANGA CORTA | D174: CABALLERO | E174: =TRIM(B174)&" — "&TRIM(D174)&" [#"&A174&"]" -> CAMISAS — CABALLERO [#173]
A175: 174 | B175: CAMISAS | C175: CAMISA TIPO COLUMBIA MANGA CORTA | D175: CABALLERO | E175: =TRIM(B175)&" — "&TRIM(D175)&" [#"&A175&"]" -> CAMISAS — CABALLERO [#174]
A176: 175 | B176: CAMISAS | C176: CAMISA TIPO COLUMBIA MANGA CORTA | D176: CABALLERO | E176: =TRIM(B176)&" — "&TRIM(D176)&" [#"&A176&"]" -> CAMISAS — CABALLERO [#175]
A177: 176 | B177: CAMISAS | C177: CAMISA TIPO COLUMBIA MANGA CORTA | D177: CABALLERO | E177: =TRIM(B177)&" — "&TRIM(D177)&" [#"&A177&"]" -> CAMISAS — CABALLERO [#176]
A178: 177 | B178: CAMISAS | C178: CAMISA BASICA | D178: CABALLERO | E178: =TRIM(B178)&" — "&TRIM(D178)&" [#"&A178&"]" -> CAMISAS — CABALLERO [#177]
A179: 178 | B179: CAMISAS | C179: CAMISA BASICA | D179: CABALLERO | E179: =TRIM(B179)&" — "&TRIM(D179)&" [#"&A179&"]" -> CAMISAS — CABALLERO [#178]
A180: 179 | B180: CAMISAS | C180: CAMISA BASICA | D180: CABALLERO | E180: =TRIM(B180)&" — "&TRIM(D180)&" [#"&A180&"]" -> CAMISAS — CABALLERO [#179]
A181: 180 | B181: CAMISAS | C181: CAMISA BASICA SUBLIMADA TODA | D181: CAMISA BASICA SUBLIMADA TODA | E181: =TRIM(B181)&" — "&TRIM(D181)&" [#"&A181&"]" -> CAMISAS — CAMISA BASICA SUBLIMADA TODA [#180]
A182: 181 | B182: FILIPINA | C182: CAMISA BASICA SUBLIMADA TODA | D182: CAMISA BASICA SUBLIMADA TODA | E182: =TRIM(B182)&" — "&TRIM(D182)&" [#"&A182&"]" -> FILIPINA — CAMISA BASICA SUBLIMADA TODA [#181]
...
