Workbook

Sheet P COSTURA
A2: NJ STORE | F2: NJ SPORT
A3: DESCRIPCION | B3: UNIDAD | C3: DOCENA | D3: MAYOR | F3: DESCRIPCION | G3: UNIDAD | H3: DOCENA | I3: MAYOR
A4: CORTE | B4: 700 | C4: 500 | D4: 300 | F4: CORTE | G4: 700 | H4: 500 | I4: 300
A5: PLANCHADA | B5: 500 | C5: 400 | D5: 250 | F5: PLANCHADA | G5: 500 | H5: 400 | I5: 250
A7: COSTURA | B7: UNIDAD | C7: DOCENA | D7: MAYOR | F7: COSTURA | G7: UNIDAD | H7: DOCENA | I7: MAYOR
A8: FRANELA | B8: 3000 | C8: 2000 | D8: 1600 | F8: FRANELA | G8: 2500 | H8: 2000 | I8: 1600
A9: CHEMIS | B9: 5000 | C9: 4000 | D9: 2500 | F9: CHEMIS | G9: 3500 | H9: 3000 | I9: 2500 | L9: =2000*2000/4000 -> 1000
A10: CHEMIS CON UNIONES DE TELAS | B10: 8000 | C10: 7000 | D10: 6000
A11: SUETER CON GORRO | B11: 4500 | C11: 3000 | D11: 2500 | F11: SUETER CON GORRO | G11: 3500 | H11: 3000 | I11: 2500
A12: SUETER SIMPLE | B12: 4000 | C12: 3000 | D12: 2000 | F12: SUETER SIMPLE | G12: 3000 | H12: 2500 | I12: 2000
A13: SHORT | B13: 2500 | C13: 1800 | D13: 1200 | F13: SHORT | G13: 2000 | H13: 1800 | I13: 1200
A14: SHORT CON BOLSILLO | B14: 3000 | C14: 2500 | F14: MONO | G14: 4000 | H14: 3000 | I14: 2500
A15: MONO | B15: 5000 | C15: 4000 | D15: 2500 | F15: PORTA CANILLERAS C/ CORTE | G15: 1500 | H15: 1200 | I15: 900
A16: PORTA CANILLERAS C/ CORTE | B16: 2500 | C16: 1200 | D16: 900 | F16: FUNDA PORTA CANILLERA S/C | G16: 1500 | H16: 1200 | I16: 900
A17: FUNDA PORTA CANILLERA S/C | B17: 1500 | C17: 1200 | D17: 900 | F17: LICRA | G17: 3500 | H17: 3200 | I17: 2800
A18: LICRA | B18: 4000 | C18: 3200 | D18: 2800 | F18: VELAS | G18: 2500 | H18: 2200 | I18: 2000
A19: VELAS SENCILLA | B19: 3000 | C19: 2200 | D19: 2000 | F19: PROTECTORES ARQUEROS | G19: 1000 | H19: 900 | I19: 700
A20: PROTECTORES ARQUEROS | B20: 1000 | C20: 900 | D20: 700 | F20: WALL MEDIA | G20: 4500 | H20: 4300 | I20: 4000
A21: WALL MEDIA | B21: 4500 | C21: 4000 | D21: 4000 | F21: BOLSA DE ARENA | G21: 1500 | H21: 1300 | I21: 1100
A22: BOLSA DE ARENA | B22: 1500 | C22: 1300 | D22: 1100 | F22: TOP DAMA | G22: 3000 | H22: 2500 | I22: 2000
A23: TOP DAMA | B23: 3000 | C23: 2500 | D23: 2000 | F23: CHALECOS CON BOLSILLOS | G23: 4000 | H23: 3500 | I23: 3000
A24: CHALECOS CON BOLSILLOS | B24: 4000 | C24: 3500 | D24: 3000 | F24: COJINES | G24: 2000 | H24: 1800 | I24: 1500
A25: COJINES | B25: 2000 | C25: 1800 | D25: 1500 | F25: CHAQUETAS SENCILLAS | G25: 4000 | H25: 3500 | I25: 3000
A26: CHAQUETAS SENCILLAS | B26: 4000 | C26: 3500 | D26: 3000 | F26: CHAQUETAS FORRADAS | G26: 6000 | H26: 5500 | I26: 5000
... A28: QUIRURGICOS CORTE | B28: 1400 | C28: 1200 | D28: 1000 | F28: QUIRURGICOS COSTURA | G28: 6000 | H28: 5000 | I28: 4500
A29: QUIRURGICOS COSTURA | B29: 6000 | C29: 5000 | D29: 4500
A30: FALDA SHORT CON BOLSILLO | B30: 5000 | C30: 4000 | D30: 3500
A31: FALDA SHORT | B31: 4000 | C31: 3500 | D31: 3000
A32: BUZOS | B32: 3500 | C32: 2500
A33: CAMISAS

Sheet COJINES
A1: COJINES
F2: 3800
A3: TELA | B3: =7/12*F2 -> 2216.6667
A4: CORTE | B4: 500
A5: COSTURA | B5: 2000 | D5: tulas con delantero sublimado
A6: SUBLIMACION | B6: =13000/12 -> 1083.3333
A7: PLANCHA | B7: 500 | D7: +5 DOC | E7: 1 A 5 DOC | F7: DETAL
A8: DISEÑO | B8: 1000 | D8: =D13 -> 4.4333333 | E8: =E13 -> 5.5416667 | F8: =F13 -> 6.3016667
A9: TELA PELUCHE | B9: =5/12*F2 -> 1583.3333
A10: CINTA DE MARCA | B10: 300
A11: ETIQUETA | B11: 500
B12: 0 | D12: 0.4 | E12: 0.6 | F12: 0.9
A13: HILO | B13: =350 -> 350 | D13: =B15*1.4/F2 -> 4.4333333 | E13: =B15*1.75/F2 -> 5.5416667 | F13: =B15*1.99/F2 -> 6.3016667
A14: GASTOS OPERATIVOS | B14: =2000 -> 2000
B15: =SUM(B3:B14) -> 12033.333

Sheet FRA MUSE MICR
A1: FRANELAS EN BLANCO
E2: 4000
A3: MUSELINA DAMA | F3: MICRO DAMA
A4: TELA | B4: =0.8*2.3*E2 -> 7360 | F4: TELA | G4: =0.8*2*E2 -> 6400
A5: CORTE | B5: 700 | F5: CORTE | G5: 700
A6: COSTURA | B6: 2500 | C6: +5 DOC | D6: 1 A 5 DOC | E6: DETAL | F6: COSTURA | G6: 2500 | H6: +5 DOC | I6: 1 A 5 DOC | J6: DETAL
A7: ETIQUETA | B7: 200 | C7: 30 | D7: 50 | E7: 99 | F7: ETIQUETA | G7: 200 | H7: 40 | I7: 60 | J7: 99
A8: BOLSA | B8: 100 | C8: =B12*1.4 -> 5.1135 | D8: =B12*1.6 -> 5.844 | E8: =B12*1.99 -> 7.268475 | F8: BOLSA | G8: 3000 | H8: =G12*1.3 -> 5.73625 | I8: =G12*1.5 -> 6.61875 | J8: =G12*1.7 -> 7.50125
A9: MARQUILLA | B9: 500 | F9: MARQUILLA | G9: 500 | H9: =H8*3800 -> 21797.75 | I9: =I8*3800 -> 25151.25 | J9: =J8*3800 -> 28504.75
A10: HILO | B10: 250 | F10: HILO | G10: 350
A11: GASTOS OPERATIVOS | B11: 3000 | F11: GASTOS OPERATIVOS | G11: 4000
B12: =SUM(B4:B11)/E2 -> 3.6525 | G12: =SUM(G4:G11)/E2 -> 4.4125
A13: MUSELINA NIÑO | F13: MICRO NIÑO
A14: TELA | B14: =0.3*1.3*E2 -> 1560 | F14: TELA | G14: =0.6*2*E2 -> 4800
A15: CORTE | B15: 500 | C15: +5 DOC | D15: 1 A 5 DOC | E15: DETAL | F15: CORTE | G15: 700 | H15: +5 DOC | I15: 1 A 5 DOC | J15: DETAL
A16: COSTURA | B16: 2000 | C16: 30 | D16: 50 | E16: 99 | F16: COSTURA | G16: 3000 | H16: 30 | I16: 50 | J16: 99
A17: ETIQUETA | B17: 0 | C17: =B22*1.3 -> 2.05075 | D17: =B22*1.5 -> 2.36625 | E17: =B22*1.99 -> 3.139225 | F17: ETIQUETA | G17: =0.6*12000 -> 7200 | H17: =G22*1.4 -> 5.5825 | I17: =G22*1.6 -> 6.38 | J17: =G22*1.99 -> 7.935125
A18: BOLSA | B18: 0 | F18: BOLSA | G18: 0
A19: MARQUILLA | B19: 0 | F19: MARQUILLA | G19: 0
A20: HILO | B20: 250 | F20: HILO | G20: 250
A21: GASTOS OPERATIVOS | B21: 2000 | F21: GASTOS OPERATIVOS | G21: 0
B22: =SUM(B14:B21)/E2 -> 1.5775 | G22: =SUM(G14:G21)/E2 -> 3.9875
A23: MUSELINA CABALLERO | F23: MICRO CABALLERO
A24: TELA | B24: =0.9*1.5*E2 -> 5400 | F24: TELA | G24: =1*2.3*E2 -> 9200 | H24: =400*3700/G24 -> 160.86957
A25: CORTE | B25: 300 | C25: +5 DOC | D25: 1 A 5 DOC | E25: DETAL | F25: CORTE | G25: 700 | H25: +5 DOC | I25: 1 A 5 DOC | J25: DETAL
A26: COSTURA | B26: 1800 | C26: 30 | D26: 50 | E26: 99 | F26: COSTURA | G26: 3500 | H26: 40 | I26: 60 | J26: 99
A27: BORDADO | B27: 2500 | C27: =B32*1.4 -> 3.9725 | D27: =B32*1.6 -> 4.54 | E27: =B32*1.99 -> 5.646625 | F27: MARQUILLA | G27: 200 | H27: =G32*1.3 -> 8.10875 | I27: =G32*1.7 -> 10.60375 | J27: =G32*1.9 -> 11.85125
A28: ETIQUETA | B28: 50 | E28: *0 | F28: ETIQUETA | G28: 100 | H28: =H27*3800 -> 30813.25 | I28: =I27*3800 -> 40294.25 | J28: =J27*3800 -> 45034.75
A29: BOLSA | B29: 50 | F29: BOLSA | G29: =11000 -> 11000
A30: HILO | B30: =B20 -> 250 | F30: HILO | G30: =B30 -> 250
A31: GASTOS OPERATIVOS | B31: 1000 | F31: GASTOS OPERATIVOS | G31: 0
B32: =SUM(B24:B31)/E2 -> 2.8375 | G32: =SUM(G24:G31)/E2 -> 6.2375
A35: REPLICA DE MARCAS VINIL MEDIANO/PÑO
A36: MUSELINA DAMA | F36: MUSELINA NIÑO
A37: TELA | B37: 0 | F37: TELA | G37: =0.8*1.8*4000 -> 5760
A38: CORTE | B38: 700 | F38: CORTE | G38: 700
A39: COSTURA | B39: 2500 | F39: COSTURA | G39: 3500
A40: PLANCHA | B40: 1000 | F40: PLANCHA | G40: 1000
A41: VINIL 15 CMS | B41: 5000 | F41: VINIL 15 CMS | G41: 700
A42: CORTE DEL PLOTTER | B42: 200 | C42: +5 DOC | D42: 1 A 5 DOC | E42: DETAL | F42: CORTE DEL PLOTTER | G42: 0 | H42: +5 DOC | I42: 1 A 5 DOC | J42: DETAL
A43: DEPILADA | B43: 500 | C43: 30 | D43: 50 | E43: 99 | F43: DEPILADA | G43: 0 | H43: 30 | I43: 50 | J43: 99
A44: ETIQUETA | B44: 200 | C44: =B49*1.35 -> 4.910625 | D44: =B49*1.65 -> 6.001875 | E44: =B49*1.99 -> 7.238625 | F44: ETIQUETA | G44: 50 | H44: =G49*1.5 -> 6.04125 | I44: =G49*1.65 -> 6.645375 | J44: =G49*1.9 -> 7.65225
A45: BOLSA | B45: 100 | F45: BOLSA | G45: 100
A46: HILO | B46: 250 | F46: HILO | G46: 250
A47: MARQUILLA | B47: 100 | F47: MARQUILLA | G47: 50
A48: GASTOS OPERATIVOS | B48: 4000 | F48: GASTOS OPERATIVOS | G48: 4000
B49: =SUM(B37:B48)/E2 -> 3.6375 | G49: =SUM(G37:G48)/E2 -> 4.0275
A51: MICRO DAMA | F51: MICRO NIÑO
A52: TELA | B52: =0.8*2.3*E2 -> 7360 | F52: TELA | G52: =0.6*2*E2 -> 4800
A53: CORTE | B53: 700 | F53: CORTE | G53: 700
A54: COSTURA | B54: 2500 | F54: COSTURA | G54: 3500
A55: DISEÑO | B55: 1000 | F55: DISEÑO | G55: 0
A56: PLANCHA | B56: 0 | F56: PLANCHA | G56: 1000
A57: VINIL 15 CMS | B57: 3000 | F57: VINIL 15 CMS | G57: 8000
A58: CORTE DEL PLOTTER | B58: 200 | C58: +5 DOC | D58: 1 A 5 DOC | E58: DETAL | F58: CORTE DEL PLOTTER | G58: 0 | H58: +5 DOC | I58: 1 A 5 DOC | J58: DETAL
A59: DEPILADA | B59: 200 | C59: 30 | D59: 50 | E59: 99 | F59: DEPILADA | G59: 0 | H59: 30 | I59: 50 | J59: 0.85
A60: ETIQUETA | B60: 100 | C60: =B65*1.45 -> 7.108625 | D60: =B65*1.7 -> 8.33425 | E60: =B65*1.99 -> 9.755975 | F60: ETIQUETA | G60: 200 | H60: =G65*1.3 -> 7.39375 | I60: =G65*1.5 -> 8.53125 | J60: =G65*1.99 -> 11.318125
A61: BOLSA | B61: 100 | D61: =D60*3900 -> 32503.575 | F61: BOLSA | G61: 500
A62: HILO | B62: =B46 -> 250 | F62: HILO | G62: =G46 -> 250
A63: MARQUILLA | B63: 500 | F63: MARQUILLA | G63: 100
A64: GASTOS OPERATIVOS | B64: 3700 | F64: GASTOS OPERATIVOS | G64: 3700
B65: =SUM(B52:B64)/E2 -> 4.9025 | G65: =SUM(G52:G64)/E2 -> 5.6875
A67: MUSE CABALLERO | F67: MICRO CABALLERO
A68: TELA | B68: =0.9*1.1*E2 -> 3960 | F68: TELA | G68: =0.8*2*4000 -> 6400
A69: CORTE | B69: 700 | F69: CORTE | G69: 700
A70: COSTURA | B70: 2500 | F70: COSTURA | G70: 3500
A71: PLANCHA | B71: 1500 | F71: VINIL | G71: 10000
A72: VINIL 15 CMS | B72: 1500 | F72: PLANCHA | G72: 1000
A73: CORTE DEL PLOTTER | B73: 200 | C73: +5 DOC | D73: 1 A 5 DOC | E73: DETAL | F73: CORTE DEL PLOTTER | G73: 0 | H73: +5 DOC | I73: 1 A 5 DOC | J73: DETAL
A74: DEPILADA | B74: 200 | C74: 30 | D74: 50 | E74: 99 | F74: DEPILADA | G74: 0 | H74: 30 | I74: 50 | J74: 99
A75: ETIQUETA | B75: 200 | C75: =B80*1.5 -> 5.31 | D75: =B80*1.6 -> 5.664 | E75: =B80*1.99 -> 7.0446 | F75: ETIQUETA | G75: 50 | H75: =G80*1.35 -> 8.8425 | I75: =G80*1.65 -> 10.8075 | J75: =G80*1.9 -> 12.445
A76: BOLSA | B76: 100 | F76: BOLSA | G76: 500
A77: HILO | B77: 250 | D77: MAS DE 20 | E77: MAS DE 40 | F77: HILO | G77: 250
A78: MARQUILLA | B78: 50 | C78: FRANELAS DAMAS | D78: 10 | E78: 9 | F78: MARQUILLA | G78: 100
A79: GASTOS OPERATIVOS | B79: 3000 | C79: FRANELAS CAB. | F79: GASTOS OPERATIVOS | G79: 3700
B80: =SUM(B68:B79)/E2 -> 3.54 | G80: =SUM(G68:G79)/E2 -> 6.55
A84: SUBLIMACION TAMAÑO CARTA Y VINIL
A85: MUSELINA DAMA | F85: MUSELINA NIÑO
A86: TELA | B86: =0.7*1.6*E2 -> 4480 | F86: TELA | G86: =0.5*1.6*E2 -> 3200
A87: CORTE | B87: 300 | F87: CORTE | G87: 300
A88: COSTURA | B88: 1600 | F88: COSTURA | G88: 1600
A89: SUBLIMACION CARTA | B89: =13000/15 -> 866.66667 | F89: SUBLIMACION CARTA | G89: =B89 -> 866.66667
A90: PLANCHA | B90: 500 | C90: +5 DOC | D90: 1 A 5 DOC | E90: DETAL | F90: PLANCHA | G90: =B90 -> 500 | H90: +5 DOC | I90: 1 A 5 DOC | J90: DETAL
A91: ETIQUETA | B91: 200 | C91: 0.4 | D91: 0.55 | E91: 0.85 | F91: ETIQUETA | G91: 200 | H91: 0.4 | I91: 0.55 | J91: 0.85
A92: VINIL | B92: =30000/39 -> 769.23077 | C92: =B96*1.45 -> 4.1926378 | D92: =B96*1.75 -> 5.0600801 | E92: =B96*1.99 -> 5.754034 | F92: VINIL | G92: =B92 -> 769.23077 | H92: =G96*1.45 -> 3.7286378 | I92: =G96*1.75 -> 4.5000801 | J92: =G96*1.99 -> 5.117234
A93: MARQUILLA | B93: 500 | F93: MARQUILLA | G93: 500
A94: HILO | B94: 350 | F94: HILO | G94: 350
A95: GASTOS OPERATIVOS | B95: 2000 | F95: GASTOS OPERATIVOS | G95: 2000
B96: =SUM(B86:B95)/E2 -> 2.8914744 | G96: =SUM(G86:G95)/E2 -> 2.5714744
A97: micro DAMA | C97: FRANELAS | F97: micro NIÑO | H97: FRANELAS
A98: TELA | B98: =0.6*1.8*E2 -> 4320 | F98: TELA | G98: =0.7*2.65*E2 -> 7420
A99: CORTE | B99: 700 | F99: CORTE | G99: 300
A100: COSTURA | B100: 2500 | F100: COSTURA | G100: 1600
A101: SUBLIMACION CARTA | B101: =4000 -> 4000 | F101: SUBLIMACION CARTA | G101: =B89 -> 866.66667
A102: DISEÑO | B102: 0 | C102: +5 DOC | D102: 1 A 5 DOC | E102: DETAL | F102: DISEÑO | G102: 0 | H102: +5 DOC | I102: 1 A 5 DOC | J102: DETAL
A103: PLANCHA | B103: 1000 | C103: 0.4 | D103: 0.55 | E103: 0.85 | F103: PLANCHA | G103: =B90 -> 500 | H103: 0.4 | I103: 0.55 | J103: 0.85
A104: ETIQUETA | B104: 200 | C104: =B109*1.45 -> 6.6479712 | D104: =B109*1.75 -> 8.0234135 | E104: =B109*1.99 -> 9.1237673 | F104: ETIQUETA | G104: 200 | H104: =G109*1.45 -> 5.2583878 | I104: =G109*1.75 -> 6.3463301 | J104: =G109*1.99 -> 7.216684
A105: VINIL | B105: =B92 -> 769.23077 | F105: VINIL | G105: =B92 -> 769.23077
A106: MARQUILLA | B106: 500 | F106: MARQUILLA | G106: 500
A107: HILO | B107: 350 | F107: HILO | G107: 350
...

Sheet VESTIDO PROMOTORA
A2: LICRA UNICOLOR
A3: DAMA
A4: TELA | B4: =1.8*6*4000 -> 43200
A5: CORTE | B5: 2500
A6: COSTURA | B6: 12000
A7: PLANCHA | B7: 1250
A8: VINIL 15 CMS | B8: 2500 | D8: +5 DOC | E8: 1 A 5 DOC | F8: DETAL
A9: DISEÑO | B9: 1000 | D9: =D14 -> 24.269375 | E9: =E14 -> 26.78 | F9: =F14 -> 33.307625
A10: CORTE DEL PLOTTER | B10: 200
A11: DEPILADA | B11: 200
A12: ETIQUETA | B12: 0
A13: BOLSA | B13: 0 | D13: 0.4 | E13: 0.55 | F13: 0.85
A14: HILO | B14: 350 | D14: =B17*1.45 -> 24.269375 | E14: =B17*1.6 -> 26.78 | F14: =B17*1.99 -> 33.307625
A15: MARQUILLA | B15: 250
A16: GASTOS OPERATIVOS | B16: 3500
B17: =SUM(B4:B16)/4000 -> 16.7375
A19: LICRA SUBLIMADO
A20: DAMA
A21: TELA | B21: =1.8*6*4000 -> 43200
A22: CORTE | B22: 2500
A23: COSTURA | B23: 12000
A24: PLANCHA | B24: 1250
A25: SUBLIMACION | B25: =0.5*11000 -> 5500 | D25: +5 DOC | E25: 1 A 5 DOC | F25: DETAL
A26: DISEÑO | B26: 1000 | D26: =D31 -> 25.356875 | E26: =E31 -> 27.98 | F26: =F31 -> 34.800125
A27: CORTE DEL PLOTTER | B27: 200
A28: DEPILADA | B28: 200
A29: ETIQUETA | B29: 0
A30: BOLSA | B30: 0 | D30: 0.4 | E30: 0.55 | F30: 0.85
A31: HILO | B31: 350 | D31: =B34*1.45 -> 25.356875 | E31: =B34*1.6 -> 27.98 | F31: =B34*1.99 -> 34.800125
A32: MARQUILLA | B32: 250
A33: GASTOS OPERATIVOS | B33: 3500
B34: =SUM(B21:B33)/4000 -> 17.4875

Sheet WALL MEDIA 
A3: WALL 1*2 | J3: WALL 0,5*2
A4: 2 curvas pvc 3/4 (2700$) | B4: =2*2700 -> 5400 | F4: 4000 | G4: DÓLAR | J4: 2 curvas pvc 3/4 (2700$) | K4: =2*2700 -> 5400
A5: tubo pvc 3/4 5 mts (4,82m) 11$ | B5: =4.9*11/6*F4 -> 35933.333 | J5: tubo pvc 3/4 5 mts (4,47m) 11$ | K5: =4.5*11/6*3800 -> 31350
A6: tubo pvc caliente 1/2 x 50cm (5$) | B6: =0.5*5/3*F4 -> 3333.3333 | J6: tubo pvc caliente 1/2 x 50cm (5$) | K6: =0.5*5/3*3800 -> 3166.6667
A7: tubo aluminio 1/2*6cm (5$) | B7: =0.06*5/6*F4 -> 200 | E7: WALL 1*2 | J7: tubo aluminio 1/2*6cm (5$) | K7: =0.06*5/6*3800 -> 190
A8: tubo pvc 1/2 x 1,40cm (9$) | B8: =1.4*5/6*F4 -> 4666.6667 | D8: 50CMSX2MTS | J8: tubo pvc 1/2 x 0,9cm (9$) | K8: =0.9*5/6*3800 -> 2850
A9: goma pvc x 1 wall media | B9: =6*1/30*F4 -> 800 | J9: goma pvc x 1 wall media | K9: =6*1/30*3800 -> 760
A10: tees pvc 1/2 x 2 | B10: =2*2500 -> 5000 | D10: 35 | E10: 65 | F10: 99 | H10: COSTO | J10: tees pvc 1/2 x 2 | K10: =2*2500 -> 5000
A11: tubo base MT 24cm x2 | B11: =0.24*10/3*F4 -> 3200 | D11: =H11*1.35 -> 56.065263 | E11: =H11*1.65 -> 68.524211 | F11: =H11*1.8 -> 74.753684 | H11: =B27 -> 41.529825 | J11: tubo base MT 24cm x2 | K11: =0.24*10/3*3800 -> 3040
A12: tubo base x2 | B12: =2*3000 -> 6000 | J12: tubo base x2 | K12: =2*3000 -> 6000
A13: tornillos 9mm drywall x 8 | B13: =8*100 -> 800 | J13: tornillos 9mm drywall x 8 | K13: =8*100 -> 800
A14: pintura aerosol x 6 piezas GRIS | B14: =14000/3 -> 4666.6667 | J14: pintura aerosol x 6 piezas GRIS | K14: =14000/3 -> 4666.6667
A15: pintura aerosol x 2 piezas NEGRA | B15: =14000/6 -> 2333.3333 | J15: pintura aerosol x 2 piezas NEGRA | K15: =14000/6 -> 2333.3333
A16: MDF 9mm x 2 | B16: =1600*2 -> 3200 | E16: WALL 0,5*2 | J16: MDF 9mm x 2 | K16: =1600*2 -> 3200
A17: corte MDF x 2 | B17: 6000 | D17: 90CMS * 2MTS | J17: corte MDF x 2 | K17: 6000
A18: goma zapatera x 4 | B18: 500 | D18: 35 | E18: 65 | F18: 99 | H18: COSTO | J18: goma zapatera x 4 | K18: 500
A19: microporosa x 4 | B19: =250*4 -> 1000 | D19: =H19*1.35 -> 40.714816 | E19: =H19*1.65 -> 49.762553 | F19: =H19*1.8 -> 54.286421 | H19: =K27 -> 30.159123 | J19: microporosa x 4 | K19: =250*4 -> 1000
A20: tornillos aluminio x 2 | B20: 650*2 | J20: tornillos aluminio x 2 | K20: 650*2
A21: tela atletica trasera negra 53*220 | B21: =1.8*2.2*F4 -> 15840 | J21: tela atletica trasera negra 53*220 | K21: =1.8*2.2*3800/2 -> 7524
A22: tela atletica blanca 53*220 | B22: =2.2*1.8*F4 -> 15840 | J22: tela atletica blanca 53*220 | K22: =2.2*1.8*3800/2 -> 7524
A23: impresión y calandra 53*220 (18000$) | B23: =2.2*18000 -> 39600 | E23: PURA FUNDA IMPRESA 2*1 | J23: impresión y calandra 53*220 (18000$) | K23: =2.2*18000/2 -> 19800
A24: costura | B24: 2500 | F24: 35$ | J24: costura | K24: 2500
A25: cierre magico x1mts | B25: 1000 | J25: cierre magico x1mts | K25: 1000
A26: total | B26: =SUM(B4:B25) -> 157813.33 | C26: PESOS | J26: total | K26: =SUM(K4:K25) -> 114604.67 | L26: PESOS
B27: =B26/3800 -> 41.529825 | C27: DÓLAR | K27: =K26/3800 -> 30.159123 | L27: DÓLAR

Sheet WALL 
A1: WALL 1*2
A2: tela garbadina 4 mts | B2: =4*4.5 -> 18
A3: tela para patas | B3: =0.3*2 -> 0.6
A4: sublimacion 4 | B4: 0
A5: costura | B5: =8000/4000 -> 2
A6: corte | B6: =1000/4000 -> 0.25 | D6: DETAL | E6: MAYOR 12
D7: =B11*1.68 -> 35.028 | E7: =B11*1.35 -> 28.1475
A11: total | B11: =SUM(B2:B10) -> 20.85

Sheet LANYARD
A2: LANYARD
A3: CINTA | B3: 1000
A4: MOSQUETON | B4: 800
A5: CLIKCLAK | B5: 300
A6: SUBLIMACION | B6: =0.9*11000/11 -> 900
A7: PLANCHA | B7: 250
A8: CORTE | B8: 500
A9: HILO | B9: 250 | D9: 40% | E9: 65% | F9: 90%
A10: COSTURA | B10: 1500 | D10: =B12*1.4 -> 2.1875 | E10: =B12*1.65 -> 2.578125 | F10: =B12*1.99 -> 3.109375
A11: GASTOS OPERATIVOS | B11: 1750
B12: =SUM(B4:B11)/4000 -> 1.5625

Sheet franelas cucuta
D1: FRANELAS EN BLANCO
E2: 3800 | P2: FRANELAS EN BLANCO
A3: COTTONE DAMA | H3: COTTONE CABALLERO
A4: TELA | B4: =0.8*4.2*E2 -> 12768 | H4: TELA | I4: =1*4.2*E2 -> 15960 | O4: COTTONE DAMA | S4: COTTONE CABALLERO
A5: CORTE | B5: 500 | H5: CORTE | I5: 500 | O5: +5 DOC | P5: 1 A 5 DOC | Q5: DETAL | S5: +5 DOC | T5: 1 A 5 DOC | U5: DETAL
A6: COSTURA | B6: 2500 | H6: COSTURA | I6: 2500 | O6: 40 | P6: 60 | Q6: 99 | S6: 40 | T6: 60 | U6: 99
A7: ETIQUETA | B7: 250 | D7: +5 DOC | E7: 1 A 5 DOC | F7: DETAL | H7: ETIQUETA | I7: 250 | K7: +5 DOC | L7: 1 A 5 DOC | M7: DETAL | O7: =D9 -> 7.6882105 | P7: =E9 -> 8.7865263 | Q7: =F9 -> 10.928242 | S7: =K9 -> 8.8642105 | T7: =L9 -> 10.130526 | U7: =M9 -> 12.599842
A8: BOLSA | B8: 100 | D8: 40 | E8: 60 | F8: 99 | H8: BOLSA | I8: 100 | K8: 40 | L8: 60 | M8: 99
A9: MARQUILLA | B9: 500 | D9: =B12*1.4 -> 7.6882105 | E9: =B12*1.6 -> 8.7865263 | F9: =B12*1.99 -> 10.928242 | H9: MARQUILLA | I9: 500 | K9: =I12*1.4 -> 8.8642105 | L9: =I12*1.6 -> 10.130526 | M9: =I12*1.99 -> 12.599842 | O9: KEIRA PLUS DAMA | S9: KEIRA PLUS CABALLERO
A10: HILO | B10: 250 | H10: HILO | I10: =B10 -> 250 | O10: +5 DOC | P10: 1 A 5 DOC | Q10: DETAL | S10: +5 DOC | T10: 1 A 5 DOC | U10: DETAL
A11: GASTOS OPERATIVOS | B11: 4000 | H11: GASTOS OPERATIVOS | I11: =B11 -> 4000 | O11: 40 | P11: 60 | Q11: 99 | S11: 40 | T11: 60 | U11: 99
B12: =SUM(B4:B11)/E2 -> 5.4915789 | I12: =SUM(I4:I11)/E2 -> 6.3315789 | O12: =D20 -> 6.1202105 | P12: =E20 -> 6.9945263 | Q12: =F20 -> 8.6994421 | S12: =K20 -> 6.9042105 | T12: =L20 -> 7.8905263 | U12: =M20 -> 9.8138421
A14: KEIRA PLUS DAMA | H14: KEIRA PLUS CABALLERO | O14: CENTAURO DAMA | S14: CENTAURO CABALLERO
A15: TELA | B15: =0.8*2.8*E2 -> 8512 | H15: TELA | I15: =1*2.8*E2 -> 10640 | O15: +5 DOC | P15: 1 A 5 DOC | Q15: DETAL | S15: +5 DOC | T15: 1 A 5 DOC | U15: DETAL
A16: CORTE | B16: =B5 -> 500 | H16: CORTE | I16: 500 | O16: 40 | P16: 60 | Q16: 99 | S16: 40 | T16: 60 | U16: 99
A17: COSTURA | B17: =B6 -> 2500 | H17: COSTURA | I17: 2500 | O17: =D31 -> 7.2402105 | P17: =E31 -> 8.2745263 | Q17: =F31 -> 10.291442 | S17: =K30 -> 8.8282895 | T17: =L30 -> 10.463158 | U17: =M30 -> 13.013553
A18: ETIQUETA | B18: 250 | D18: +5 DOC | E18: 1 A 5 DOC | F18: DETAL | H18: ETIQUETA | I18: 250 | K18: +5 DOC | L18: 1 A 5 DOC | M18: DETAL
A19: BOLSA | B19: 100 | D19: 40 | E19: 60 | F19: 99 | H19: BOLSA | I19: 100 | K19: 40 | L19: 60 | M19: 99 | O19: CENTAHELADA DA FRIA | S19: CENTAHELADA CAB
A20: MARQUILLA | B20: 500 | D20: =B23*1.4 -> 6.1202105 | E20: =B23*1.6 -> 6.9945263 | F20: =B23*1.99 -> 8.6994421 | H20: MARQUILLA | I20: 500 | K20: =I23*1.4 -> 6.9042105 | L20: =I23*1.6 -> 7.8905263 | M20: =I23*1.99 -> 9.8138421 | O20: +5 DOC | P20: 1 A 5 DOC | Q20: DETAL | S20: +5 DOC | T20: 1 A 5 DOC | U20: DETAL
A21: HILO | B21: 250 | H21: HILO | I21: 250 | O21: 40 | P21: 60 | Q21: 99 | S21: 40 | T21: 60 | U21: 99
A22: GASTOS OPERATIVOS | B22: 4000 | H22: GASTOS OPERATIVOS | I22: 4000 | O22: =D41 -> 7.9122105 | P22: =E41 -> 9.0425263 | Q22: =F41 -> 11.246642 | S22: =K41 -> 9.1442105 | T22: =L41 -> 10.450526 | U22: =M41 -> 12.997842
B23: =SUM(B15:B22)/E2 -> 4.3715789 | I23: =SUM(I15:I22)/E2 -> 4.9315789
H24: CENTAURO CABALLERO | O24: CENTAURO EGIPCIO DA FRIA | S24: CENTAURO EGIPCIO CAB
A25: CENTAURO DAMA | H25: TELA | I25: =1*4*E2 -> 15200 | O25: +5 DOC | P25: 1 A 5 DOC | Q25: DETAL | S25: +5 DOC | T25: 1 A 5 DOC | U25: DETAL
A26: TELA | B26: =0.8*3.8*E2 -> 11552 | H26: CORTE | I26: 500 | O26: 40 | P26: 60 | Q26: 99 | S26: 40 | T26: 60 | U26: 99
A27: CORTE | B27: =B16 -> 500 | H27: COSTURA | I27: 2000 | O27: =D51 -> 7.3522105 | P27: =E51 -> 8.4025263 | Q27: =F51 -> 10.450642 | S27: =K51 -> 8.4442105 | T27: =L51 -> 9.6505263 | U27: =M51 -> 12.002842
A28: COSTURA | B28: =B17 -> 2500 | H28: MARQUILLA | I28: 500 | K28: +5 DOC | L28: 1 A 5 DOC | M28: DETAL
A29: MARQUILLA | B29: 500 | D29: +5 DOC | E29: 1 A 5 DOC | F29: DETAL | H29: ETIQUETA | I29: 250 | K29: 40 | L29: 60 | M29: 99 | O29: MICRO DAMA | S29: MICRO CABALLERO
A30: ETIQUETA | B30: 250 | D30: 40 | E30: 60 | F30: 99 | H30: BOLSA | I30: 100 | K30: =I34*1.35 -> 8.8282895 | L30: =I34*1.6 -> 10.463158 | M30: =I34*1.99 -> 13.013553 | O30: +5 DOC | P30: 1 A 5 DOC | Q30: DETAL | S30: +5 DOC | T30: 1 A 5 DOC | U30: DETAL
A31: BOLSA | B31: 100 | D31: =B34*1.4 -> 7.2402105 | E31: =B34*1.6 -> 8.2745263 | F31: =B34*1.99 -> 10.291442 | H31: HILO | I31: 300 | O31: 40 | P31: 60 | Q31: 99 | S31: 40 | T31: 60 | U31: 99
A32: HILO | B32: 250 | H32: VINIL | I32: 4000 | O32: ='FRA MUSE MICR'!H8 -> 5.73625 | P32: ='FRA MUSE MICR'!I8 -> 6.61875 | Q32: ='FRA MUSE MICR'!J8 -> 7.50125 | S32: ='FRA MUSE MICR'!H27 -> 8.10875 | T32: ='FRA MUSE MICR'!I27 -> 10.60375 | U32: ='FRA MUSE MICR'!J27 -> 11.85125
A33: GASTOS OPERATIVOS | B33: 4000 | H33: GASTOS OPERATIVOS | I33: 2000
B34: =SUM(B26:B33)/E2 -> 5.1715789 | I34: =SUM(I25:I33)/E2 -> 6.5394737 | O34: MUSELINA DAMA | S34: MUSELINA CABALLERO
A35: CENTAHELADA DAMA | H35: CENTAHELADA CAB | O35: +5 DOC | P35: 1 A 5 DOC | Q35: DETAL | S35: +5 DOC | T35: 1 A 5 DOC | U35: DETAL
A36: TELA | B36: =0.8*4.4*E2 -> 13376 | H36: TELA | I36: =1*4.4*E2 -> 16720 | O36: 40 | P36: 60 | Q36: 99 | S36: 40 | T36: 60 | U36: 99
A37: CORTE | B37: 500 | H37: CORTE | I37: 500 | O37: ='FRA MUSE MICR'!C8 -> 5.1135 | P37: ='FRA MUSE MICR'!D8 -> 5.844 | Q37: ='FRA MUSE MICR'!E8 -> 7.268475 | S37: ='FRA MUSE MICR'!C27 -> 3.9725 | T37: ='FRA MUSE MICR'!D27 -> 4.54 | U37: ='FRA MUSE MICR'!E27 -> 5.646625
A38: COSTURA | B38: 2500 | H38: COSTURA | I38: 2500
A39: MARQUILLA | B39: 500 | D39: +5 DOC | E39: 2 A 5 DOC | F39: DETAL | H39: MARQUILLA | I39: 500 | K39: +5 DOC | L39: 2 A 5 DOC | M39: DETAL
A40: ETIQUETA | B40: 250 | D40: 40 | E40: 60 | F40: 99 | H40: ETIQUETA | I40: 250 | K40: 40 | L40: 60 | M40: 99
A41: BOLSA | B41: 100 | D41: =B44*1.4 -> 7.9122105 | E41: =B44*1.6 -> 9.0425263 | F41: =B44*1.99 -> 11.246642 | H41: BOLSA | I41: 100 | K41: =I44*1.4 -> 9.1442105 | L41: =I44*1.6 -> 10.450526 | M41: =I44*1.99 -> 12.997842
A42: HILO | B42: 250 | H42: HILO | I42: 250
A43: GASTOS OPERATIVOS | B43: 4000 | H43: GASTOS OPERATIVOS | I43: 4000
B44: =SUM(B36:B43)/E2 -> 5.6515789 | I44: =SUM(I36:I43)/E2 -> 6.5315789
A45: CENTAURO EGIPCIO DAMA | H45: CENTAURO EGIPCIO CAB
A46: TELA | B46: =0.8*3.9*E2 -> 11856 | H46: TELA | I46: =1*3.9*E2 -> 14820
A47: CORTE | B47: 500 | H47: CORTE | I47: 500
A48: COSTURA | B48: 2500 | H48: COSTURA | I48: 2500
A49: MARQUILLA | B49: 500 | D49: +5 DOC | E49: 3 A 5 DOC | F49: DETAL | H49: MARQUILLA | I49: 500 | K49: +5 DOC | L49: 3 A 5 DOC | M49: DETAL
A50: ETIQUETA | B50: 250 | D50: 40 | E50: 60 | F50: 99 | H50: ETIQUETA | I50: 250 | K50: 40 | L50: 60 | M50: 99
A51: BOLSA | B51: 100 | D51: =B54*1.4 -> 7.3522105 | E51: =B54*1.6 -> 8.4025263 | F51: =B54*1.99 -> 10.450642 | H51: BOLSA | I51: 100 | K51: =I54*1.4 -> 8.4442105 | L51: =I54*1.6 -> 9.6505263 | M51: =I54*1.99 -> 12.002842
A52: HILO | B52: 250 | H52: HILO | I52: 250
A53: GASTOS OPERATIVOS | B53: 4000 | H53: GASTOS OPERATIVOS | I53: 4000
B54: =SUM(B46:B53)/E2 -> 5.2515789 | I54: =SUM(I46:I53)/E2 -> 6.0315789

Sheet CHALECOS
E2: DRILL SAHARA
A3: CORTA VIENTO DAMA | D3: CON VINIL PÑO
A4: TELA DRILL SAHARA | B4: =1*2.3*F4 -> 8740 | F4: 3800 | G4: DÓLAR
A5: CORTE | B5: 500
A6: COSTURA | B6: 6000
A7: CIERRE | B7: 2500
A8: PLANCHA | B8: 0 | D8: CORTA VIENTO DE DAMA IMPERMEABLE
A9: VINIL 15 CMS | B9: =1*11000 -> 11000
A10: DISEÑO | B10: 2000 | D10: +5 DOC | E10: 1 A 5 DOC | F10: DETAL
A11: CORTE DEL PLOTTER | B11: 0 | D11: =D15 -> 14.463947 | E11: =E15 -> 16.330263 | F11: =F15 -> 18.569842
A12: DEPILADA | B12: 0
A13: ETIQUETA | B13: 200
A14: BOLSA | B14: 100 | D14: 45 | E14: 75 | F14: 99
A15: HILO | B15: 350 | D15: =B18*1.55 -> 14.463947 | E15: =B18*1.75 -> 16.330263 | F15: =B18*1.99 -> 18.569842
A16: MARQUILLA | B16: 70
A17: GASTOS OPERATIVOS | B17: 4000
B18: =SUM(B4:B17)/F4 -> 9.3315789
E20: MEMORY
A21: CHALECO TODO SUBLIMADO
A22: TELA | B22: =1*4*F22 -> 15200 | F22: 3800 | G22: DÓLAR
A23: CORTE | B23: 700
A24: COSTURA | B24: 6000
A25: CIERRE | B25: 2500
A26: PLANCHA | B26: 1500 | D26: CORTA VIENTO DE DAMA IMPERMEABLE
A27: VINIL | B27: 2500
A28: DISEÑO | B28: 2000 | D28: +5 DOC | E28: 1 A 5 DOC | F28: DETAL
A29: CORTE DEL PLOTTER | B29: 200 | D29: =D33 -> 14.325263 | E29: =E33 -> 14.787368 | F29: =F33 -> 17.56
A30: DEPILADA | B30: 200
A31: ETIQUETA | B31: 200
A32: BOLSA | B32: 100 | D32: 45 | E32: 75 | F32: 99
A33: HILO | B33: 250 | D33: =B36*1.55 -> 14.325263 | E33: =B36*1.6 -> 14.787368 | F33: =B36*1.9 -> 17.56
A34: MARQUILLA | B34: 70
A35: GASTOS OPERATIVOS | B35: 3700
B36: =SUM(B22:B35)/F22 -> 9.2421053

Sheet FRA ALGODON
A1: ALGODÓN EN BLANCO
A2: DAMA | F2: 3800 | G2: DÓLAR
A3: TELA | B3: =0.8*5.31*F2 -> 16142.4
A4: CORTE | B4: 1000
A5: COSTURA | B5: 2500 | D5: +5 DOC | E5: 1 A 5 DOC | F5: DETAL
A6: PLANCHA | B6: 0 | D6: =D12 -> 9.9372316 | E6: =E12 -> 11.993211 | F6: =F12 -> 13.637994
A7: DISEÑO | B7: 1000
A8: CORTE DEL PLOTTER | B8: 0
A9: DEPILADA | B9: 0
A10: ETIQUETA | B10: 200
A11: BOLSA | B11: 100 | D11: 0.4 | E11: 0.6 | F11: 0.9
A12: HILO | B12: 350 | D12: =B15*1.45 -> 9.9372316 | E12: =B15*1.75 -> 11.993211 | F12: =B15*1.99 -> 13.637994
A13: MARQUILLA | B13: 750
A14: GASTOS OPERATIVOS | B14: 4000
B15: =SUM(B3:B14)/F2 -> 6.8532632
A19: CABALLERO | D19: ALGODÓN EN BLANCO
A20: TELA | B20: =1.1*1.9*F2 -> 7942
A21: CORTE | B21: 700
A22: COSTURA | B22: 2500
A23: PLANCHA | B23: 1000
A24: VINIL | B24: 4500 | D24: +5 DOC | E24: 1 A 5 DOC | F24: DETAL
A25: DISEÑO | B25: 1000 | D25: =D30 -> 8.0291842 | E25: =E30 -> 8.3060526 | F25: =F30 -> 11.019363
A26: CORTE DEL PLOTTER | B26: 0
A27: DEPILADA | B27: 0
A28: ETIQUETA | B28: 0
A29: BOLSA | B29: 100 | D29: 0.4 | E29: 0.55 | F29: 0.85
A30: HILO | B30: 350 | D30: =B33*1.45 -> 8.0291842 | E30: =B33*1.5 -> 8.3060526 | F30: =B33*1.99 -> 11.019363
A31: MARQUILLA | B31: 250
A32: GASTOS OPERATIVOS | B32: 2700
B33: =SUM(B20:B32)/F2 -> 5.5373684
A37: ALGODÓN CON DISEÑO VINIL
A38: DAMA
A39: TELA | B39: =0.8*5.31*F2 -> 16142.4
A40: CORTE | B40: 1000
A41: COSTURA | B41: 2500
A42: PLANCHA | B42: 1000
A43: VINIL 15 CMS | B43: 1000 | D43: +5 DOC | E43: 1 A 5 DOC | F43: DETAL
A44: DISEÑO | B44: 1000 | D44: =D49 -> 10.853021 | E44: =E49 -> 13.098474 | F44: =F49 -> 14.894836
A45: CORTE DEL PLOTTER | B45: 200
A46: DEPILADA | B46: 200
A47: ETIQUETA | B47: 200
A48: BOLSA | B48: 100 | D48: 0.4 | E48: 0.55 | F48: 0.85
A49: HILO | B49: 350 | D49: =B52*1.45 -> 10.853021 | E49: =B52*1.75 -> 13.098474 | F49: =B52*1.99 -> 14.894836
A50: MARQUILLA | B50: 750
A51: GASTOS OPERATIVOS | B51: 4000
B52: =SUM(B39:B51)/F2 -> 7.4848421
A56: CABALLERO | D56: ALGODÓN CON DISEÑO VINIL
A57: TELA | B57: =2*5.31*F2 -> 40356 | F57: FRANELAS
A58: CORTE | B58: 1000
A59: COSTURA | B59: 2500
A60: PLANCHA | B60: 1000
A61: VINIL 15 CMS | B61: 1000 | D61: +5 DOC | E61: 1 A 5 DOC | F61: DETAL
A62: DISEÑO | B62: 1000 | D62: =D68 -> 20.092421 | E62: =E68 -> 20.785263 | F62: =F68 -> 27.575116
A63: CORTE DEL PLOTTER | B63: 200
A64: DEPILADA | B64: 200
A65: ETIQUETA | B65: 200
A66: BOLSA | B66: 100
A67: HILO | B67: 350 | D67: 0.4 | E67: 0.55 | F67: 0.85
A68: MARQUILLA | B68: 750 | D68: =B70*1.45 -> 20.092421 | E68: =B70*1.5 -> 20.785263 | F68: =B70*1.99 -> 27.575116
A69: GASTOS OPERATIVOS | B69: 4000
B70: =SUM(B57:B69)/F2 -> 13.856842

Sheet HODDI  MONO
A1: HODDI CON GORRO EN BLANCO TELA DE MONO
A2: DAMA | F2: 3800 | G2: DÓLAR
A3: TELA MONO | B3: =1.7*4*F2 -> 25840
A4: CORTE | B4: 1000 | H4: HODDI CON DISEÑO EN VINIL
A5: COSTURA | B5: 4500 | H5: DAMA
A6: PLANCHA | B6: 0 | D6: DAMA | H6: TELA MONO | I6: =1.8*2.9*F2 -> 19836
A7: DISEÑO | B7: 0 | D7: +5 DOC | E7: 1 A 5 DOC | F7: DETAL | H7: CORTE | I7: 700
A8: CORTE DEL PLOTTER | B8: 0 | D8: =D12 -> 14.000132 | E8: =E12 -> 16.896711 | F8: =F12 -> 19.213974 | H8: COSTURA | I8: 3000
A9: DEPILADA | B9: 0 | H9: PLANCHA | I9: 3000 | K9: DAMA
A10: ETIQUETA | B10: 200 | H10: sublimacion | I10: =1.8*13000 -> 23400 | K10: +5 DOC | L10: 1 A 5 DOC | M10: DETAL
A11: BOLSA | B11: 100 | D11: 0.4 | E11: 0.6 | F11: 0.9 | H11: CORDON | I11: 1000
A12: HILO | B12: 300 | D12: =B15*1.45 -> 14.000132 | E12: =B15*1.75 -> 16.896711 | F12: =B15*1.99 -> 19.213974 | H12: DISEÑO | I12: 2000 | K12: =K17 -> 20.706868 | L12: =L17 -> 26.842237 | M12: =M17 -> 30.523458
A13: MARQUILLA | B13: 750 | H13: ETIQUETA | I13: 200
A14: GASTOS OPERATIVOS | B14: 4000 | H14: BOLSA | I14: 100
B15: =SUM(B3:B14)/F2 -> 9.6552632 | H15: HILO | I15: 300
H16: MARQUILLA | I16: 750 | K16: 0.4 | L16: 0.6 | M16: 0.9
H17: GASTOS OPERATIVOS | I17: 4000 | K17: =I18*1.35 -> 20.706868 | L17: =I18*1.75 -> 26.842237 | M17: =I18*1.99 -> 30.523458
A18: NIÑO | I18: =SUM(I6:I17)/F2 -> 15.338421
A19: TELA MONO | B19: =1.5*4*F2 -> 22800
A20: CORTE | B20: 1000
A21: COSTURA | B21: 4000 | D21: NIÑO
A22: PLANCHA | B22: 0 | D22: +5 DOC | E22: 1 A 5 DOC | F22: DETAL
A23: DISEÑO | B23: =B7 -> 0 | D23: =D27 -> 12.649342 | E23: =E27 -> 15.266447 | F23: =F27 -> 17.360132 | H23: NIÑO
A24: CORTE DEL PLOTTER | B24: =B8 -> 0 | H24: TELA MONO | I24: =1.5*2.9*F2 -> 16530
A25: DEPILADA | B25: =B9 -> 0 | H25: CORTE | I25: 700 | K25: NIÑO
A26: ETIQUETA | B26: 200 | D26: 0.4 | E26: 0.6 | F26: 0.9 | H26: COSTURA | I26: 3000 | K26: +5 DOC | L26: 1 A 5 DOC | M26: DETAL
A27: BOLSA | B27: 100 | D27: =B31*1.45 -> 12.649342 | E27: =B31*1.75 -> 15.266447 | F27: =B31*1.99 -> 17.360132 | H27: PLANCHA | I27: 1000 | K27: =K33 -> 17.436316 | L27: =L33 -> 21.956842 | M27: =M33 -> 25.702421
A28: HILO | B28: =B12 -> 300 | H28: sublimacion | I28: =1.5*13000 -> 19500
A29: MARQUILLA | B29: =B13 -> 750 | H29: CORDON | I29: 1000
A30: GASTOS OPERATIVOS | B30: =B14 -> 4000 | H30: DISEÑO | I30: =I12 -> 2000
B31: =SUM(B19:B30)/F2 -> 8.7236842 | H31: ETIQUETA | I31: 200
H32: BOLSA | I32: 100 | K32: 0.4 | L32: 0.6 | M32: 0.9
A33: CABALLERO | H33: HILO | I33: =I15 -> 300 | K33: =I36*1.35 -> 17.436316 | L33: =I36*1.7 -> 21.956842 | M33: =I36*1.99 -> 25.702421
A34: TELA MONO | B34: =2*4*F2 -> 30400 | H34: MARQUILLA | I34: =I16 -> 750
A35: CORTE | B35: 700 | H35: GASTOS OPERATIVOS | I35: =I17 -> 4000
A36: COSTURA | B36: 3500 | I36: =SUM(I24:I35)/F2 -> 12.915789
A37: PLANCHA | B37: 0
A38: VINIL | B38: 2000
A39: DISEÑO | B39: 1000 | D39: CABALLERO
A40: CORTE DEL PLOTTER | B40: 200 | D40: +5 DOC | E40: 1 A 5 DOC | F40: DETAL | H40: CABALLERO
A41: DEPILADA | B41: 200 | D41: =D45 -> 16.064474 | E41: =E45 -> 19.388158 | F41: =F45 -> 22.047105 | H41: TELA MONO | I41: =1*2*F2 -> 7600
A42: ETIQUETA | B42: 200 | H42: CORTE | I42: 700
A43: BOLSA | B43: 100 | H43: COSTURA | I43: 3000 | K43: CABALLERO
A44: HILO | B44: 300 | D44: 0.4 | E44: 0.6 | F44: 0.9 | H44: PLANCHA | I44: 3000 | K44: +5 DOC | L44: 1 A 5 DOC | M44: DETAL
A45: MARQUILLA | B45: 500 | D45: =B47*1.45 -> 16.064474 | E45: =B47*1.75 -> 19.388158 | F45: =B47*1.99 -> 22.047105 | H45: VINIL | I45: 11000 | K45: =K49 -> 11.623684 | L45: =L49 -> 13.699342 | M45: =M49 -> 14.944737
A46: GASTOS OPERATIVOS | B46: 3000 | H46: CORDON | I46: 1000
B47: =SUM(B34:B46)/F2 -> 11.078947 | H47: ETIQUETA | I47: 200
H48: CIERRE | I48: 0 | K48: 0.4 | L48: 0.6 | M48: 0.9
A49: HODDI CON DISEÑO EN VINIL | H49: HILO | I49: 300 | K49: =I52*1.4 -> 11.623684 | L49: =I52*1.65 -> 13.699342 | M49: =I52*1.8 -> 14.944737
A50: DAMA | H50: MARQUILLA | I50: 750
A51: TELA MONO | B51: =1.8*4*F2 -> 27360 | H51: GASTOS OPERATIVOS | I51: 4000
A52: CORTE | B52: 700 | I52: =SUM(I41:I51)/F2 -> 8.3026316
A53: COSTURA | B53: 3000
A54: PLANCHA | B54: 500 | D54: DAMA
A55: VINIL 15 CMS | B55: 3000 | D55: +5 DOC | E55: 1 A 5 DOC | F55: DETAL
A56: CORDON | B56: 1000
A57: DISEÑO | B57: 1000 | D57: =D62 -> 16.144605 | E57: =E62 -> 19.484868 | F57: =F62 -> 22.157079
A58: CORTE DEL PLOTTER | B58: 200
A59: DEPILADA | B59: 200
A60: ETIQUETA | B60: 200
A61: BOLSA | B61: 100 | D61: 0.4 | E61: 0.6 | F61: 0.9
A62: HILO | B62: 300 | D62: =B65*1.45 -> 16.144605 | E62: =B65*1.75 -> 19.484868 | F62: =B65*1.99 -> 22.157079
A63: MARQUILLA | B63: 750
A64: GASTOS OPERATIVOS | B64: 4000
B65: =SUM(B51:B64)/F2 -> 11.134211
A68: NIÑO
A69: TELA MONO | B69: =1.5*4*F2 -> 22800
A70: CORTE | B70: 700 | D70: NIÑO
A71: COSTURA | B71: 3000 | D71: +5 DOC | E71: 1 A 5 DOC | F71: DETAL
A72: PLANCHA | B72: 1000 | D72: =D78 -> 14.786184 | E72: =E78 -> 17.335526 | F72: =F78 -> 20.292763
A73: VINIL 15 CMS | B73: 3500
A74: CORDON | B74: 1000
A75: DISEÑO | B75: =B57 -> 1000
A76: CORTE DEL PLOTTER | B76: =B58 -> 200
A77: DEPILADA | B77: =B59 -> 200 | D77: 0.4 | E77: 0.6 | F77: 0.9
A78: ETIQUETA | B78: 200 | D78: =B83*1.45 -> 14.786184 | E78: =B83*1.7 -> 17.335526 | F78: =B83*1.99 -> 20.292763
A79: BOLSA | B79: 100
A80: HILO | B80: =B62 -> 300
A81: MARQUILLA | B81: =B63 -> 750
A82: GASTOS OPERATIVOS | B82: =B64 -> 4000
B83: =SUM(B69:B82)/F2 -> 10.197368
A85: CABALLERO
A86: TELA MONO | B86: =2*4*F2 -> 30400
A87: CORTE | B87: 700
A88: COSTURA | B88: 3000 | D88: CABALLERO
A89: PLANCHA | B89: 1000 | D89: +5 DOC | E89: 1 A 5 DOC | F89: DETAL
A90: VINIL 15 CMS | B90: 4000 | D90: =D94 -> 17.495395 | E90: =E94 -> 21.115132 | F90: =F94 -> 24.010921
A91: CORDON | B91: 1000
A92: CORTE DEL PLOTTER | B92: 200
A93: DEPILADA | B93: 200 | D93: 0.4 | E93: 0.6 | F93: 0.9
A94: ETIQUETA | B94: 200 | D94: =B99*1.45 -> 17.495395 | E94: =B99*1.75 -> 21.115132 | F94: =B99*1.99 -> 24.010921
A95: BOLSA | B95: 100
A96: HILO | B96: 300
A97: MARQUILLA | B97: 750
A98: GASTOS OPERATIVOS | B98: 4000
B99: =SUM(B86:B98)/F2 -> 12.065789

Sheet TAPASOL
A3: FECHA: 20 MAYO DE 2025
A6: Presupuesto
A9: ARTICULO | B9: CATEGORIA | C9: TECNICA | D9: DISEÑO | E9: CANT | F9: PRECIO ($)
A11: TAPASOL | B11: ARTICULOS | C11: SUBLIMACIÓN | D11: REMAX | E11: 1 | F11: 25
A13: TAPASOL | B13: ARTICULOS | C13: SUBLIMACIÓN | D13: REMAX | E13: 12 | F13: 20
A15: TAPASOL | B15: ARTICULOS | C15: SUBLIMACIÓN | D15: REMAX | E15: 36 | F15: 18
A19: NOTAS: - SE REQUIERE UN ABONO DEL 60% DEL TOTAL, PARA DAR COMIENZO AL PROYECTO. - EL DISEÑO VA INCLUÍDO EN EL PROYECTO. - LA FECHA DE ENTREGA ES ESTIMADA. - EL PRESUPUESTO ES VÁLIDO PARA EL DÍA ESPECIFICADO, PUEDE VARIAR POSTERIORMENTE.

Sheet CHAQUETA NORF
A3: CHAQUETA NORT | F3: 3800
A4: CAB
A5: TELA norface 5,5$ | B5: =2*5.5*3800 -> 41800
A6: CORTE | B6: 700
A7: COSTURA | B7: 10000
A8: CIERRE BOLSILLOS | B8: 2800 | D8: DAMA
A9: CIERRE | B9: 3000 | D9: +5 DOC | E9: 1 A 5 DOC | F9: DETAL
A10: CORDON | B10: 0
A11: DISEÑO | B11: 1000 | D11: =D16 -> 24.440132 | E11: =E16 -> 29.496711 | F11: =F16 -> 32.025
A12: CORTE DEL PLOTTER | B12: 0
A13: DEPILADA | B13: 0
A14: ETIQUETA | B14: 0
A15: BOLSA | B15: 0 | D15: 0.4 | E15: 0.6 | F15: 0.9
A16: HILO | B16: 300 | D16: =B19*1.45 -> 24.440132 | E16: =B19*1.75 -> 29.496711 | F16: =B19*1.9 -> 32.025
A17: MARQUILLA | B17: 750
A18: GASTOS OPERATIVOS | B18: 3700
B19: =SUM(B5:B18)/F3 -> 16.855263

Sheet PANTALON MONO
A2: PANTALON DE MONO
A3: DAMA | F3: 4000
A4: TELA MONO | B4: =1.1*3*F3 -> 13200
A5: CORTE | B5: 7000
A6: COSTURA | B6: 3500
A7: PLANCHA | B7: 1000 | D7: PANTALON MONO DAMA
A8: CORTE DEL PLOTTER | B8: 200 | D8: +5 DOC | E8: 1 A 5 DOC | F8: DETAL
A9: VINIL | B9: 1500 | D9: =D13 -> 11.581875 | E9: =E13 -> 13.978125 | F9: =F13 -> 15.895125
A10: DEPILADA | B10: 200
A11: ETIQUETA | B11: 200
A12: BOLSA | B12: 100 | D12: 0.4 | E12: 0.6 | F12: 0.9
A13: HILO | B13: 300 | D13: =B16*1.45 -> 11.581875 | E13: =B16*1.75 -> 13.978125 | F13: =B16*1.99 -> 15.895125
A14: MARQUILLA | B14: 750
A15: GASTOS OPERATIVOS | B15: 4000
B16: =SUM(B4:B15)/F3 -> 7.9875
A19: HODDI NIÑO
A20: TELA MONO | B20: =0.6*3*F3 -> 7200
A21: CORTE | B21: 700
A22: COSTURA | B22: 2500 | D22: PANTALON MONO NIÑO
A23: PLANCHA | B23: 1000 | D23: +5 DOC | E23: 1 A 5 DOC | F23: DETAL
A24: VINIL | B24: 1000 | D24: =D28 -> 6.10875 | E24: =E28 -> 7.91875 | F24: =F28 -> 9.00475
A25: CORTE DEL PLOTTER | B25: =B8 -> 200
A26: DEPILADA | B26: 500
A27: ETIQUETA | B27: 200 | D27: 0.4 | E27: 0.6 | F27: 0.9
A28: MARQUILLA | B28: 500 | D28: =B32*1.35 -> 6.10875 | E28: =B32*1.75 -> 7.91875 | F28: =B32*1.99 -> 9.00475
A29: HILO | B29: =B13 -> 300
A30: DISEÑO | B30: 2000
A31: GASTOS OPERATIVOS | B31: 2000
B32: =SUM(B20:B31)/F3 -> 4.525
A34: HODDI EN BLANCO
A35: HODDI CABALLERO
A36: TELA MONO | B36: =1.25*3*F3 -> 15000
A37: CORTE | B37: 1000
A38: COSTURA | B38: 4000
A39: PLANCHA | B39: 1000
A40: VINIL | B40: 2500 | D40: PANTALON MONO CABALLERO
A41: CORTE DEL PLOTTER | B41: 200 | D41: +5 DOC | E41: 1 A 5 DOC | F41: DETAL
A42: DEPILADA | B42: 200 | D42: =D46 -> 10.603125 | E42: =E46 -> 12.796875 | F42: =F46 -> 14.551875
A43: ETIQUETA | B43: 200
A44: BOLSA | B44: 100
A45: HILO | B45: 300 | D45: 0.4 | E45: 0.6 | F45: 0.9
A46: MARQUILLA | B46: 750 | D46: =B48*1.45 -> 10.603125 | E46: =B48*1.75 -> 12.796875 | F46: =B48*1.99 -> 14.551875
A47: GASTOS OPERATIVOS | B47: 4000
B48: =SUM(B36:B47)/F3 -> 7.3125

Sheet HODDI TERRY
A1: HODDI DAMA | C1: EN BLANCO
A2: TELA TERRY SPUN | B2: =1.8*5.2*F2 -> 37440 | F2: 4000 | G2: DÓLAR
A3: CORTE | B3: 1000
A4: COSTURA | B4: 4500
A5: PLANCHA | B5: 0
A6: DISEÑO | B6: 0 | D6: HODDI TERRY EN BLANCO DAMA
A7: CORTE DEL PLOTTER | B7: 0 | D7: +5 DOC | E7: 1 A 5 DOC | F7: DETAL
A8: DEPILADA | B8: 0 | D8: =D13 -> 17.505125 | E8: =E13 -> 21.126875 | F8: =F13 -> 24.024275
A9: ETIQUETA | B9: 200
A10: BOLSA | B10: 100
A11: HILO | B11: 300 | D11: 0.4 | E11: 0.6 | F11: 0.9
A12: MARQUILLA | B12: 750 | D12: =B14*1.45 -> 70020.5 | E12: =B14*1.75 -> 84507.5 | F12: =B14*1.99 -> 96097.1
A13: GASTOS OPERATIVOS | B13: 4000 | D13: =D12/F2 -> 17.505125 | E13: =E12/F2 -> 21.126875 | F13: =F12/F2 -> 24.024275
B14: =SUM(B2:B13) -> 48290
A18: NIÑO
A19: TELA TERRY SPUN | B19: =1.5*5.2*F2 -> 31200
A20: CORTE | B20: 1000
A21: COSTURA | B21: 4500 | D21: HODDI TERRY EN BLANCO NIÑO
A22: PLANCHA | B22: 0 | D22: +5 DOC | E22: 1 A 5 DOC | F22: DETAL
A23: DISEÑO | B23: =B6 -> 0 | D23: =D30 -> 15.243125 | E23: =E30 -> 18.396875 | F23: =F30 -> 20.919875
A24: CORTE DEL PLOTTER | B24: =B7 -> 0
A25: DEPILADA | B25: =B8 -> 0
A26: ETIQUETA | B26: 200
A27: BOLSA | B27: 100
A28: HILO | B28: =B11 -> 300 | D28: 0.4 | E28: 0.6 | F28: 0.9
A29: MARQUILLA | B29: =B12 -> 750 | D29: =B31*1.45 -> 60972.5 | E29: =B31*1.75 -> 73587.5 | F29: =B31*1.99 -> 83679.5
A30: GASTOS OPERATIVOS | B30: =B13 -> 4000 | D30: =D29/F2 -> 15.243125 | E30: =E29/F2 -> 18.396875 | F30: =F29/F2 -> 20.919875
B31: =SUM(B19:B30) -> 42050
A38: HODDI CABALLERO | C38: EN BLANCO
A39: TELA TERRY SPUN | B39: =2*5.2*F2 -> 41600
A40: CORTE | B40: 1000
A41: COSTURA | B41: 4500
A42: PLANCHA | B42: 0 | D42: HODDI TERRY EN BLANCO CABALLERO
A43: DISEÑO | B43: 1000 | D43: +5 DOC | E43: 1 A 5 DOC | F43: DETAL
A44: CORTE DEL PLOTTER | B44: 0 | D44: =D48 -> 19.375625 | E44: =E48 -> 23.384375 | F44: =F48 -> 26.591375
A45: DEPILADA | B45: 0
A46: ETIQUETA | B46: 200 | D46: 0.4 | E46: 0.6 | F46: 0.9
A47: BOLSA | B47: 100 | D47: =B51*1.45 -> 77502.5 | E47: =B51*1.75 -> 93537.5 | F47: =B51*1.99 -> 106365.5
A48: HILO | B48: 300 | D48: =D47/F2 -> 19.375625 | E48: =E47/F2 -> 23.384375 | F48: =F47/F2 -> 26.591375
A49: MARQUILLA | B49: 750
A50: GASTOS OPERATIVOS | B50: 4000
B51: =SUM(B39:B50) -> 53450
A58: HODDI DAMA | C58: CON DISEÑO EN VINIL
A59: TELA TERRY SPUN | B59: =1.8*5.2*F2 -> 37440
A60: CORTE | B60: 1000
A61: COSTURA | B61: 4500
A62: PLANCHA | B62: 1000
A63: VINIL 15 CMS | B63: 1000
A64: DISEÑO | B64: 1000 | D64: HODDI TERRY CON VINIL DAMA
A65: CORTE DEL PLOTTER | B65: 200 | D65: +5 DOC | E65: 1 A 5 DOC | F65: DETAL
A66: DEPILADA | B66: 200 | D66: =D70 -> 18.737625 | E66: =E70 -> 22.614375 | F66: =F70 -> 25.715775
A67: ETIQUETA | B67: 200
A68: BOLSA | B68: 100 | D68: 0.4 | E68: 0.6 | F68: 0.9
A69: HILO | B69: 300 | D69: =B72*1.45 -> 74950.5 | E69: =B72*1.75 -> 90457.5 | F69: =B72*1.99 -> 102863.1
A70: MARQUILLA | B70: 750 | D70: =D69/F2 -> 18.737625 | E70: =E69/F2 -> 22.614375 | F70: =F69/F2 -> 25.715775
A71: GASTOS OPERATIVOS | B71: 4000
B72: =SUM(B59:B71) -> 51690
A77: NIÑO
A78: TELA TERRY SPUN | B78: =1.5*5.2*F2 -> 31200
A79: CORTE | B79: 1000
A80: COSTURA | B80: 4500
A81: PLANCHA | B81: 1000 | D81: HODDI TERRY CON VINIL NIÑO
A82: VINIL 15 CMS | B82: =B63 -> 1000 | D82: +5 DOC | E82: 1 A 5 DOC | F82: DETAL
A83: DISEÑO | B83: =B64 -> 1000 | D83: =D88 -> 16.475625 | E83: =E88 -> 19.884375 | F83: =F88 -> 22.611375
A84: CORTE DEL PLOTTER | B84: =B65 -> 200
A85: DEPILADA | B85: =B66 -> 200
A86: ETIQUETA | B86: 200 | D86: 0.4 | E86: 0.6 | F86: 0.9
A87: BOLSA | B87: 100 | D87: =B91*1.45 -> 65902.5 | E87: =B91*1.75 -> 79537.5 | F87: =B91*1.99 -> 90445.5
A88: HILO | B88: =B69 -> 300 | D88: =D87/F2 -> 16.475625 | E88: =E87/F2 -> 19.884375 | F88: =F87/F2 -> 22.611375
A89: MARQUILLA | B89: =B70 -> 750
A90: GASTOS OPERATIVOS | B90: =B71 -> 4000
B91: =SUM(B78:B90) -> 45450
A97: HODDI CABALLERO | D97: CON DISEÑO EN VINIL
A98: TELA TERRY SPUN | B98: =2*5.2*F2 -> 41600
A99: CORTE | B99: 1000
A100: COSTURA | B100: 4500
A101: PLANCHA | B101: 1000 | D101: HODDI TERRY CON VINIL CABALLERO
A102: VINIL 15 CMS | B102: 1000 | D102: +5 DOC | E102: 1 A 5 DOC | F102: DETAL
A103: DISEÑO | B103: 1000 | D103: =D107 -> 20.245625 | E103: =E107 -> 24.434375 | F103: =F107 -> 27.785375
A104: CORTE DEL PLOTTER | B104: 200
A105: DEPILADA | B105: 200 | D105: 0.4 | E105: 0.6 | F105: 0.9
A106: ETIQUETA | B106: 200 | D106: =B111*1.45 -> 80982.5 | E106: =B111*1.75 -> 97737.5 | F106: =B111*1.99 -> 111141.5
A107: BOLSA | B107: 100 | D107: =D106/F2 -> 20.245625 | E107: =E106/F2 -> 24.434375 | F107: =F106/F2 -> 27.785375
A108: HILO | B108: 300
A109: MARQUILLA | B109: 750
A110: GASTOS OPERATIVOS | B110: 4000
B111: =SUM(B98:B110) -> 55850

Sheet SUETER
A1: SUETER SIN GORRO | C1: DAMA EN BLANCO | H1: SUETER SIN GORRO | J1: NIÑO EN BLANCO
A2: TELA DE MONO | B2: =1.1*4*F2 -> 16720 | F2: 3800 | H2: TELA DE MONO | I2: =0.9*4*M2 -> 13680 | M2: 3800
A3: CORTE | B3: 700 | H3: CORTE | I3: 700
A4: COSTURA | B4: 4000 | D4: DAMA | H4: COSTURA | I4: 4000 | K4: DAMA
A5: PLANCHA | B5: 1000 | D5: +5 DOC | E5: 1 A 5 DOC | F5: DETAL | H5: PLANCHA | I5: 1000 | K5: +5 DOC | L5: 1 A 5 DOC | M5: DETAL
A6: DISEÑO | B6: 2000 | D6: =D11 -> 51504 | E6: =E11 -> 62160 | F6: =F11 -> 70684.8 | H6: DISEÑO | I6: 2000 | K6: =K11 -> 44486 | L6: =L11 -> 53690 | M6: =M11 -> 61053.2
A7: CORTE DEL PLOTTER | B7: 200 | D7: =D6/F2 -> 13.553684 | E7: =E6/F2 -> 16.357895 | F7: =F6/F2 -> 18.601263 | H7: CORTE DEL PLOTTER | I7: 200 | K7: =K6/M2 -> 11.706842 | L7: =L6/M2 -> 14.128947 | M7: =M6/M2 -> 16.066632
A8: DEPILADA | B8: 500 | H8: DEPILADA | I8: 500
A9: VINIL | B9: 6000 | H9: ETIQUETA | I9: 200
A10: BOLSA | B10: 100 | D10: 0.4 | E10: 0.6 | F10: 0.9 | H10: BOLSA | I10: 100 | K10: 0.4 | L10: 0.6 | M10: 0.9
A11: HILO | B11: 300 | D11: =B14*1.45 -> 51504 | E11: =B14*1.75 -> 62160 | F11: =B14*1.99 -> 70684.8 | H11: HILO | I11: 300 | K11: =I14*1.45 -> 44486 | L11: =I14*1.75 -> 53690 | M11: =I14*1.99 -> 61053.2
A12: MARQUILLA | B12: 0 | D12: =D11/F2 -> 13.553684 | E12: =E11/F2 -> 16.357895 | F12: =F11/F2 -> 18.601263 | H12: VINIL | I12: 4000 | K12: =K11/M2 -> 11.706842 | L12: =L11/M2 -> 14.128947 | M12: =M11/M2 -> 16.066632
A13: GASTOS OPERATIVOS | B13: 4000 | H13: GASTOS OPERATIVOS | I13: 4000
B14: =SUM(B2:B13) -> 35520 | I14: =SUM(I2:I13) -> 30680
A19: SUETER SIN GORRO | D19: CABALLERO EN BLANCO
A20: TELA DE MONO | B20: =1.2*4*F2 -> 18240
A21: CORTE | B21: 700
A22: COSTURA | B22: 4000 | E22: CABALLERO
A23: PLANCHA | B23: 1000 | D23: +5 DOC | E23: 1 A 5 DOC | F23: DETAL
A24: DISEÑO | B24: 2000 | D24: =D30 -> 55158 | E24: =E30 -> 66570 | F24: =F30 -> 75699.6
A25: CORTE DEL PLOTTER | B25: 200 | D25: =D24/F2 -> 14.515263 | E25: =E24/F2 -> 17.518421 | F25: =F24/F2 -> 19.920947
A26: VINIL | B26: 6000
A27: DEPILADA | B27: 500
A28: ETIQUETA | B28: 200
A29: BOLSA | B29: 100 | D29: 0.4 | E29: 0.6 | F29: 0.9
A30: HILO | B30: 350 | D30: =B33*1.45 -> 55158 | E30: =B33*1.75 -> 66570 | F30: =B33*1.99 -> 75699.6
A31: MARQUILLA | B31: 750 | D31: =D30/F2 -> 14.515263 | E31: =E30/F2 -> 17.518421 | F31: =F30/F2 -> 19.920947
A32: GASTOS OPERATIVOS | B32: 4000
B33: =SUM(B20:B32) -> 38040
A40: SUETER DAMA | C40: DAMA CON VINIL PQÑO | H40: SUETER | J40: NIÑO CON VINIL PQÑO
A41: TELA DE MONO | B41: =B2 -> 16720 | F41: 3800 | H41: TELA DE MONO | I41: =I2 -> 13680
A42: CORTE | B42: 500 | H42: CORTE | I42: 500
A43: COSTURA | B43: 3000 | H43: COSTURA | I43: 3000
A44: PLANCHA | B44: 500 | H44: PLANCHA | I44: 500
A45: VINIL | B45: 3000 | H45: VINIL | I45: 3000
A46: CORDON | B46: 1000 | D46: +5 DOC | E46: 1 A 5 DOC | F46: DETAL | H46: CORDON | I46: 1000 | K46: +5 DOC | L46: 1 A 5 DOC | M46: DETAL
A47: CORTE DEL PLOTTER | B47: 200 | D47: =D52 -> 11.626711 | E47: =E52 -> 14.032237 | F47: =F52 -> 15.956658 | H47: CORTE DEL PLOTTER | I47: 200 | K47: =K52 -> 10.466711 | L47: =L52 -> 12.632237 | M47: =M52 -> 14.364658
A48: DEPILADA | B48: 200 | D48: =D47/F2 -> 0.0030596607 | E48: =E47/F2 -> 0.0036926939 | F48: =F47/F2 -> 0.0041991205 | H48: DEPILADA | I48: 200 | K48: =K47/M2 -> 0.0027543975 | L48: =L47/M2 -> 0.0033242729 | M48: =M47/M2 -> 0.0037801731
A49: ETIQUETA | B49: 200 | H49: ETIQUETA | I49: 200
A50: BOLSA | B50: 100 | H50: BOLSA | I50: 100
A51: HILO | B51: =B11 -> 300 | D51: 0.4 | E51: 0.6 | F51: 0.9 | H51: HILO | I51: =I11 -> 300 | K51: 0.4 | L51: 0.6 | M51: 0.9
A52: MARQUILLA | B52: 750 | D52: =B54*1.45 -> 11.626711 | E52: =B54*1.75 -> 14.032237 | F52: =B54*1.99 -> 15.956658 | H52: MARQUILLA | I52: 750 | K52: =I54*1.45 -> 10.466711 | L52: =I54*1.75 -> 12.632237 | M52: =I54*1.99 -> 14.364658
A53: GASTOS OPERATIVOS | B53: =B13 -> 4000 | D53: =D52/F2 -> 0.0030596607 | E53: =E52/F2 -> 0.0036926939 | F53: =F52/F2 -> 0.0041991205 | H53: GASTOS OPERATIVOS | I53: =I13 -> 4000 | K53: =K52/M2 -> 0.0027543975 | L53: =L52/M2 -> 0.0033242729 | M53: =M52/M2 -> 0.0037801731
B54: =SUM(B41:B53)/F41 -> 8.0184211 | I54: =SUM(I41:I53)/F41 -> 7.2184211
A58: SUETER CABALLERO | C58: CON VINIL PQÑO
A59: TELA DE MONO | B59: =B20 -> 18240
A60: CORTE | B60: 500
A61: COSTURA | B61: 3000 | D61: +5 DOC | E61: 1 A 5 DOC | F61: DETAL
A62: VINIL | B62: 4000 | D62: =D68 -> 12.607368 | E62: =E68 -> 15.215789 | F62: =F68 -> 17.302526
A63: PLANCHA | B63: 500 | D63: =D62/F2 -> 0.0033177285 | E63: =E62/F2 -> 0.0040041551 | F63: =F62/F2 -> 0.0045532964
A64: CORDON | B64: 1000
A65: CORTE DEL PLOTTER | B65: 200
A66: DEPILADA | B66: 200
A67: ETIQUETA | B67: 200 | D67: 0.4 | E67: 0.6 | F67: 0.9
A68: BOLSA | B68: 100 | D68: =B72*1.45 -> 12.607368 | E68: =B72*1.75 -> 15.215789 | F68: =B72*1.99 -> 17.302526
A69: HILO | B69: =B30 -> 350 | D69: =D68/F2 -> 0.0033177285 | E69: =E68/F2 -> 0.0040041551 | F69: =F68/F2 -> 0.0045532964
A70: MARQUILLA | B70: 750
A71: GASTOS OPERATIVOS | B71: =B32 -> 4000
B72: =SUM(B59:B71)/F41 -> 8.6947368
A78: SUETER DAMA | D78: CON VINIL MEDIANO | H78: SUETER NIÑO | K78: NIÑO CON VINIL MEDIANO
A79: TELA DE MONO | B79: =B2 -> 16720 | H79: TELA DE MONO | I79: =I2 -> 13680
A80: CORTE | B80: 1000 | H80: CORTE | I80: 1000
A81: COSTURA | B81: 4500 | H81: COSTURA | I81: 4500
A82: PLANCHA | B82: 1000 | D82: +5 DOC | E82: 1 A 5 DOC | F82: DETAL | H82: PLANCHA | I82: 1000 | K82: +5 DOC | L82: 1 A 5 DOC | M82: DETAL
A83: VINIL 15 CMS | B83: 4000 | D83: =D89 -> 50779 | E83: =E89 -> 61285 | F83: =F89 -> 69689.8 | H83: VINIL 15 CMS | I83: 4000 | K83: =K89 -> 46371 | L83: =L89 -> 55965 | M83: =M89 -> 63640.2
A84: DISEÑO | B84: 2000 | D84: =D83/F2 -> 13.362895 | E84: =E83/F2 -> 16.127632 | F84: =F83/F2 -> 18.339421 | H84: DISEÑO | I84: 2000 | K84: =K83/M2 -> 12.202895 | L84: =L83/M2 -> 14.727632 | M84: =M83/M2 -> 16.747421
A85: CORTE DEL PLOTTER | B85: 200 | H85: CORTE DEL PLOTTER | I85: 200
A86: DEPILADA | B86: 200 | H86: DEPILADA | I86: 200
A87: ETIQUETA | B87: 200 | H87: ETIQUETA | I87: 200
A88: BOLSA | B88: 100 | D88: 0.4 | E88: 0.6 | F88: 0.9 | H88: BOLSA | I88: 100 | K88: 0.4 | L88: 0.6 | M88: 0.9
A89: HILO | B89: 350 | D89: =B92*1.45 -> 50779 | E89: =B92*1.75 -> 61285 | F89: =B92*1.99 -> 69689.8 | H89: HILO | I89: 350 | K89: =I92*1.45 -> 46371 | L89: =I92*1.75 -> 55965 | M89: =I92*1.99 -> 63640.2
A90: MARQUILLA | B90: 750 | D90: =D89/F2 -> 13.362895 | E90: =E89/F2 -> 16.127632 | F90: =F89/F2 -> 18.339421 | H90: MARQUILLA | I90: 750 | K90: =K89/M2 -> 12.202895 | L90: =L89/M2 -> 14.727632 | M90: =M89/M2 -> 16.747421
A91: GASTOS OPERATIVOS | B91: 4000 | H91: GASTOS OPERATIVOS | I91: 4000
B92: =SUM(B79:B91) -> 35020 | I92: =SUM(I79:I91) -> 31980
A98: SUETER CABALLERO | D98: CON VINIL MEDIANO
A99: TELA DE MONO | B99: =B20 -> 18240
A100: CORTE | B100: 1000
A101: COSTURA | B101: 4500 | D101: +5 DOC | E101: 1 A 5 DOC | F101: DETAL
A102: PLANCHA | B102: 1000 | D102: =D108 -> 52983 | E102: =E108 -> 63945 | F102: =F108 -> 72714.6
A103: VINIL 15 CMS | B103: 4000 | D103: =D102/F2 -> 13.942895 | E103: =E102/F2 -> 16.827632 | F103: =F102/F2 -> 19.135421
A104: DISEÑO | B104: 2000
A105: CORTE DEL PLOTTER | B105: 200
A106: DEPILADA | B106: 200
A107: ETIQUETA | B107: 200 | D107: 0.4 | E107: 0.6 | F107: 0.9
A108: BOLSA | B108: 100 | D108: =B112*1.45 -> 52983 | E108: =B112*1.75 -> 63945 | F108: =B112*1.99 -> 72714.6
A109: HILO | B109: 350 | D109: =D108/F2 -> 13.942895 | E109: =E108/F2 -> 16.827632 | F109: =F108/F2 -> 19.135421
A110: MARQUILLA | B110: 750
A111: GASTOS OPERATIVOS | B111: 4000
B112: =SUM(B99:B111) -> 36540

Sheet BUZO
B1: MUSELINA | E1: VINIL PÑO | I1: MUSELINA | K1: TODO SUBLIMADO | P1: LICRA | R1: COLORES | W1: LICRA | X1: sublimacion total | AD1: MICRO | AF1: VINIL PÑO | AK1: MICRO | AL1: TODO SUBLIMADO | AR1: ALGODÓN
B2: BUZO DAMA | I2: BUZO DAMA | P2: BUZO DAMA | S2: VINIL PÑO | W2: BUZO DAMA | AD2: BUZO DAMA | AK2: BUZO DAMA | AR2: BUZO DAMA
B3: TELA | C3: =0.9*1.8*F3 -> 6480 | F3: 4000 | I3: TELA | J3: =1.1*1.6*F3 -> 7040 | P3: TELA | Q3: =0.9*4*F3 -> 14400 | W3: TELA | X3: =1.2*4*F3 -> 19200 | AD3: TELA | AE3: =1*2.3*F3 -> 9200 | AK3: TELA | AL3: =1*3*F3 -> 12000 | AR3: TELA | AS3: =1*5.31*F3 -> 21240
B4: CORTE | C4: 500 | I4: CORTE | J4: 700 | P4: CORTE | Q4: 700 | W4: CORTE | X4: 700 | AD4: CORTE | AE4: 500 | AK4: CORTE | AL4: 700 | AR4: CORTE | AS4: 700
B5: COSTURA | C5: 2000 | E5: BUZO REPLICA | I5: COSTURA | J5: 2500 | K5: +5 DOC | L5: 1 A 5 DOC | M5: DETAL | P5: COSTURA | Q5: 2500 | W5: COSTURA | X5: 2500 | AD5: COSTURA | AE5: 2500 | AK5: COSTURA | AL5: 2500 | AR5: COSTURA | AS5: 2500
B6: VINIL | C6: 500 | D6: +5 DOC | E6: 1 A 5 DOC | F6: DETAL | I6: PLANCHA | J6: 2000 | K6: =K12 -> 11.704 | L6: =L12 -> 14.63 | M6: =M12 -> 16.6364 | P6: VINIL | Q6: 5000 | S6: BUZO LICRA DAMA | W6: PLANCHA | X6: 3000 | AD6: VINIL | AE6: 1000 | AK6: SUBIMACION | AL6: =15000/1.3 -> 11538.462 | AR6: PLANCHA | AS6: 1000
B7: PLANCHA | C7: 500 | D7: =D11 -> 4.814 | E7: =E11 -> 5.81 | F7: =F11 -> 6.6068 | I7: SUBLIMACION | J7: =1.3*11000 -> 14300 | P7: PLANCHA | Q7: 500 | R7: +5 DOC | S7: 1 A 5 DOC | T7: DETAL | W7: SUBLIMACION | X7: =15000/1.1 -> 13636.364 | Y7: +5 DOC | Z7: 1 A 5 DOC | AA7: DETAL | AD7: PLANCHA | AE7: 500 | AF7: +5 DOC | AG7: 1 A 5 DOC | AH7: DETAL | AK7: PLANCHA | AL7: 3000 | AM7: +5 DOC | AN7: 1 A 5 DOC | AO7: DETAL | AR7: VINIL 15 CMS | AS7: 1500 | AT7: +5 DOC | AU7: 1 A 5 DOC | AV7: DETAL
B8: DISEÑO | C8: 0 | I8: DISEÑO | J8: 1000 | P8: DISEÑO | Q8: 0 | R8: =R12 -> 10.385625 | S8: =S12 -> 11.818125 | T8: =T12 -> 15.04125 | W8: DISEÑO | X8: 2000 | Y8: =Y13 -> 16.833182 | Z8: =Z13 -> 20.315909 | AA8: =AA13 -> 23.102091 | AD8: DISEÑO | AE8: 0 | AF8: =AF13 -> 5.8 | AG8: =AG13 -> 6.6 | AH8: =AH13 -> 7.96 | AK8: VINIL | AL8: 0 | AM8: =AM12 -> 13.462692 | AN8: =AN12 -> 16.248077 | AO8: =AO12 -> 18.476385 | AR8: DISEÑO | AS8: =X8 -> 2000 | AT8: =AT13 -> 12.44825 | AU8: =AU13 -> 15.02375 | AV8: =AV13 -> 17.08415
B9: CORTE DEL PLOTTER | C9: 200 | I9: CORTE DEL PLOTTER | J9: 300 | P9: CORTE DEL PLOTTER | Q9: 200 | W9: CORTE DEL PLOTTER | X9: 0 | AD9: CORTE DEL PLOTTER | AE9: 0 | AK9: DISEÑO | AL9: 2000 | AR9: CORTE DEL PLOTTER | AS9: =X9 -> 0
B10: DEPILADA | C10: 50 | D10: 0.4 | E10: 0.6 | F10: 0.9 | I10: DEPILADA | J10: 200 | P10: DEPILADA | Q10: 200 | W10: DEPILADA | X10: 0 | AD10: DEPILADA | AE10: 0 | AK10: CORTE DEL PLOTTER | AL10: 0 | AR10: DEPILADA | AS10: =X10 -> 0
B11: ETIQUETA | C11: 200 | D11: =C16*1.45 -> 4.814 | E11: =C16*1.75 -> 5.81 | F11: =C16*1.99 -> 6.6068 | I11: ETIQUETA | J11: 200 | K11: 0.4 | L11: 0.6 | M11: 0.9 | P11: ETIQUETA | Q11: 200 | R11: 0.4 | S11: 0.6 | T11: 0.9 | W11: ETIQUETA | X11: 200 | AD11: ETIQUETA | AE11: 0 | AK11: DEPILADA | AL11: 0 | AM11: 0.4 | AN11: 0.6 | AO11: 0.9 | AR11: ETIQUETA | AS11: 200
B12: BOLSA | C12: 100 | I12: BOLSA | J12: 100 | K12: =J16*1.4 -> 11.704 | L12: =J16*1.75 -> 14.63 | M12: =J16*1.99 -> 16.6364 | P12: BOLSA | Q12: 100 | R12: =Q16*1.45 -> 10.385625 | S12: =Q16*1.65 -> 11.818125 | T12: =Q16*2.1 -> 15.04125 | W12: BOLSA | X12: 100 | Y12: 0.4 | Z12: 0.6 | AA12: 0.9 | AD12: BOLSA | AE12: 0 | AF12: 0.4 | AG12: 0.6 | AH12: 0.9 | AK12: ETIQUETA | AL12: 200 | AM12: =AL17*1.45 -> 13.462692 | AN12: =AL17*1.75 -> 16.248077 | AO12: =AL17*1.99 -> 18.476385 | AR12: BOLSA | AS12: 100 | AT12: 0.4 | AU12: 0.6 | AV12: 0.9
B13: HILO | C13: 250 | I13: HILO | J13: 350 | P13: HILO | Q13: 350 | W13: HILO | X13: =J13 -> 350 | Y13: =X16*1.45 -> 16.833182 | Z13: =X16*1.75 -> 20.315909 | AA13: =X16*1.99 -> 23.102091 | AD13: HILO | AE13: =C13 -> 250 | AF13: =AE16*1.45 -> 5.8 | AG13: =AE16*1.65 -> 6.6 | AH13: =AE16*1.99 -> 7.96 | AK13: BOLSA | AL13: 100 | AR13: HILO | AS13: =X13 -> 350 | AT13: =AS16*1.45 -> 12.44825 | AU13: =AS16*1.75 -> 15.02375 | AV13: =AS16*1.99 -> 17.08415
B14: MARQUILLA | C14: 500 | I14: MARQUILLA | J14: 750 | P14: MARQUILLA | Q14: 500 | W14: MARQUILLA | X14: =J14 -> 750 | AD14: MARQUILLA | AE14: 50 | AK14: HILO | AL14: 350 | AR14: MARQUILLA | AS14: =X14 -> 750
B15: GASTOS OPERATIVOS | C15: 2000 | I15: GASTOS OPERATIVOS | J15: 4000 | P15: GASTOS OPERATIVOS | Q15: 4000 | W15: GASTOS OPERATIVOS | X15: =J15 -> 4000 | AD15: GASTOS OPERATIVOS | AE15: =C15 -> 2000 | AK15: MARQUILLA | AL15: 750 | AR15: GASTOS OPERATIVOS | AS15: =X15 -> 4000
C16: =SUM(C3:C15)/F3 -> 3.32 | J16: =SUM(J3:J15)/F3 -> 8.36 | Q16: =SUM(Q3:Q15)/F3 -> 7.1625 | X16: =SUM(X3:X15)/F3 -> 11.609091 | AE16: =SUM(AE3:AE15)/F3 -> 4 | AK16: GASTOS OPERATIVOS | AL16: 4000 | AS16: =SUM(AS3:AS15)/F3 -> 8.585
AL17: =SUM(AL3:AL16)/F3 -> 9.2846154
B20: MUSELINA | E20: VINIL PÑO | I20: MUSELINA | K20: TODO SUBLIMADO | P20: LICRA | R20: COLORES | W20: LICRA | X20: sublimacion total | AD20: MICRO | AF20: VINIL PÑO | AK20: MICRO | AM20: TODO SUBLIMADO
B21: BUZO NIÑO | I21: BUZO NIÑO | P21: BUZO NIÑO | S21: NIÑOS PÑO | W21: BUZO NIÑO | AD21: BUZO NIÑO | AK21: BUZO NIÑO
B22: TELA | C22: =0.7*1.6*F22 -> 4256 | F22: 3800 | I22: TELA | J22: =0.8*1.2*F3 -> 3840 | P22: TELA | Q22: =0.9*4*F3 -> 14400 | W22: TELA | X22: =0.5*4*F3/1.5 -> 5333.3333 | AD22: TELA | AE22: =0.85*3*F22 -> 9690 | AK22: TELA | AL22: =0.7*2*F22 -> 5320
B23: CORTE | C23: 500 | I23: CORTE | J23: 700 | P23: CORTE | Q23: 700 | S23: VINIL PÑO | W23: CORTE | X23: 700 | AD23: CORTE | AE23: 700 | AK23: CORTE | AL23: 700
B24: COSTURA | C24: 2000 | I24: COSTURA | J24: 2500 | P24: COSTURA | Q24: 2500 | W24: COSTURA | X24: 2500 | AD24: COSTURA | AE24: 2500 | AK24: COSTURA | AL24: 2500
B25: VINIL | C25: 500 | D25: +5 DOC | E25: 1 A 5 DOC | F25: DETAL | I25: SUBLIMACION | J25: =0.8*13000 -> 10400 | K25: +5 DOC | L25: 1 A 5 DOC | M25: DETAL | P25: VINIL | Q25: 2000 | S25: BUZO LICRA NIÑO | W25: SUBIMACION | X25: =0.5*10000 -> 5000 | AD25: VINIL | AE25: 500 | AK25: SUBLIMACION TOTAL | AL25: =0.7*10000 -> 7000
B26: PLANCHA | C26: 500 | D26: =D30 -> 4.0078 | E26: =E30 -> 4.837 | F26: =F30 -> 5.50036 | I26: PLANCHA | J26: 3000 | K26: =K30 -> 9.928875 | L26: =L30 -> 11.983125 | M26: =M30 -> 13.626525 | P26: PLANCHA | Q26: 0 | R26: +5 DOC | S26: 1 A 5 DOC | T26: DETAL | W26: PLANCHA | X26: 2000 | Y26: +5 DOC | Z26: 1 A 5 DOC | AA26: DETAL | AD26: PLANCHA | AE26: 1000 | AF26: +5 DOC | AG26: 1 A 5 DOC | AH26: DETAL | AK26: PLANCHA | AL26: 1000 | AM26: +5 DOC | AN26: 1 A 5 DOC | AO26: DETAL
B27: DISEÑO | C27: 0 | I27: DISEÑO | J27: 2000 | P27: DISEÑO | Q27: 1000 | R27: =R31 -> 9.38875 | S27: =S31 -> 11.0075 | T27: =T31 -> 13.5975 | W27: VINIL | X27: 0 | Y27: =Y32 -> 7.2802083 | Z27: =Z32 -> 8.7864583 | AA27: =AA32 -> 9.9914583 | AD27: DISEÑO | AE27: 0 | AF27: =AF32 -> 6.412625 | AG27: =AG32 -> 7.739375 | AH27: =AH32 -> 8.800775 | AK27: DISEÑO | AL27: 1000 | AM27: =AM31 -> 8.1635 | AN27: =AN31 -> 9.008 | AO27: =AO31 -> 11.2037
B28: CORTE DEL PLOTTER | C28: 200 | I28: CORTE DEL PLOTTER | J28: 200 | P28: CORTE DEL PLOTTER | Q28: 200 | W28: DISEÑO | X28: 0 | AD28: CORTE DEL PLOTTER | AE28: =C28 -> 200 | AK28: CORTE DEL PLOTTER | AL28: 0
B29: DEPILADA | C29: 50 | D29: 0.4 | E29: 0.6 | F29: 0.9 | I29: DEPILADA | J29: 200 | K29: 0.4 | L29: 0.6 | M29: 0.9 | P29: DEPILADA | Q29: 200 | W29: CORTE DEL PLOTTER | X29: 0 | AD29: DEPILADA | AE29: =C29 -> 50 | AK29: DEPILADA | AL29: 0
B30: ETIQUETA | C30: 200 | D30: =C35*1.45 -> 4.0078 | E30: =C35*1.75 -> 4.837 | F30: =C35*1.99 -> 5.50036 | I30: ETIQUETA | J30: 200 | K30: =J35*1.45 -> 9.928875 | L30: =J35*1.75 -> 11.983125 | M30: =J35*1.99 -> 13.626525 | P30: ETIQUETA | Q30: 200 | R30: 0.4 | S30: 0.6 | T30: 0.9 | W30: DEPILADA | X30: 0 | AD30: ETIQUETA | AE30: 200 | AK30: ETIQUETA | AL30: 200 | AM30: 0.4 | AN30: 0.6 | AO30: 0.9
B31: BOLSA | C31: 100 | I31: BOLSA | J31: 100 | P31: BOLSA | Q31: 100 | R31: =Q35*1.45 -> 9.38875 | S31: =Q35*1.7 -> 11.0075 | T31: =Q35*2.1 -> 13.5975 | W31: ETIQUETA | X31: 200 | Y31: 0.4 | Z31: 0.6 | AA31: 0.9 | AD31: BOLSA | AE31: 100 | AF31: 0.4 | AG31: 0.6 | AH31: 0.9 | AK31: BOLSA | AL31: 100 | AM31: =AL35*1.45 -> 8.1635 | AN31: =AL35*1.6 -> 9.008 | AO31: =AL35*1.99 -> 11.2037
B32: HILO | C32: 250 | I32: HILO | J32: 250 | P32: HILO | Q32: 100 | W32: BOLSA | X32: 0 | Y32: =X36*1.45 -> 7.2802083 | Z32: =X36*1.75 -> 8.7864583 | AA32: =X36*1.99 -> 9.9914583 | AD32: HILO | AE32: =C32 -> 250 | AF32: =AE35*1.45 -> 6.412625 | AG32: =AE35*1.75 -> 7.739375 | AH32: =AE35*1.99 -> 8.800775 | AK32: HILO | AL32: 250
B33: MARQUILLA | C33: 500 | I33: MARQUILLA | J33: 0 | P33: MARQUILLA | Q33: 500 | W33: HILO | X33: 350 | AD33: MARQUILLA | AE33: 500 | AK33: MARQUILLA | AL33: 750
B34: GASTOS OPERATIVOS | C34: 2000 | I34: GASTOS OPERATIVOS | J34: 4000 | P34: GASTOS OPERATIVOS | Q34: 4000 | W34: MARQUILLA | X34: 0 | AD34: GASTOS OPERATIVOS | AE34: =C34 -> 2000 | AK34: GASTOS OPERATIVOS | AL34: 3700
C35: =SUM(C22:C34)/F3 -> 2.764 | J35: =SUM(J22:J34)/F3 -> 6.8475 | Q35: =SUM(Q22:Q34)/F3 -> 6.475 | W35: GASTOS OPERATIVOS | X35: 4000 | AE35: =SUM(AE22:AE34)/F3 -> 4.4225 | AL35: =SUM(AL22:AL34)/F3 -> 5.63
X36: =SUM(X22:X35)/F3 -> 5.0208333
B39: MUSELINA | I39: MUSELINA | K39: TODO SUBLIMADO | P39: LICRA | R39: COLORES | W39: LICRA | X39: sublimacion total | AD39: MICRO | AF39: VINIL PÑO | AK39: MICRO | AL39: TODO SUBLIMADO | AR39: ALGODÓN | AY39: ALGODÓN
B40: BUZO CABALLERO | E40: VINIL PÑO | I40: BUZO CABALLERO | P40: BUZO | R40: CABALLERO | W40: BUZO CABALLERO | AD40: BUZO CABALLERO | AK40: BUZO CABALLERO | AR40: BUZO CABALLERO | AY40: BUZO CABALLERO
B41: TELA | C41: =2*1.3*F3 -> 10400 | I41: TELA | J41: =1.5*1.2*4000 -> 7200 | P41: TELA | Q41: =1.5*1*F3 -> 6000 | W41: TELA | X41: =2*6*F3 -> 48000 | AD41: TELA | AE41: =1.5*2*F3 -> 12000 | AK41: TELA | AL41: =1.5*2*F3 -> 12000 | AR41: TELA | AS41: =1.5*5.31*F3 -> 31860 | AY41: TELA | AZ41: =1.5*5.31*F3 -> 31860
B42: CORTE | C42: 700 | I42: CORTE | J42: 1000 | K42: +5 DOC | L42: 1 A 5 DOC | M42: DETAL | P42: CORTE | Q42: 1400 | S42: VINIL PÑO | W42: CORTE | X42: 1500 | AD42: CORTE | AE42: 700 | AK42: CORTE | AL42: 700 | AR42: CORTE | AS42: 700 | AY42: CORTE | AZ42: 700
B43: COSTURA | C43: 3500 | I43: COSTURA | J43: 4500 | K43: =K48 -> 13.25625 | L43: =L48 -> 15.02375 | M43: =M48 -> 17.586625 | P43: COSTURA | Q43: 4500 | W43: COSTURA | X43: 8000 | AD43: COSTURA | AE43: 3500 | AK43: COSTURA | AL43: 3500 | AR43: COSTURA | AS43: 2500 | AY43: COSTURA | AZ43: 2500 | BA43: +5 DOC | BB43: 1 A 5 DOC | BC43: DETAL
B44: VINIL | C44: 1500 | D44: +5 DOC | E44: 1 A 5 DOC | F44: DETAL | I44: PLANCHA | J44: 2000 | P44: VINIL | Q44: 4500 | W44: PLANCHA | X44: 5000 | AD44: PLANCHA | AE44: 1000 | AK44: SUBIMACION | AL44: =1.5*11000 -> 16500 | AR44: PLANCHA | AS44: 0 | AY44: PLANCHA | AZ44: 1000 | BA44: =BA49 -> 16.0805 | BB44: =BB49 -> 19.4075 | BC44: =BC49 -> 22.0691
B45: PLANCHA | C45: 1000 | D45: =D50 -> 7.58875 | E45: =E50 -> 10.215625 | F45: =F50 -> 11.616625 | I45: SUBLIMACION | J45: =1.5*9500 -> 14250 | P45: PLANCHA | Q45: 2000 | R45: +5 DOC | S45: 1 A 5 DOC | T45: DETAL | W45: DISEÑO | X45: 2000 | AD45: VINIL | AE45: 3000 | AF45: +5 DOC | AG45: 1 A 5 DOC | AH45: DETAL | AK45: PLANCHA | AL45: 2000 | AM45: +5 DOC | AN45: 1 A 5 DOC | AO45: DETAL | AR45: DISEÑO | AS45: 0 | AT45: +5 DOC | AU45: 1 A 5 DOC | AV45: DETAL | AY45: VINIL 15 CMS | AZ45: 1500
B46: DISEÑO | C46: 2000 | I46: DISEÑO | J46: 2000 | P46: DISEÑO | Q46: 1000 | R46: =R51 -> 9.28125 | S46: =S51 -> 10.209375 | T46: =T51 -> 12.99375 | W46: SUBLIMACION | X46: 13000 | Y46: +5 DOC | Z46: 1 A 5 DOC | AA46: DETAL | AD46: DISEÑO | AE46: 0 | AF46: =AF52 -> 8.96 | AG46: =AG52 -> 11.2 | AH46: =AH52 -> 12.736 | AK46: VINIL | AL46: 0 | AM46: =AM51 -> 14.8625 | AN46: =AN51 -> 16.9125 | AO46: =AO51 -> 19.475 | AR46: CORTE DEL PLOTTER | AS46: 0 | AT46: =AT50 -> 14.648625 | AU46: =AU50 -> 17.679375 | AV46: =AV50 -> 20.103975 | AY46: DISEÑO | AZ46: 1000
B47: CORTE DEL PLOTTER | C47: 100 | I47: CORTE DEL PLOTTER | J47: 0 | K47: 0.4 | L47: 0.6 | M47: 0.9 | P47: CORTE DEL PLOTTER | Q47: 200 | W47: CORTE DEL PLOTTER | X47: 0 | Y47: =Y52 -> 29.90625 | Z47: =Z52 -> 36.09375 | AA47: =AA52 -> 41.04375 | AD47: CORTE DEL PLOTTER | AE47: 500 | AK47: DISEÑO | AL47: 2000 | AR47: DEPILADA | AS47: 0 | AY47: CORTE DEL PLOTTER | AZ47: 200
B48: DEPILADA | C48: 100 | I48: CIERRES | J48: 0 | K48: =J54*1.5 -> 13.25625 | L48: =J54*1.7 -> 15.02375 | M48: =J54*1.99 -> 17.586625 | P48: DEPILADA | Q48: 200 | W48: DEPILADA | X48: 0 | AD48: DEPILADA | AE48: 50 | AK48: CORTE DEL PLOTTER | AL48: 0 | AR48: ETIQUETA | AS48: 200 | AY48: DEPILADA | AZ48: 200 | BA48: 0.4 | BB48: 0.6 | BC48: 0.9
B49: ETIQUETA | C49: 100 | D49: 0.4 | E49: 0.6 | F49: 0.9 | I49: ETIQUETA | J49: 100 | P49: ETIQUETA | Q49: 300 | R49: =R46/F3 -> 0.0023203125 | S49: =S46/F3 -> 0.0025523437 | T49: =T46/F3 -> 0.0032484375 | W49: ETIQUETA | X49: 200 | AD49: ETIQUETA | AE49: 200 | AK49: DEPILADA | AL49: 0 | AR49: BOLSA | AS49: 100 | AT49: 0.4 | AU49: 0.6 | AV49: 0.9 | AY49: ETIQUETA | AZ49: 200 | BA49: =AZ54*1.45 -> 16.0805 | BB49: =AZ54*1.75 -> 19.4075 | BC49: =AZ54*1.99 -> 22.0691
B50: BOLSA | C50: 100 | D50: =C54*1.3 -> 7.58875 | E50: =C54*1.75 -> 10.215625 | F50: =C54*1.99 -> 11.616625 | I50: BOLSA | J50: 0 | P50: BOLSA | Q50: 100 | R50: 0.4 | S50: 0.6 | T50: 0.9 | W50: BOLSA | X50: 100 | AD50: BOLSA | AE50: 100 | AK50: ETIQUETA | AL50: 200 | AM50: 0.4 | AN50: 0.6 | AO50: 0.9 | AR50: HILO | AS50: 300 | AT50: =AS53*1.45 -> 14.648625 | AU50: =AS53*1.75 -> 17.679375 | AV50: =AS53*1.99 -> 20.103975 | AY50: BOLSA | AZ50: 100
B51: HILO | C51: 350 | I51: HILO | J51: 250 | P51: HILO | Q51: 350 | R51: =Q54*1.5 -> 9.28125 | S51: =Q54*1.65 -> 10.209375 | T51: =Q54*2.1 -> 12.99375 | W51: HILO | X51: 250 | Y51: 0.4 | Z51: 0.6 | AA51: 0.9 | AD51: HILO | AE51: =C51 -> 350 | AF51: 0.4 | AG51: 0.6 | AH51: 0.9 | AK51: BOLSA | AL51: 100 | AM51: =AL55*1.45 -> 14.8625 | AN51: =AL55*1.65 -> 16.9125 | AO51: =AL55*1.9 -> 19.475 | AR51: MARQUILLA | AS51: 750 | AY51: HILO | AZ51: 350
B52: MARQUILLA | C52: 0 | I52: MARQUILLA | J52: 50 | P52: MARQUILLA | Q52: 500 | W52: MARQUILLA | X52: 750 | Y52: =X54*1.45 -> 29.90625 | Z52: =X54*1.75 -> 36.09375 | AA52: =X54*1.99 -> 41.04375 | AD52: MARQUILLA | AE52: 500 | AF52: =AE54*1.4 -> 8.96 | AG52: =AE54*1.75 -> 11.2 | AH52: =AE54*1.99 -> 12.736 | AK52: HILO | AL52: 250 | AR52: GASTOS OPERATIVOS | AS52: 4000 | AY52: MARQUILLA | AZ52: 750
B53: GASTOS OPERATIVOS | C53: 3500 | D53: =C54+1 -> 6.8375 | I53: GASTOS OPERATIVOS | J53: 4000 | P53: GASTOS OPERATIVOS | Q53: 3700 | W53: GASTOS OPERATIVOS | X53: 3700 | AD53: GASTOS OPERATIVOS | AE53: 3700 | AK53: MARQUILLA | AL53: 50 | AS53: =SUM(AS41:AS52)/F3 -> 10.1025 | AY53: GASTOS OPERATIVOS | AZ53: 4000
C54: =SUM(C41:C53)/F3 -> 5.8375 | J54: =SUM(J41:J53)/F3 -> 8.8375 | Q54: =SUM(Q41:Q53)/F3 -> 6.1875 | X54: =SUM(X41:X53)/F3 -> 20.625 | AE54: =SUM(AE41:AE53)/F3 -> 6.4 | AF54: =AF52-AE54 -> 2.56 | AK54: GASTOS OPERATIVOS | AL54: 3700 | AZ54: =SUM(AZ41:AZ53)/F3 -> 11.09
AL55: =SUM(AL41:AL54)/F3 -> 10.25

Sheet FALDA SHORT LICRA
A2: FALDA SHORT | C2: VINIL PÑO
A3: DAMA LICRA
A4: TELA | B4: =1.5*5*4000 -> 30000
A5: CORTE | B5: 700
A6: COSTURA | B6: 5000
A7: PLANCHA | B7: 1000
A8: VINIL | B8: 500 | C8: +5 DOC | D8: 1 A 5 DOC | E8: DETAL
A9: DISEÑO | B9: 500 | C9: =C15 -> 15.05 | D9: =D15 -> 18.8125 | E9: =E15 -> 20.425
A10: CORTE DEL PLOTTER | B10: 500
A11: DEPILADA | B11: 50
A12: ETIQUETA | B12: 200
A13: BOLSA | B13: 100
A14: HILO | B14: =250 -> 250 | C14: 0.4 | D14: 0.6 | E14: 0.9
A15: MARQUILLA | B15: 500 | C15: =B17*1.4 -> 15.05 | D15: =B17*1.75 -> 18.8125 | E15: =B17*1.9 -> 20.425
A16: GASTOS OPERATIVOS | B16: 3700
B17: =SUM(B4:B16)/4000 -> 10.75 | C17: =C15-B17 -> 4.3

Sheet CROPTOP LICRA
A2: CROP TOP | D2: VINIL PÑO
A3: LICRA DAMA
A4: TELA | B4: =0.6*5*4000 -> 12000
A5: CORTE | B5: 700
A6: COSTURA | B6: 3500
A7: PLANCHA | B7: 1000
A8: VINIL | B8: 500 | D8: +5 DOC | E8: 1 A 5 DOC | F8: DETAL
A9: DISEÑO | B9: 1000 | D9: =D15 -> 8.47 | E9: =E15 -> 10.5875 | F9: =F15 -> 12.0395
A10: CORTE DEL PLOTTER | B10: 500
A11: DEPILADA | B11: 250
A12: ETIQUETA | B12: 200
A13: BOLSA | B13: 100
A14: HILO | B14: =250 -> 250 | D14: 0.4 | E14: 0.6 | F14: 0.9
A15: MARQUILLA | B15: 500 | D15: =B17*1.4 -> 8.47 | E15: =B17*1.75 -> 10.5875 | F15: =B17*1.99 -> 12.0395
A16: GASTOS OPERATIVOS | B16: 3700
B17: =SUM(B4:B16)/4000 -> 6.05

Sheet MANUBRIO
A2: MANUBRIO | E2: MANUBRIO | H2: MANUBRIO
A3: PEQUEÑO | B3: 510 | E3: MEDIANO | F3: 40 | H3: GRANDE | I3: 65
A4: TELA TRANSPARENTE | B4: =27*2.3 -> 62.1 | E4: TELA TRANSPARENTE | F4: =2.3*3 -> 6.9 | H4: TELA TRANSPARENTE | I4: =2.3*4.5 -> 10.35
A5: TELA LONA | B5: =25*2.75 -> 68.75 | E5: TELA LONA | F5: =2.75*3 -> 8.25 | H5: TELA LONA | I5: =2.75*4 -> 11
A6: COSTURA | B6: =510*2000/4000 -> 255 | E6: COSTURA | F6: =40*2000/4000 -> 20 | H6: COSTURA | I6: =65*2000/4000 -> 32.5
A7: PLANCHA | B7: 25 | E7: PLANCHA | F7: 2 | H7: PLANCHA | I7: 4
A8: CORTE | B8: =510*500/4000 -> 63.75 | E8: CORTE | F8: =40*500/4000 -> 5 | H8: CORTE | I8: =65*500/4000 -> 8.125
A9: HILO | B9: 20 | E9: HILO | F9: 5 | H9: HILO | I9: 5
A10: CIERRE MAGICO | B10: =1500*286/4000 -> 107.25 | E10: CIERRE MAGICO | F10: =1500*28/4000 -> 10.5 | H10: CIERRE MAGICO | I10: =1500*47/4000 -> 17.625
A11: IMPRESIÓN | B11: =27*10000/4000 -> 67.5 | E11: IMPRESIÓN | F11: =3*10000/4000 -> 7.5 | H11: IMPRESIÓN | I11: =4*10000/4000 -> 10
A12: GASTOS OPERATIVOS | B12: =1700/4000*510 -> 216.75 | E12: GASTOS OPERATIVOS | F12: =1700/4000*40 -> 17 | H12: GASTOS OPERATIVOS | I12: =1700/4000*65 -> 27.625
B13: =SUM(B4:B12) -> 886.1 | F13: =SUM(F4:F12) -> 82.15 | I13: =SUM(I4:I12) -> 126.225
B14: =B13/510 -> 1.737451 | F14: =F13/40 -> 2.05375 | I14: =I13/65 -> 1.9419231
E17: =B13+F13+I13 -> 1094.475
E18: =1120/615 -> 1.8211382 | F18: =E18*1.5 -> 2.7317073

Sheet ESTANDARTE 
A2: MUSE/ATLE
A3: SHORT NIÑO | F3: 3800
A4: TELA | B4: =1.4*2*F3 -> 10640
A5: CORTE | B5: 700
A6: COSTURA | B6: 3000
A7: SUBLIMACION | B7: =15000*1.4 -> 21000
A8: TUBO | B8: 8000 | D8: =B18*1.75 -> 22.330921
B9: 0
B10: 0
B11: 0
B12: 0
A13: ETIQUETA | B13: 250
A14: BOLSA | B14: 100
A15: HILO | B15: 350
A16: MARQUILLA | B16: 750
A17: GASTOS OPERATIVOS | B17: 3700
B18: =SUM(B4:B17)/F3 -> 12.760526

Sheet SHORT
A1: MUSE/ATLE | D1: EN BLANCO
A2: SHORT NIÑO | F2: 3800 | G2: DÓLAR
A3: TELA | B3: =0.55*1.8*F2 -> 3762
A4: CORTE | B4: 500
A5: COSTURA | B5: 2000
A6: MALLA | B6: 800
A7: CAUCHO | B7: 800
A8: PLANCHA | B8: 0 | D8: +5 DOC | E8: 1 A 5 DOC | F8: DETAL
A9: DISEÑO | B9: 0 | D9: =D12 -> 4.1675789 | E9: =E12 -> 4.7629474 | F9: =F12 -> 5.656
A10: CORTE DEL PLOTTER | B10: 0
A11: DEPILADA | B11: 0 | D11: 0.4 | E11: 0.6 | F11: 0.9
A12: ETIQUETA | B12: 250 | D12: =B17*1.4 -> 4.1675789 | E12: =B17*1.6 -> 4.7629474 | F12: =B17*1.9 -> 5.656
A13: BOLSA | B13: 100
A14: HILO | B14: 350
A15: MARQUILLA | B15: 750
A16: GASTOS OPERATIVOS | B16: 2000
B17: =SUM(B3:B16)/F2 -> 2.9768421
A21: SHORT DAMA
A22: TELA | B22: =0.6*6/2*F2 -> 6840
A23: CORTE | B23: 700
A24: COSTURA | B24: 2500
A25: MALLA | B25: 0
A26: CAUCHO | B26: 0
A27: PLANCHA | B27: 2000 | D27: +5 DOC | E27: 1 A 5 DOC | F27: DETAL
A28: DISEÑO | B28: 7000 | D28: =D32 -> 8.3226316 | E28: =E32 -> 10.106053 | F28: =F32 -> 11.295
A29: CORTE DEL PLOTTER | B29: 0
A30: DEPILADA | B30: 0
A31: ETIQUETA | B31: 50 | D31: 0.4 | E31: 0.6 | F31: 0.9
A32: BOLSA | B32: 100 | D32: =B36*1.4 -> 8.3226316 | E32: =B36*1.7 -> 10.106053 | F32: =B36*1.9 -> 11.295
A33: HILO | B33: 350
A34: MARQUILLA | B34: 50
A35: GASTOS OPERATIVOS | B35: 3000
B36: =SUM(B22:B35)/F2 -> 5.9447368
D42: EN BLANCO
A43: MUSE/ATLE
A44: SHORT CABALLERO
A45: TELA | B45: =0.8*1.8*F2 -> 5472
A46: CORTE | B46: 500
A47: COSTURA | B47: 1500
A48: MALLA | B48: 0 | D48: +5 DOC | E48: 1 A 5 DOC | F48: DETAL
A49: CAUCHO | B49: 800 | D49: =D54 -> 5.5031316 | E49: =E54 -> 6.6417105 | F49: =F54 -> 7.5525737
A50: PLANCHA | B50: 300
A51: VINIL | B51: 500
A52: CORTE DEL PLOTTER | B52: 100
A53: DEPILADA | B53: 100 | D53: 0.4 | E53: 0.6 | F53: 0.9
A54: ETIQUETA | B54: 200 | D54: =B59*1.45 -> 5.5031316 | E54: =B59*1.75 -> 6.6417105 | F54: =B59*1.99 -> 7.5525737
A55: BOLSA | B55: 100
A56: HILO | B56: 350
A57: MARQUILLA | B57: 500
A58: GASTOS OPERATIVOS | B58: 4000
B59: =SUM(B45:B58)/F2 -> 3.7952632
A63: MUSE/ATLE | D63: CON LOGO Y VINIL#
A64: SHORT NIÑO
A65: TELA | B65: =0.55*1.8*F2 -> 3762
A66: CORTE | B66: 1000
A67: COSTURA | B67: 2500 | D67: +5 DOC | E67: 1 A 5 DOC | F67: DETAL
A68: MALLA | B68: 1000 | D68: =D73 -> 7.3728421 | E68: =E73 -> 8.4261053 | F68: =F73 -> 10.006
A69: CAUCHO | B69: 800
A70: PLANCHA | B70: 1000
A71: VINIL 15 CMS | B71: 3000
A72: DISEÑO | B72: 1000 | D72: 0.4 | E72: 0.6 | F72: 0.9
A73: CORTE DEL PLOTTER | B73: 300 | D73: =B80*1.4 -> 7.3728421 | E73: =B80*1.6 -> 8.4261053 | F73: =B80*1.9 -> 10.006
A74: DEPILADA | B74: 200
A75: ETIQUETA | B75: 250
A76: BOLSA | B76: 100
A77: HILO | B77: 350
A78: MARQUILLA | B78: 750
A79: GASTOS OPERATIVOS | B79: 4000
B80: =SUM(B65:B79)/F2 -> 5.2663158
A84: SHORT DAMA | D84: CON LOGO Y VINIL#
A85: TELA | B85: =0.6*1.8*F2 -> 4104
A86: CORTE | B86: 1000
A87: COSTURA | B87: 2500
A88: MALLA | B88: 1000
A89: CAUCHO | B89: 800
A90: PLANCHA | B90: 1000
A91: VINIL 15 CMS | B91: 3000
A92: DISEÑO | B92: 1000 | D92: +5 DOC | E92: 1 A 5 DOC | F92: DETAL
A93: CORTE DEL PLOTTER | B93: 200 | D93: =D96 -> 7.462 | E93: =E96 -> 8.528 | F93: =F96 -> 10.127
A94: DEPILADA | B94: 200
A95: ETIQUETA | B95: 250 | D95: 0.4 | E95: 0.6 | F95: 0.9
A96: BOLSA | B96: 100 | D96: =B100*1.4 -> 7.462 | E96: =B100*1.6 -> 8.528 | F96: =B100*1.9 -> 10.127
A97: HILO | B97: 350
A98: MARQUILLA | B98: 750
A99: GASTOS OPERATIVOS | B99: 4000
B100: =SUM(B85:B99)/F2 -> 5.33
A105: MUSE/ATLE | D105: CON LOGO Y VINIL#
A106: SHORT CABALLERO
A107: TELA | B107: =0.8*1.8*F2 -> 5472
A108: CORTE | B108: 1000
A109: COSTURA | B109: 2500
A110: MALLA | B110: 0 | D110: +5 DOC | E110: 1 A 5 DOC | F110: DETAL
A111: CAUCHO | B111: 800 | D111: =D115 -> 5.9610263 | E111: =E115 -> 6.9887895 | F111: =F115 -> 8.1809947
A112: PLANCHA | B112: 0
A113: VINIL 15 CMS | B113: 0
A114: DISEÑO | B114: 1000 | D114: 0.4 | E114: 0.6 | F114: 0.9
A115: CORTE DEL PLOTTER | B115: 200 | D115: =B122*1.45 -> 5.9610263 | E115: =B122*1.7 -> 6.9887895 | F115: =B122*1.99 -> 8.1809947
A116: DEPILADA | B116: 200
A117: ETIQUETA | B117: 250
A118: BOLSA | B118: 100
...

Sheet CV TASLAN
F2: TASLAN | AC2: TASLAN
A3: CORTA VIENTO DAMA | D3: CON VINIL PÑO | X3: CORTA VIENTO DAMA | AA3: SUBLIMACION TOTAL
A4: TELA TASLAN | B4: =1.5*5*F4 -> 28500 | F4: 3800 | G4: DÓLAR | X4: TELA TASLAN | Y4: =1.5*3*AC4 -> 17550 | AC4: 3900 | AD4: DÓLAR
A5: CORTE | B5: 700 | K5: Mts | L5: $ | X5: CORTE | Y5: 700
A6: COSTURA | B6: 9000 | I6: TELA DAMA 3 DOC | J6: 1,5S 1,5L | K6: =36*1.6 -> 57.6 | X6: COSTURA | Y6: 4500
A7: CIERRE | B7: 4000 | I7: TELA caballero 6 DOC | J7: 3 M 3 L | K7: =6*12*1.9 -> 136.8 | X7: CIERRE | Y7: 3000
A8: PLANCHA | B8: 500 | D8: CORTA VIENTO DE DAMA IMPERMEABLE | I8: TELA caballero 1 DOC | J8: 1 XL | K8: =12*2.2 -> 26.4 | X8: PLANCHA | Y8: 500 | AA8: CORTA VIENTO DE DAMA IMPERMEABLE
A9: VINIL 15 CMS | B9: 5500 | K9: =SUM(K6:K8) -> 220.8 | L9: =K9*3 -> 662.4 | O9: =120*13 -> 1560 | X9: SUBLIMACION TOTAL | Y9: 15000
A10: DISEÑO | B10: 1000 | D10: +5 DOC | E10: 1 A 5 DOC | F10: DETAL | X10: DISEÑO | Y10: 2000 | AA10: +5 DOC | AB10: 1 A 5 DOC | AC10: DETAL
A11: CORTE DEL PLOTTER | B11: 500 | D11: =D15 -> 21.005921 | E11: =E15 -> 25.351974 | F11: =F15 -> 28.828816 | I11: Cierres | J11: 120 | K11: =2500/4000 -> 0.625 | L11: =K11*J11 -> 75 | X11: ETIQUETA | Y11: 0 | AA11: =AA15 -> 17.883333 | AB11: =AB15 -> 21.583333 | AC11: =AC15 -> 24.543333
A12: DEPILADA | B12: 500 | I12: vinil | J12: 120 | K12: =2000/4000 -> 0.5 | L12: =K12*J12 -> 60 | X12: BOLSA | Y12: 0
A13: ETIQUETA | B13: 0 | I13: costura | J13: =120 -> 120 | K13: 1 | L13: =J13*K13 -> 120 | X13: HILO | Y13: 350
A14: BOLSA | B14: 0 | D14: 0.35 | E14: 0.5 | F14: 0.8 | I14: depilada | J14: 120 | K14: =440/4000 -> 0.11 | L14: =J14*K14 -> 13.2 | N14: =0.11*4000 -> 440 | X14: MARQUILLA | Y14: 500 | AA14: 0.45 | AB14: 0.75 | AC14: 0.99
A15: HILO | B15: 350 | D15: =B18*1.45 -> 21.005921 | E15: =B18*1.75 -> 25.351974 | F15: =B18*1.99 -> 28.828816 | I15: etiqueta | J15: 120 | K15: =200/4000 -> 0.05 | L15: =J15*K15 -> 6 | X15: GASTOS OPERATIVOS | Y15: 4000 | AA15: =Y16*1.45 -> 17.883333 | AB15: =Y16*1.75 -> 21.583333 | AC15: =Y16*1.99 -> 24.543333
A16: MARQUILLA | B16: 500 | I16: corte plotter | J16: 120 | K16: =300/4000 -> 0.075 | L16: =J16*K16 -> 9 | Y16: =SUM(Y4:Y15)/AC4 -> 12.333333
A17: GASTOS OPERATIVOS | B17: 4000 | I17: diseño | J17: 120 | K17: =1000/4000 -> 0.25 | L17: =J17*K17 -> 30
B18: =SUM(B4:B17)/F4 -> 14.486842 | I18: marquilla | J18: 120 | K18: =500/4000 -> 0.125 | L18: =J18*K18 -> 15
I19: corte tela | J19: 120 | K19: =1400/4000 -> 0.35 | L19: =J19*K19 -> 42
L20: =SUM(L9:L19) -> 1032.6
L21: =L20*1.55 -> 1600.53 | M21: =L21/120 -> 13.33775 | N21: =M21*4000 -> 53351
L22: =L21-L20 -> 567.93 | M22: Ganancia
A24: CORTA VIENTO CABALLERO | D24: CON VINIL PÑO | I24: CORTA VIENTO CABALLERO | L24: CON VINIL PÑO | P24: PANTALON DE MONO | S24: CON VINIL PÑO | X24: CORTA VIENTO CABALLERO | AA24: SUBLIMACION TOTAL
A25: TELA TASLAN | B25: =2.2*2.5*F4 -> 20900 | I25: TELA TASLAN | J25: =1.8*3*F4 -> 20520 | P25: TELA TASLAN | Q25: =1.1*3*F4 -> 12540 | X25: TELA TASLAN | Y25: =2.5*3*AC4 -> 29250
A26: CORTE | B26: 700 | I26: CORTE | J26: 700 | P26: CORTE | Q26: =J26 -> 700 | X26: CORTE | Y26: 1500
A27: COSTURA | B27: 5000 | I27: COSTURA | J27: 3500 | P27: COSTURA | Q27: 2500 | X27: COSTURA | Y27: 24000
A28: CIERRE | B28: 1500 | D28: CORTA VIENTO DE CABALLERO IMPERMEABLE | I28: CIERRE | J28: 3500 | L28: CORTA VIENTO DE CABALLERO IMPERMEABLE | P28: CIERRE | Q28: 0 | S28: CORTA VIENTO DE CABALLERO IMPERMEABLE | X28: FORRO | Y28: =2.5*1.3*3700 -> 12025 | AA28: CORTA VIENTO DE CABALLERO IMPERMEABLE
A29: PLANCHA | B29: 1400 | I29: PLANCHA | J29: 2000 | P29: PLANCHA | Q29: 0 | X29: CIERRE | Y29: 1800
A30: VINIL 15 CMS | B30: 4500 | D30: +5 DOC | E30: 1 A 5 DOC | F30: DETAL | I30: SUBLIMACION TOTAL | J30: 0 | L30: +5 DOC | M30: 1 A 5 DOC | N30: DETAL | P30: SUBLIMACION TOTAL | Q30: 0 | S30: +5 DOC | T30: 1 A 5 DOC | U30: DETAL | X30: PLANCHA | Y30: 4000 | AA30: +5 DOC | AB30: 1 A 5 DOC | AC30: DETAL
A31: DISEÑO | B31: 1500 | D31: =D36 -> 15.363158 | E31: =E36 -> 18.106579 | F31: =F36 -> 21.837632 | I31: DISEÑO | J31: 1000 | L31: =L36 -> 12.493684 | M31: =M36 -> 16.818421 | N31: =N36 -> 19.124947 | P31: DISEÑO | Q31: 0 | S31: =S36 -> 6.4452632 | T31: =T36 -> 8.6763158 | U31: =U36 -> 9.8662105 | X31: kalandra | Y31: =1.8*13000 -> 23400 | AA31: =AA34 -> 38.452885 | AB31: =AB34 -> 46.408654 | AC31: =AC34 -> 52.773269
A32: CORTE DEL PLOTTER | B32: 500 | I32: CORTE DEL PLOTTER | J32: 200 | P32: CORTE DEL PLOTTER | Q32: 0 | X32: DISEÑO | Y32: 2000
A33: DEPILADA | B33: 500 | I33: DEPILADA | J33: 200 | P33: DEPILADA | Q33: 0 | X33: ETIQUETA | Y33: 200 | AA33: 0.45 | AB33: 0.75 | AC33: 0.99
A34: ETIQUETA | B34: 250 | I34: ETIQUETA | J34: 50 | P34: ETIQUETA | Q34: 0 | X34: CORDON | Y34: 700 | AA34: =Y38*1.45 -> 38.452885 | AB34: =Y38*1.75 -> 46.408654 | AC34: =Y38*1.99 -> 52.773269
A35: BOLSA | B35: 100 | D35: 0.45 | E35: 0.75 | F35: 0.99 | I35: BOLSA | J35: 150 | L35: 0.4 | M35: 0.65 | N35: 0.9 | P35: BOLSA | Q35: 150 | S35: 0.4 | T35: 0.65 | U35: 0.9 | X35: HILO | Y35: =Y13 -> 350
A36: HILO | B36: =B15 -> 350 | D36: =B39*1.4 -> 15.363158 | E36: =B39*1.65 -> 18.106579 | F36: =B39*1.99 -> 21.837632 | I36: HILO | J36: 200 | L36: =J39*1.3 -> 12.493684 | M36: =J39*1.75 -> 16.818421 | N36: =J39*1.99 -> 19.124947 | P36: HILO | Q36: 200 | S36: =Q39*1.3 -> 6.4452632 | T36: =Q39*1.75 -> 8.6763158 | U36: =Q39*1.99 -> 9.8662105 | X36: MARQUILLA | Y36: 200
A37: MARQUILLA | B37: 500 | I37: MARQUILLA | J37: 500 | P37: MARQUILLA | Q37: 750 | X37: GASTOS OPERATIVOS | Y37: 4000
A38: GASTOS OPERATIVOS | B38: 4000 | I38: GASTOS OPERATIVOS | J38: 4000 | P38: GASTOS OPERATIVOS | Q38: 2000 | Y38: =SUM(Y25:Y37)/AC4 -> 26.519231
B39: =SUM(B25:B38)/F4 -> 10.973684 | J39: =SUM(J25:J38)/F4 -> 9.6105263 | Q39: =SUM(Q25:Q38)/F4 -> 4.9578947
L42: =L36-J39 -> 2.8831579 | P42: =L36+S36 -> 18.938947
L43: =S36-Q39 -> 1.4873684
L44: =SUM(L42:L43)-1.05 -> 3.3205263 | M44: =L44*200 -> 664.10526
A45: Descripción | B45: Precio | C45: Cantd | D45: Total
A46: UNIFORME DE FUTBOL FRANELA TODA SUBLIMADA TEMA MUNDIAL TALLAS 8-14 SHORT LOGO Y NUMERO | B46: 10.5 | C46: 500 | D46: =C46*B46 -> 5250
A48: PESOS | B48: =B46*4000 -> 42000
A49: ABONO 70% ENTREGA 25 DIAS HABILES
A52: Descripción | B52: Precio | C52: Cantd | D52: Total
A53: UNIFORME DE FUTBOL FRANELA TODA SUBLIMADA TEMA MUNDIAL TALLAS 16-S-M SHORT LOGO Y NUMERO | B53: 13 | C53: 500 | D53: =C53*B53 -> 6500
A55: PESOS | B55: =B53*4000 -> 52000
A56: ABONO 70% ENTREGA 25 DIAS HABILES
A59: Descripción | B59: Precio | C59: Cantd | D59: Total
A60: UNIFORME DE FUTBOL FRANELA FRENTE SUBLIMADO TEMA MUNDIAL TALLAS 8-14 SHORT LOGO Y NUMERO | B60: 9 | C60: 500 | D60: =C60*B60 -> 4500
A62: PESOS | B62: =B60*4000 -> 36000
A63: ABONO 70% ENTREGA 25 DIAS HABILES
A65: Descripción | B65: Precio | C65: Cantd | D65: Total
A66: UNIFORME DE FUTBOL FRANELA SOLO FRENTE SUBLIMADA TEMA MUNDIAL TALLAS 16-S-M SHORT LOGO Y NUMERO | B66: 12 | C66: 500 | D66: =C66*B66 -> 6000
A68: PESOS | B68: =B66*4000 -> 48000
A69: ABONO 70% ENTREGA 25 DIAS HABILES

Sheet MOUSE
A2: MOUSE 5MM
A3: MOUSE | F3: 3800
A4: MOUSE | B4: 10000
A5: SUBLIMACION | B5: =1000 -> 1000 | D5: 45 | E5: 70 | F5: 99
A6: PLANCHA | B6: 1000 | D6: =B9*1.45 -> 5.9907895 | E6: =B9*1.7 -> 7.0236842 | F6: =B9*1.99 -> 8.2218421
A7: DISEÑO | B7: 1000
A8: GASTOS OPERATIVOS | B8: 2700
B9: =SUM(B4:B8)/F3 -> 4.1315789

Sheet PAÑOLETA
A2: DELANTAL
A3: UNISEX | F3: 3800
A4: TELA | B4: =0.7*3 -> 2.1
A5: CORTE | B5: =700/F3 -> 0.18421053 | D5: +5 DOC | E5: 1 A 5 DOC | F5: DETAL
A6: COSTURA | B6: =3000/F3 -> 0.78947368 | D6: =D9 -> 10.345263 | E6: =E9 -> 11.084211 | F6: =F9 -> 14.705053
A7: SUBLIMACION | B7: =13000*0.7/2/F3 -> 1.1973684
A8: PLANCHA | B8: =500/F3 -> 0.13157895 | D8: 45 | E8: 75 | F8: 99
A9: DISEÑO | B9: =1500/F3 -> 0.39473684 | D9: =B14*1.4 -> 10.345263 | E9: =B14*1.5 -> 11.084211 | F9: =B14*1.99 -> 14.705053
A10: CORTE DEL PLOTTER | B10: =500/F3 -> 0.13157895
A11: HERRAJES | B11: =5000/F3 -> 1.3157895
A12: HILO | B12: =350/F3 -> 0.092105263
A13: GASTOS OPERATIVOS | B13: =4000/F3 -> 1.0526316
B14: =SUM(B4:B13) -> 7.3894737
A17: bandana de perro
A18: tela | B18: =1.3*3/8*4400 -> 2145
A19: impresión | B19: =1.3*11000/8 -> 1787.5
A20: planchado | B20: 500
A21: confeccion | B21: 1000 | D21: =B23*1.45 -> 8602.125
A22: diseño | B22: 500
B23: =SUM(B18:B22) -> 5932.5

Sheet PROMO
A1: PRODUCTO | B1: MATERIAL | C1: CANTIDAD | D1: PRECIO | E1: PEDIDO | F1: MONTO
A2: GORRA | B2: MALLA | C2: 1
B3: MALLA | C3: 6 A 12
B4: MALLA | C4: 12 O MAS
A5: GORRA | B5: DRILL | C5: 1
B6: DRILL | C6: 6 A 12
B7: DRILL | C7: 12 O MAS
A8: GORRA | B8: DRILL | C8: 1
B9: DRILL | C9: 6 A 12
B10: DRILL | C10: 12 O MAS
A12: PRODUCTO | B12: MATERIAL | C12: CANTIDAD | D12: PRECIO | E12: PEDIDO | F12: MONTO
A13: FRANELA | B13: MICRO | C13: 1
B14: MICRO | C14: 6 A 12
B15: MICRO | C15: 12 O MAS
A16: FRANELA | B16: MUSELINA | C16: 1
B17: MUSELINA | C17: 6 A 12
B18: MUSELINA | C18: 12 O MAS

Sheet CV MEMORY
A2: CORTA VIENTO DAMA | D2: CON VINIL PÑO | I2: DAMA | L2: SUBLIMADA TODA
A3: TELA MEMORY | B3: =1.8*2*F3 -> 13680 | F3: 3800 | G3: DÓLAR | I3: TELA MEMORY | J3: =1.5*2*N3 -> 11400 | N3: 3800
A4: CORTE | B4: 700 | I4: CORTE | J4: 700
A5: COSTURA | B5: 3500 | I5: COSTURA | J5: 4500
A6: CIERRE | B6: 3000 | I6: CIERRE | J6: 3000
A7: PLANCHA | B7: 1000 | D7: CORTA VIENTO DE DAMA IMPERMEABLE | I7: PLANCHA | J7: 3000 | L7: CORTA VIENTO DE DAMA IMPERMEABLE
A8: VINIL 15 CMS | B8: 1000 | I8: SUBLIMACION TOTAL | J8: 13000
A9: DISEÑO | B9: 0 | D9: +5 DOC | E9: 1 A 5 DOC | F9: DETAL | I9: DISEÑO | J9: 2000 | L9: +5 DOC | M9: 1 A 5 DOC | N9: DETAL
A10: CORTE DEL PLOTTER | B10: 200 | D10: =D14 -> 10.867368 | E10: =E14 -> 13.115789 | F10: =F14 -> 14.914526 | I10: CORTE DEL PLOTTER | J10: 0 | L10: =L14 -> 16.331579 | M10: =M14 -> 19.710526 | N10: =N14 -> 22.413684
A11: DEPILADA | B11: 200 | I11: DEPILADA | J11: 0
A12: ETIQUETA | B12: 250 | I12: ETIQUETA | J12: 250
A13: BOLSA | B13: 100 | D13: 0.35 | E13: 0.5 | F13: 0.8 | I13: BOLSA | J13: 100 | L13: 0.35 | M13: 0.5 | N13: 0.8
A14: HILO | B14: 350 | D14: =B17*1.45 -> 10.867368 | E14: =B17*1.75 -> 13.115789 | F14: =B17*1.99 -> 14.914526 | I14: HILO | J14: 350 | L14: =J17*1.45 -> 16.331579 | M14: =J17*1.75 -> 19.710526 | N14: =J17*1.99 -> 22.413684
A15: MARQUILLA | B15: 500 | I15: MARQUILLA | J15: 500
A16: GASTOS OPERATIVOS | B16: 4000 | I16: GASTOS OPERATIVOS | J16: 4000
B17: =SUM(B3:B16)/F3 -> 7.4947368 | J17: =SUM(J3:J16)/N3 -> 11.263158
A19: CORTA VIENTO NIÑO | D19: CON VINIL PÑO | I19: CORTA VIENTO NIÑO | L19: SUBLIMADA TODA
A20: TELA MEMORY | B20: =1.8*1.2*F20 -> 8640 | F20: 4000 | G20: DÓLAR | I20: TELA MEMORY | J20: =1*4*N20 -> 15200 | N20: 3800 | O20: DÓLAR
A21: CORTE | B21: 500 | I21: CORTE | J21: 700
A22: COSTURA | B22: 3500 | I22: COSTURA | J22: 3500
A23: CIERRE | B23: 1200 | I23: CIERRE | J23: 1300
A24: PLANCHA | B24: =1.6*3500 -> 5600 | D24: CORTA VIENTO DE DAMA IMPERMEABLE | I24: PLANCHA | J24: 3000 | L24: CORTA VIENTO DE DAMA IMPERMEABLE
A25: SUBLIMACION | B25: =1.8*6000 -> 10800 | I25: SUBLIMACION TOTAL | J25: 13000
A26: DISEÑO | B26: 300 | D26: +5 DOC | E26: 1 A 5 DOC | F26: DETAL | I26: DISEÑO | J26: 1000 | L26: +5 DOC | M26: 1 A 5 DOC | N26: DETAL
A27: CORDON | B27: 700 | D27: =D31 -> 12.575125 | E27: =E31 -> 15.176875 | F27: =F31 -> 17.258275 | I27: CORTE DEL PLOTTER | J27: 0 | L27: =L31 -> 15.713158 | M27: =M31 -> 19.641447 | N27: =N31 -> 22.335132
A28: CAUCHO | B28: 500 | I28: DEPILADA | J28: 0
A29: ETIQUETA | B29: 250 | I29: ETIQUETA | J29: 0
A30: BOLSA | B30: 100 | D30: 0.35 | E30: 0.5 | F30: 0.8 | I30: BOLSA | J30: 100 | L30: 0.35 | M30: 0.5 | N30: 0.8
A31: HILO | B31: 500 | D31: =B34*1.45 -> 12.575125 | E31: =B34*1.75 -> 15.176875 | F31: =B34*1.99 -> 17.258275 | I31: HILO | J31: 350 | L31: =J34*1.4 -> 15.713158 | M31: =J34*1.75 -> 19.641447 | N31: =J34*1.99 -> 22.335132
A32: MARQUILLA | B32: 100 | I32: MARQUILLA | J32: 500
A33: GASTOS OPERATIVOS | B33: 2000 | I33: GASTOS OPERATIVOS | J33: 4000
B34: =SUM(B20:B33)/F20 -> 8.6725 | J34: =SUM(J20:J33)/N20 -> 11.223684
A36: CORTA VIENTO con Gorro CABALLERO | D36: SUBLIMACION TOTAL | I36: CORTA VIENTO CABALLERO | K36: DELANTERO Y TRASERO SUBLIMADO MANGAS Y GORRO UNICOLOR
A37: TELA MEMORY | B37: =2*1.7*F3 -> 12920 | I37: TELA MEMORY | J37: =2*2*N3 -> 15200
A38: SUBLIMACION | B38: =2*11000 -> 22000 | I38: SUBLIMACION | J38: 0
A39: CORTE | B39: 700 | I39: CORTE | J39: 700
A40: COSTURA | B40: 4500 | I40: COSTURA | J40: 4500
A41: CIERRE | B41: 1500 | D41: CORTA VIENTO DE CABALLERO IMPERMEABLE | I41: CIERRE | J41: 1300 | L41: CORTA VIENTO DE CABALLERO IMPERMEABLE
A42: CORDON | B42: =2*500 -> 1000 | I42: PLANCHA | J42: 1000
A43: VINIL | B43: 0 | D43: +5 DOC | E43: 1 A 5 DOC | F43: DETAL | I43: CORDON | J43: =1000 -> 1000 | L43: +5 DOC | M43: 1 A 5 DOC | N43: DETAL
A44: DISEÑO | B44: 2000 | D44: =D49 -> 17.772632 | E44: =E49 -> 20.311579 | F44: =F49 -> 22.850526 | I44: DISEÑO | J44: 2500 | L44: =L49 -> 11.638158 | M44: =M49 -> 13.243421 | N44: =N49 -> 15.972368
A45: FORRO | B45: 0 | I45: TELA FORRO | J45: 500
A46: PISA CORDON | B46: 100 | I46: PISA CORDON | J46: =100*2 -> 200
A47: OJALETES | B47: =6*20 -> 120 | D47: MAS DE 48 | E47: MAS DE 12 | F47: HASTA 12 | I47: ETIQUETA | J47: =J12 -> 250
A48: CIERRE BOLSILLOS | B48: 0 | D48: 0.35 | E48: 0.5 | F48: 0.8 | I48: BOLSA | J48: 0 | L48: 0.35 | M48: 0.5 | N48: 0.8
A49: HILO | B49: =B14 -> 350 | D49: =B52*1.4 -> 17.772632 | E49: =B52*1.6 -> 20.311579 | F49: =B52*1.8 -> 22.850526 | I49: HILO | J49: =J14 -> 350 | L49: =J52*1.45 -> 11.638158 | M49: =J52*1.65 -> 13.243421 | N49: =J52*1.99 -> 15.972368
A50: MARQUILLA | B50: 50 | I50: MARQUILLA | J50: 0
A51: GASTOS OPERATIVOS | B51: 3000 | I51: GASTOS OPERATIVOS | J51: 3000
B52: =SUM(B37:B51)/F3 -> 12.694737 | D52: =D49-B52 -> 5.0778947 | E52: =D52*36 -> 182.80421 | J52: =SUM(J37:J51)/N3 -> 8.0263158
A54: CORTA VIENTO CABALLERO | D54: VINIL PÑO | I54: CORTA VIENTO CABALLERO | L54: VINIL PÑO
A55: TELA MEMORY | B55: =2*2*F3 -> 15200 | I55: TELA MEMORY | J55: =2*1.7*F3 -> 12920
A56: CORTE | B56: 700 | I56: CORTE | J56: 1000
A57: COSTURA | B57: =B23 -> 1200 | I57: COSTURA | J57: 4500
A58: CIERRE | B58: 3000 | D58: CORTA VIENTO DE CABALLERO IMPERMEABLE | I58: CIERRE | J58: 2000 | L58: CORTA VIENTO DE CABALLERO IMPERMEABLE
A59: PLANCHA | B59: 500 | I59: PLANCHA | J59: =500*4 -> 2000
A60: VINIL 15 CMS | B60: =B26 -> 300 | D60: +5 DOC | E60: 1 A 5 DOC | F60: DETAL | I60: SUBLIMACION TOTAL | J60: =2*11000 -> 22000 | L60: +5 DOC | M60: 1 A 5 DOC | N60: DETAL
A61: DISEÑO | B61: =B27 -> 700 | D61: =D66 -> 10.5125 | E61: =E66 -> 12.6875 | F61: =F66 -> 14.4275 | I61: DISEÑO | J61: 0 | L61: =L66 -> 20.661053 | M61: =M66 -> 22.598026 | N61: =N66 -> 25.180658
A62: CORTE DEL PLOTTER | B62: =B28 -> 500 | I62: CORTE DEL PLOTTER | J62: 0
A63: DEPILADA | B63: =B29 -> 250 | I63: DEPILADA | J63: 0
A64: ETIQUETA | B64: =B30 -> 100 | I64: ETIQUETA | J64: =J30 -> 100
A65: BOLSA | B65: =B31 -> 500 | D65: 0.35 | E65: 0.5 | F65: 0.8 | I65: BOLSA | J65: 100 | L65: 0.35 | M65: 0.5 | N65: 0.8
A66: HILO | B66: =B32 -> 100 | D66: =B69*1.45 -> 10.5125 | E66: =B69*1.75 -> 12.6875 | F66: =B69*1.99 -> 14.4275 | I66: HILO | J66: 250 | L66: =J69*1.6 -> 20.661053 | M66: =J69*1.75 -> 22.598026 | N66: =J69*1.95 -> 25.180658
A67: MARQUILLA | B67: 500 | I67: MARQUILLA | J67: 500
A68: GASTOS OPERATIVOS | B68: 4000 | I68: GASTOS OPERATIVOS | J68: 3700
B69: =SUM(B55:B68)/F3 -> 7.25 | J69: =SUM(J55:J68)/F3 -> 12.913158
A71: CORTA VIENTO sin Gorro CABALLERO | D71: SUBLIMACION TOTAL | I71: CORTA VIENTO CON Gorro CABALLERO | L71: SUBLIMACION TOTAL
A72: TELA MEMORY | B72: =1.2*1.3*4000 -> 6240 | I72: TELA MEMORY | J72: =2.2*1.7*4000 -> 14960
A73: SUBLIMACION | B73: =1.2*8500 -> 10200 | I73: SUBLIMACION | J73: =2.2*10000 -> 22000
A74: CORTE | B74: 700 | I74: CORTE | J74: 1500
A75: PLANCHA | B75: =3*500 -> 1500 | I75: PLANCHA | J75: 3000
A76: COSTURA | B76: 4500 | I76: COSTURA | J76: 6000
A77: CIERRE | B77: 2000 | D77: CORTA VIENTO DE CABALLERO IMPERMEABLE | I77: CIERRE | J77: 1800 | L77: CORTA VIENTO DE CABALLERO IMPERMEABLE
A78: CAUCHO | B78: =1*500 -> 500 | I78: CAUCHO | J78: =1*500 -> 500
A79: DISEÑO | B79: 800 | D79: +5 DOC | E79: 1 A 5 DOC | F79: DETAL | I79: DISEÑO | J79: 1500 | L79: +5 DOC | M79: 1 A 5 DOC | N79: DETAL
A80: HILO | B80: 200 | D80: =D85 -> 10.68375 | E80: =E85 -> 11.396 | F80: =F85 -> 15.6695 | I80: CAUCHO HILO | J80: 1500 | L80: =M84 -> 21.22875 | M80: =N84 -> 24.05925 | N80: =O84 -> 28.305
A81: MARQUILLA | B81: 50 | I81: REMACHES | J81: 300
A82: GASTOS OPERATIVOS | B82: 1800 | I82: MOSQUETON | J82: 300 | L82: CORTA VIENTO CAB.
B83: =SUM(B72:B82)/4000 -> 7.1225 | D83: 24 + & | E83: 6 A 18 | F83: UNIDAD | I83: OPERARIO PARA TERMINAR | J83: 300 | L83: MAS DE 36 | M83: 12 A 36 | N83: 6 A 12 | O83: UNIDAD
D84: 0.35 | E84: 0.6 | F84: 0.9 | I84: HILO | J84: 200 | L84: =J87*1.35 -> 19.105875 | M84: =J87*1.5 -> 21.22875 | N84: =J87*1.7 -> 24.05925 | O84: =J87*2 -> 28.305
D85: =B83*1.5 -> 10.68375 | E85: =B83*1.6 -> 11.396 | F85: =B83*2.2 -> 15.6695 | I85: MARQUILLA | J85: 50
I86: GASTOS OPERATIVOS | J86: 2700 | L86: CORTA VIENTO TELA IMPERMEABLE CON GORRO TODO SUBLIMADO
J87: =SUM(J72:J86)/4000 -> 14.1525

Sheet KSAKAS
A2: KASAKAS SOLO LOGO | F2: 4000
A3: TELA Malla | B3: =0.5*1.2*F2 -> 2400
A4: CORTE | B4: 700
A5: COSTURA | B5: 2500
A6: SUBLIMACION | B6: 2500 | D6: KASAKAS
A7: PLANCHA | B7: 500
A8: SESGO | B8: =1000 -> 1000 | D8: +5 DOC | E8: 1 A 5 DOC | F8: DETAL
A9: DISEÑO | B9: 1000 | D9: =D14 -> 4.615 | E9: =E14 -> 5.68 | F9: =F14 -> 7.0645
A10: CORTE DEL PLOTTER | B10: 0
A11: CAUCHO | B11: 500
A12: ETIQUETA | B12: 50
A13: BOLSA | B13: 100 | D13: 0.35 | E13: 0.5 | F13: 0.8
A14: HILO | B14: 250 | D14: =B17*1.3 -> 4.615 | E14: =B17*1.6 -> 5.68 | F14: =B17*1.99 -> 7.0645
A15: MARQUILLA | B15: 0 | D15: =6.5*3800 -> 24700
A16: GASTOS OPERATIVOS | B16: 2700
B17: =SUM(B3:B16)/F2 -> 3.55
A19: KASAKAS SUBLIMACION TOTAL | F19: 4000
A20: TELA Malla | B20: =0.6*1.2*F19 -> 2880
A21: CORTE | B21: 700
A22: COSTURA | B22: 2500
A23: SUBLIMACION | B23: =0.5*8500 -> 4250 | D23: KASAKAS
A24: PLANCHA | B24: 1500
A25: SESGO | B25: =1000 -> 1000 | D25: +5 DOC | E25: 1 A 5 DOC | F25: DETAL
A26: DISEÑO | B26: 1000 | D26: =D31 -> 5.66475 | E26: =E31 -> 6.972 | F26: =F31 -> 8.671425
A27: CORTE DEL PLOTTER | B27: 0
A28: CAUCHO | B28: 500
A29: ETIQUETA | B29: 50
A30: BOLSA | B30: 100 | D30: 0.35 | E30: 0.5 | F30: 0.8
A31: HILO | B31: 250 | D31: =B34*1.3 -> 5.66475 | E31: =B34*1.6 -> 6.972 | F31: =B34*1.99 -> 8.671425
A32: MARQUILLA | B32: 0 | D32: =6.5*3800 -> 24700
A33: GASTOS OPERATIVOS | B33: 2700
B34: =SUM(B20:B33)/F19 -> 4.3575

Sheet F. SUBLIM 1,3
A2: MICRO | C2: SUBLIMACION 1/3 MAS VINIL | I2: MUSE | K2: SUBLIMACION 1/3 MAS VINIL
A3: CABALLERO | D3: FRANELAS | I3: CABALLERO | L3: FRANELAS
A4: TELA | B4: =1*3*F4 -> 11400 | F4: 3800 | I4: TELA | J4: =1*1.8*N4 -> 6840 | N4: 3800
A5: CORTE | B5: 1000 | I5: CORTE | J5: 1000
A6: COSTURA | B6: 2500 | D6: SUBLIMACION 1/3 MAS VINIL DAMA | I6: COSTURA | J6: 2500 | L6: SUBLIMACION 1/3 MAS VINIL DAMA
A7: SUBLIMACION 1/3 | B7: =15000/3 -> 5000 | D7: +5 DOC | E7: 1 A 5 DOC | F7: DETAL | I7: SUBLIMACION 1/3 | J7: =15000/3 -> 5000 | L7: +5 DOC | M7: 1 A 5 DOC | N7: DETAL
A8: VINIL | B8: 1000 | D8: =D12 -> 10.894079 | E8: =E12 -> 13.148026 | F8: =F12 -> 14.951184 | I8: VINIL | J8: 1000 | L8: =L13 -> 9.5928947 | M8: =M13 -> 11.577632 | N8: =N13 -> 13.165421
A9: PLANCHA | B9: 1000 | I9: PLANCHA | J9: 1000
A10: DISEÑO | B10: 2000 | I10: DISEÑO | J10: 2000
A11: CORTE DEL PLOTTER | B11: ='FRA MUSE MICR'!G73 -> 0 | D11: 0.4 | E11: 0.55 | F11: 0.85 | I11: CORTE DEL PLOTTER | J11: 200
A12: DEPILADA | B12: 200 | D12: =B18*1.45 -> 10.894079 | E12: =B18*1.75 -> 13.148026 | F12: =B18*1.99 -> 14.951184 | I12: DEPILADA | J12: 200 | L12: 0.4 | M12: 0.55 | N12: 0.85
A13: ETIQUETA | B13: 200 | I13: ETIQUETA | J13: 200 | L13: =J18*1.45 -> 9.5928947 | M13: =J18*1.75 -> 11.577632 | N13: =J18*1.99 -> 13.165421
A14: BOLSA | B14: 100 | I14: BOLSA | J14: 100
A15: HILO | B15: 350 | I15: HILO | J15: 350
A16: MARQUILLA | B16: ='FRA MUSE MICR'!G78 -> 100 | I16: MARQUILLA | J16: 750
A17: GASTOS OPERATIVOS | B17: ='FRA MUSE MICR'!G79 -> 3700 | I17: GASTOS OPERATIVOS | J17: 4000
B18: =SUM(B4:B17)/F4 -> 7.5131579 | J18: =SUM(J4:J17)/F4 -> 6.6157895
A23: MICRO | C23: SUBLIMACION 1/3 MAS VINIL | I23: MUSE | K23: SUBLIMACION 1/3 MAS VINIL
A24: DAMA | D24: FRANELAS | I24: DAMA | L24: FRANELAS
A25: TELA | B25: =0.7*3*F4 -> 7980 | I25: TELA | J25: =0.7*1.8*N4 -> 4788
A26: CORTE | B26: 1000 | I26: CORTE | J26: 1000
A27: COSTURA | B27: 2500 | D27: SUBLIMACION 1/3 MAS VINIL DAMA | I27: COSTURA | J27: 2500 | L27: SUBLIMACION 1/3 MAS VINIL DAMA
A28: SUBLIMACION 1/3 | B28: =15000/3 -> 5000 | D28: +5 DOC | E28: 1 A 5 DOC | F28: DETAL | I28: SUBLIMACION 1/3 | J28: =15000/3 -> 5000 | L28: +5 DOC | M28: 1 A 5 DOC | N28: DETAL
A29: VINIL | B29: 1000 | D29: =D33 -> 9.5890789 | E29: =E33 -> 11.573026 | F29: =F33 -> 13.160184 | I29: VINIL | J29: 1000 | L29: =L32 -> 8.8098947 | M29: =M32 -> 10.632632 | N29: =N32 -> 12.090821
A30: PLANCHA | B30: 1000 | I30: PLANCHA | J30: 1000
A31: DISEÑO | B31: 2000 | I31: DISEÑO | J31: 2000 | L31: 0.4 | M31: 0.55 | N31: 0.85
A32: CORTE DEL PLOTTER | B32: =B11 -> 0 | D32: 0.4 | E32: 0.55 | F32: 0.85 | I32: CORTE DEL PLOTTER | J32: 200 | L32: =J39*1.45 -> 8.8098947 | M32: =J39*1.75 -> 10.632632 | N32: =J39*1.99 -> 12.090821
A33: DEPILADA | B33: 200 | D33: =B39*1.45 -> 9.5890789 | E33: =B39*1.75 -> 11.573026 | F33: =B39*1.99 -> 13.160184 | I33: DEPILADA | J33: 200
A34: ETIQUETA | B34: 200 | I34: ETIQUETA | J34: 200
A35: BOLSA | B35: 100 | I35: BOLSA | J35: 100
A36: HILO | B36: =B15 -> 350 | I36: HILO | J36: =J15 -> 350
A37: MARQUILLA | B37: =B16 -> 100 | I37: MARQUILLA | J37: =J16 -> 750
A38: GASTOS OPERATIVOS | B38: =B17 -> 3700 | I38: GASTOS OPERATIVOS | J38: =J17 -> 4000
B39: =SUM(B25:B38)/F4 -> 6.6131579 | J39: =SUM(J25:J38)/F4 -> 6.0757895

Sheet UNI FUTBOL
A1: TALLAS 6-8-10-12 | I1: CABALLERO S-M-L
A2: MUSELINA | C2: SUBLIMADOS TODO | I2: MUSELINA | K2: SUBLIMADOS TODO
E3: FRANELAS | M3: FRANELAS
A4: TELA | B4: =0.7*1.7*G4 -> 4760 | G4: 4000 | H4: DÓLAR | I4: TELA | J4: =0.8*1.5*O4 -> 4560 | O4: 3800 | P4: DÓLAR
A5: CORTE | B5: 700 | I5: CORTE | J5: 700
A6: COSTURA | B6: 2500 | I6: COSTURA | J6: 2500
A7: SUBLIMACION | B7: =1*8500 -> 8500 | I7: SUBLIMACION | J7: 9000 | M7: MUSELINA
A8: PLANCHA | B8: 2000 | E8: FRANELA TODA SUBLIMADA T6-8-10 | I8: PLANCHA | J8: 2000 | L8: +5 DOC | M8: 1 A 5 DOC | N8: DETAL
A9: VINIL 15 CMS | B9: 0 | E9: +5 DOC | F9: 1 A 5 DOC | G9: DETAL | I9: VINIL 15 CMS | J9: 0 | L9: =L15 -> 7.19225 | M9: =M15 -> 8.852 | N9: =N15 -> 11.009675
A10: DISEÑO | B10: 1000 | E10: =E15 -> 7.749 | F10: =F15 -> 9.471 | G10: =G15 -> 11.4226 | I10: DISEÑO | J10: 0
A11: CORTE DEL PLOTTER | B11: 0 | I11: CORTE DEL PLOTTER | J11: 0
A12: DEPILADA | B12: 0 | I12: DEPILADA | J12: 0
A13: ETIQUETA | B13: 0 | F13: MUSELINA | I13: ETIQUETA | J13: 0 | M13: MUSELINA
A14: BOLSA | B14: 100 | E14: 0.4 | F14: 0.6 | G14: 0.9 | I14: BOLSA | J14: 50 | L14: 0.4 | M14: 0.6 | N14: 0.9
A15: HILO | B15: 350 | E15: =B18*1.35 -> 7.749 | F15: =B18*1.65 -> 9.471 | G15: =B18*1.99 -> 11.4226 | I15: HILO | J15: 250 | L15: =J18*1.3 -> 7.19225 | M15: =J18*1.6 -> 8.852 | N15: =J18*1.99 -> 11.009675
A16: MARQUILLA | B16: 350 | I16: MARQUILLA | J16: 70
A17: GASTOS OPERATIVOS | B17: 2700 | I17: GASTOS OPERATIVOS | J17: 3000
B18: =SUM(B4:B17)/G4 -> 5.74 | J18: =SUM(J4:J17)/G4 -> 5.5325
A24: MUSELINA | C24: 1/2 SUBLIMADO | I24: MUSELINA | K24: 1/2 SUBLIMADO
E25: FRANELAS | M25: FRANELAS
A26: TELA | B26: =0.55*1.6*G26 -> 3344 | G26: 3800 | H26: DÓLAR | I26: TELA | J26: =0.5*1*O26/2 -> 950 | O26: 3800 | P26: DÓLAR | T26: 6.8
A27: CORTE | B27: 700 | I27: CORTE | J27: 500 | T27: 4
A28: COSTURA | B28: 2500 | I28: COSTURA | J28: 1000
A29: SUBLIMACION | B29: =15000*1.4/6 -> 3500 | F29: MUSELINA | I29: SUBLIMACION | J29: 0 | M29: MUSELINA | T29: 7
A30: PLANCHA | B30: 1000 | E30: +5 DOC | F30: 1 A 5 DOC | G30: DETAL | I30: PLANCHA | J30: 500 | L30: +5 DOC | M30: 1 A 5 DOC | N30: DETAL | T30: 5
A31: VINIL 15 CMS | B31: 1500 | E31: =E36 -> 7.0122 | F31: =F36 -> 7.9794 | G31: =G36 -> 9.62364 | I31: VINIL 15 CMS | J31: 0 | L31: =L36 -> 1.1375 | M31: =M36 -> 1.4875 | N31: =N36 -> 1.74125
A32: DISEÑO | B32: 1000 | I32: DISEÑO | J32: 0 | T32: 9
A33: CORTE DEL PLOTTER | B33: 200 | I33: CORTE DEL PLOTTER | J33: 0 | T33: 5
A34: DEPILADA | B34: 200 | F34: MUSELINA | I34: DEPILADA | J34: 0 | M34: MUSELINA
A35: ETIQUETA | B35: 200 | E35: 0.4 | F35: 0.6 | G35: 0.9 | I35: ETIQUETA | J35: 0 | L35: 0.4 | M35: 0.6 | N35: 0.9
A36: BOLSA | B36: 100 | E36: =B40*1.45 -> 7.0122 | F36: =B40*1.65 -> 7.9794 | G36: =B40*1.99 -> 9.62364 | I36: BOLSA | J36: 0 | L36: =J40*1.3 -> 1.1375 | M36: =J40*1.7 -> 1.4875 | N36: =J40*1.99 -> 1.74125
A37: HILO | B37: 350 | I37: HILO | J37: 350
A38: MARQUILLA | B38: 750 | I38: MARQUILLA | J38: 200
A39: GASTOS OPERATIVOS | B39: 4000 | I39: GASTOS OPERATIVOS | J39: 0
B40: =SUM(B26:B39)/G4 -> 4.836 | J40: =SUM(J26:J39)/G4 -> 0.875
A44: TALLAS 16-S-M
A45: MUSELINA | C45: SUBLIMADOS TODO
E46: FRANELAS
A47: TELA | B47: =0.9*1.3*G47 -> 4446 | G47: 3800 | H47: DÓLAR
A48: CORTE | B48: 700
A49: COSTURA | B49: 3500
A50: SUBLIMACION | B50: =0.9*9500 -> 8550 | F50: MUSELINA
A51: PLANCHA | B51: 2000 | E51: +5 DOC | F51: 1 A 5 DOC | G51: DETAL
A52: VINIL 15 CMS | B52: 0 | E52: =E57 -> 8.6611 | F52: =F57 -> 10.207725 | G52: =G57 -> 12.311135
A53: DISEÑO | B53: 1000
A54: CORTE DEL PLOTTER | B54: 0
A55: DEPILADA | B55: 0 | F55: MUSELINA
A56: ETIQUETA | B56: 50 | E56: 0.4 | F56: 0.6 | G56: 0.9
A57: BOLSA | B57: 100 | E57: =B61*1.4 -> 8.6611 | F57: =B61*1.65 -> 10.207725 | G57: =B61*1.99 -> 12.311135
A58: HILO | B58: 350
A59: MARQUILLA | B59: 50
A60: GASTOS OPERATIVOS | B60: 4000
B61: =SUM(B47:B60)/G4 -> 6.1865
A64: MUSELINA | C64: 1/2 SUBLIMADO
E65: FRANELAS
A66: TELA | B66: =0.8*1.8*G66 -> 5472 | G66: 3800
A67: CORTE | B67: 1000
A68: COSTURA | B68: 2500 | F68: MUSELINA
A69: CAUCHO | B69: 800 | E69: +5 DOC | F69: 1 A 5 DOC | G69: DETAL
A70: SUBLIMACION | B70: =15000*1.4/6 -> 3500 | E70: =E74 -> 8.0011 | F70: =F74 -> 9.1047 | G70: =G74 -> 10.98082
A71: PLANCHA | B71: 1000
A72: VINIL 15 CMS | B72: 1000 | F72: MUSELINA
A73: DISEÑO | B73: 1000 | E73: 0.4 | F73: 0.6 | G73: 0.9
A74: CORTE DEL PLOTTER | B74: 200 | E74: =B81*1.45 -> 8.0011 | F74: =B81*1.65 -> 9.1047 | G74: =B81*1.99 -> 10.98082
A75: DEPILADA | B75: 200
A76: ETIQUETA | B76: 200
A77: BOLSA | B77: 100
A78: HILO | B78: 350
A79: MARQUILLA | B79: 750
A80: GASTOS OPERATIVOS | B80: 4000
B81: =SUM(B66:B80)/G4 -> 5.518
A85: MUSE/ATLE | D85: SHORT SOLO # Y LOGO | I85: MUSE/ATLE | L85: SHORT TODO SUBLIMADO
A86: SHORT NIÑO | F86: TALLAS PÑAS | I86: NIÑO
A87: TELA | B87: =0.6*1.8/2*G4 -> 2160 | I87: TELA | J87: =0.5*1.7*4000 -> 3400
A88: CORTE | B88: 1000 | I88: CORTE | J88: 700
A89: COSTURA | B89: 1500 | E89: +5 DOC | F89: 1 A 5 DOC | G89: DETAL | I89: COSTURA | J89: 1500 | M89: +5 DOC | N89: 1 A 5 DOC | O89: DETAL
A90: CAUCHO | B90: 1000 | E90: =E94 -> 4.694625 | F90: =F94 -> 5.737875 | G90: =G94 -> 6.920225 | I90: CAUCHO | J90: 800 | M90: =M94 -> 3.9410526 | N90: =N94 -> 5.1536842 | O90: =O94 -> 6.0328421
A91: PLANCHA | B91: 1000 | I91: PLANCHA | J91: 1000
A92: VINIL 15 CMS | B92: 1000 | I92: vinil | J92: 0
A93: DISEÑO | B93: 1000 | E93: 0.4 | F93: 0.6 | G93: 0.9 | I93: DISEÑO | J93: 1000 | M93: 0.4 | N93: 0.6 | O93: 0.9
A94: CORTE DEL PLOTTER | B94: 200 | E94: =B101*1.35 -> 4.694625 | F94: =B101*1.65 -> 5.737875 | G94: =B101*1.99 -> 6.920225 | I94: CORTE DEL PLOTTER | J94: 0 | M94: =J101*1.3 -> 3.9410526 | N94: =J101*1.7 -> 5.1536842 | O94: =J101*1.99 -> 6.0328421
A95: DEPILADA | B95: 200 | I95: DEPILADA | J95: 0
A96: ETIQUETA | B96: 200 | I96: ETIQUETA | J96: 50
A97: BOLSA | B97: 100 | I97: BOLSA | J97: 50
A98: HILO | B98: 350 | I98: HILO | J98: 250
A99: MARQUILLA | B99: 200 | I99: MARQUILLA | J99: 70
A100: GASTOS OPERATIVOS | B100: 4000 | I100: GASTOS OPERATIVOS | J100: 2700
B101: =SUM(B87:B100)/G4 -> 3.4775 | J101: =SUM(J87:J100)/O4 -> 3.0315789
A104: MUSE/ATLE | D104: SHORT SOLO # Y LOGO | I104: MUSE/ATLE | M104: EN BLANCO
A105: Caballero | E105: TALLAS GDES | I105: NIÑO/DAMA | M105: TALLAS GDES
A106: TELA | B106: =0.5*1.2*G4 -> 2400 | I106: TELA | J106: =0.8*1.8*O4 -> 5472
A107: CORTE | B107: 700 | I107: CORTE | J107: 1000
A108: COSTURA | B108: 1500 | E108: +5 DOC | F108: 1 A 5 DOC | G108: DETAL | I108: COSTURA | J108: 2500 | M108: +5 DOC | N108: 1 A 5 DOC | O108: DETAL
A109: CAUCHO | B109: 600 | E109: =E114 -> 3.605 | F109: =F114 -> 4.3775 | G109: =G114 -> 5.12425 | I109: CAUCHO | J109: 800 | M109: =M114 -> 7.0866842 | N109: =N114 -> 8.0641579 | O109: =O114 -> 9.7258632
A110: PLANCHA | B110: 500 | I110: PLANCHA | J110: 1000
A111: VINIL 15 CMS | B111: 1500 | I111: VINIL 15 CMS | J111: 1000
A112: DISEÑO | B112: 0 | I112: DISEÑO | J112: 1000
A113: CORTE DEL PLOTTER | B113: 0 | E113: 0.4 | F113: 0.6 | G113: 0.9 | I113: CORTE DEL PLOTTER | J113: 200 | M113: 0.4 | N113: 0.6 | O113: 0.9
A114: DEPILADA | B114: 0 | E114: =B120*1.4 -> 3.605 | F114: =B120*1.7 -> 4.3775 | G114: =B120*1.99 -> 5.12425 | I114: DEPILADA | J114: 200 | M114: =J120*1.45 -> 7.0866842 | N114: =J120*1.65 -> 8.0641579 | O114: =J120*1.99 -> 9.7258632
A115: ETIQUETA | B115: 0 | I115: ETIQUETA | J115: 200
...

Sheet FULL SUBLI
C2: SUBLIMACION COMPLETA DAMA | K2: SUBLIMACION COMPLETA NIÑO
A3: MICRO DAMA | D3: FRANELAS | I3: MICRO NIÑO | L3: FRANELAS
A4: TELA | B4: =0.8*3*F4 -> 9120 | F4: 3800 | G4: DÓLAR | I4: TELA | J4: =0.6*3*N4 -> 6840 | N4: 3800 | O4: DÓLAR
A5: CORTE | B5: 1000 | I5: CORTE | J5: 1000
A6: COSTURA | B6: 2500 | E6: SUBLIMACION COMPLETA DAMA | I6: COSTURA | J6: 2500
A7: PLANCHA | B7: 3000 | D7: +5 DOC | E7: 1 A 5 DOC | F7: DETAL | I7: PLANCHA | J7: 2000
A8: SUBLIMACION COMPLETA | B8: =15000/1.3 -> 11538.462 | D8: =D13 -> 13.453887 | E8: =E13 -> 16.237449 | F8: =F13 -> 18.4643 | I8: SUBLIMACION COMPLETA | J8: =15000/2 -> 7500
A9: DISEÑO | B9: 2000 | I9: DISEÑO | J9: 1000 | L9: SUBLIMACION COMPLETA DAMA
A10: CORTE DEL PLOTTER | B10: 300 | I10: CORTE DEL PLOTTER | J10: 300 | L10: +5 DOC | M10: 1 A 5 DOC | N10: DETAL
A11: DEPILADA | B11: 200 | I11: DEPILADA | J11: 200 | L11: =L15 -> 10.279737 | M11: =M15 -> 12.406579 | N11: =N15 -> 14.108053
A12: ETIQUETA | B12: 500 | D12: 0.4 | E12: 0.55 | F12: 0.85 | I12: ETIQUETA | J12: 500
A13: BOLSA | B13: 100 | D13: =B17*1.45 -> 13.453887 | E13: =B17*1.75 -> 16.237449 | F13: =B17*1.99 -> 18.4643 | I13: BOLSA | J13: 100
A14: HILO | B14: 250 | I14: HILO | J14: 250 | L14: 0.4 | M14: 0.55 | N14: 0.85
A15: MARQUILLA | B15: 750 | I15: MARQUILLA | J15: 750 | L15: =J17*1.45 -> 10.279737 | M15: =J17*1.75 -> 12.406579 | N15: =J17*1.99 -> 14.108053
A16: GASTOS OPERATIVOS | B16: 4000 | I16: GASTOS OPERATIVOS | J16: 4000
B17: =SUM(B4:B16)/F4 -> 9.2785425 | J17: =SUM(J4:J16)/F4 -> 7.0894737
C23: SUBLIMACION COMPLETA CABALLERO
A24: MICRO CABALLERO | D24: FRANELAS
A25: TELA | B25: =1.1*3*F4 -> 12540
A26: CORTE | B26: 1000
A27: COSTURA | B27: 2500 | E27: SUBLIMACION COMPLETA CABALLERO
A28: SUBLIMACION FULL | B28: =15000/1 -> 15000 | D28: +5 DOC | E28: 1 A 5 DOC | F28: DETAL
A29: PLANCHA | B29: 3000 | D29: =D34 -> 15.525263 | E29: =E34 -> 17.743158 | F29: =F34 -> 21.07
A30: DISEÑO | B30: 2000
A31: CORTE DEL PLOTTER | B31: 300
A32: DEPILADA | B32: 200
A33: ETIQUETA | B33: 500 | D33: 0.4 | E33: 0.55 | F33: 0.85
A34: BOLSA | B34: 100 | D34: =B38*1.4 -> 15.525263 | E34: =B38*1.6 -> 17.743158 | F34: =B38*1.9 -> 21.07
A35: HILO | B35: 250
A36: MARQUILLA | B36: 750
A37: GASTOS OPERATIVOS | B37: 4000
B38: =SUM(B25:B37)/F4 -> 11.089474
C42: SUBLIMACION COMPLETA DAMA | I42: MUSELINA NIÑO | L42: FRANELAS
A43: MUSELINA DAMA | D43: FRANELAS | I43: TELA | J43: =0.6*1.7*N43 -> 3876 | N43: 3800 | O43: DÓLAR
A44: TELA | B44: =0.8*1.7*F44 -> 5168 | F44: 3800 | G44: DÓLAR | I44: CORTE | J44: 1000
A45: CORTE | B45: 1000 | I45: COSTURA | J45: 2500 | K45: SUBLIMACION COMPLETA DAMA
A46: COSTURA | B46: 2500 | C46: SUBLIMACION COMPLETA DAMA | I46: PLANCHA | J46: 2000 | L46: +5 DOC | M46: 1 A 5 DOC | N46: DETAL
A47: PLANCHA | B47: 2000 | D47: +5 DOC | E47: 1 A 5 DOC | F47: DETAL | I47: SUBLIMACION COMPLETA | J47: =15000/2 -> 7500 | L47: =L51 -> 9.1487368 | M47: =M51 -> 11.041579 | N47: =N51 -> 12.555853
A48: SUBLIMACION COMPLETA | B48: =15000/1.5 -> 10000 | D48: =D52 -> 10.595684 | E48: =E52 -> 12.787895 | F48: =F52 -> 14.541663 | I48: DISEÑO | J48: 1000
A49: DISEÑO | B49: 1000 | I49: CORTE DEL PLOTTER | J49: 300
A50: CORTE DEL PLOTTER | B50: 300 | I50: DEPILADA | J50: 200 | L50: 0.4 | M50: 0.55 | N50: 0.85
A51: DEPILADA | B51: 200 | D51: 0.4 | E51: 0.55 | F51: 0.85 | I51: ETIQUETA | J51: 500 | L51: =J56*1.45 -> 9.1487368 | M51: =J56*1.75 -> 11.041579 | N51: =J56*1.99 -> 12.555853
A52: ETIQUETA | B52: 500 | D52: =B57*1.45 -> 10.595684 | E52: =B57*1.75 -> 12.787895 | F52: =B57*1.99 -> 14.541663 | I52: BOLSA | J52: 100
A53: BOLSA | B53: 100 | I53: HILO | J53: 250
A54: HILO | B54: 250 | I54: MARQUILLA | J54: 750
A55: MARQUILLA | B55: 750 | I55: GASTOS OPERATIVOS | J55: 4000
A56: GASTOS OPERATIVOS | B56: 4000 | J56: =SUM(J43:J55)/F4 -> 6.3094737
B57: =SUM(B44:B56)/F4 -> 7.3073684
A59: MUSELINA | C59: SUBLIMACION COMPLETA CABALLERO
A60: CABALLERO | D60: FRANELAS
A61: TELA | B61: =1.1*1.7*F44 -> 7106
A62: CORTE | B62: 1000 | D62: SUBLIMACION COMPLETA CABALLERO
A63: COSTURA | B63: 2500 | D63: +5 DOC | E63: 1 A 5 DOC | F63: DETAL
A64: SUBLIMACION FULL | B64: 15000 | D64: =D68 -> 13.128605 | E64: =E68 -> 15.844868 | F64: =F68 -> 18.017879
A65: PLANCHA | B65: 2000
A66: DISEÑO | B66: 1000
A67: CORTE DEL PLOTTER | B67: 300 | D67: 0.4 | E67: 0.55 | F67: 0.85
A68: DEPILADA | B68: 200 | D68: =B74*1.45 -> 13.128605 | E68: =B74*1.75 -> 15.844868 | F68: =B74*1.99 -> 18.017879
A69: ETIQUETA | B69: 200
A70: BOLSA | B70: 100
A71: HILO | B71: 250
A72: MARQUILLA | B72: 750
A73: GASTOS OPERATIVOS | B73: 4000
B74: =SUM(B61:B73)/F4 -> 9.0542105

Sheet LICRAS 
F3: 3800
A5: PANTALON LICRA
A6: NIÑO | D6: TALLAS 6-8 | J6: PANTALON LICRA | S6: PANTALON LICRA
J7: NIÑO | M7: TODAS LAS TALLAS | S7: NIÑO | V7: TODAS LAS TALLAS
A8: TELA | B8: =1*2.2*4000/2 -> 4400 | J8: TELA | K8: =0.7*4*F3/2 -> 5320 | N8: 10-12-14 | S8: DISEÑO | T8: =45000 -> 45000 | W8: 10-12-14
A9: CAUCHO | B9: =2000*0.55 -> 1100 | J9: CAUCHO | K9: 2000 | S9: CAUCHO | T9: =2000*0.65 -> 1300
A10: CORTE | B10: 700 | J10: CORTE | K10: 700 | S10: CORTE | T10: 700
A11: COSTURA | B11: 4000 | J11: COSTURA | K11: 3500 | S11: COSTURA | T11: 8000
A12: PLANCHA | B12: 500 | J12: PLANCHA | K12: 200 | S12: PLANCHA | T12: 2000
A13: VINIL | B13: 500 | D13: PANTALON LICRA talla 6-8-10 | J13: VINIL | K13: 500 | M13: PANTALON LICRA | S13: SUBLIMACION | T13: =1*13000 -> 13000 | V13: PANTALON LICRA
A14: CORTE DEL PLOTTER | B14: 200 | D14: +5 DOC | E14: 1 A 5 DOC | F14: DETAL | J14: CORTE DEL PLOTTER | K14: 200 | M14: +5 DOC | N14: 1 A 5 DOC | O14: DETAL | S14: CORTE DEL PLOTTER | T14: 0 | V14: +5 DOC | W14: 1 A 5 DOC | X14: DETAL
A15: DEPILADA | B15: 200 | D15: =D19 -> 6.4677632 | E15: =E19 -> 7.1368421 | F15: =F19 -> 8.8764474 | J15: DEPILADA | K15: 200 | M15: =M18 -> 6.7425 | N15: =N18 -> 7.44 | O15: =O18 -> 10.695 | S15: DEPILADA | T15: 0 | V15: =V18 -> 28.751974 | W15: =W18 -> 31.726316 | X15: =X18 -> 45.606579
A16: ETIQUETA | B16: 500 | J16: ETIQUETA | K16: 500 | S16: ETIQUETA | T16: 500
A17: BOLSA | B17: 100 | J17: BOLSA | K17: 100 | M17: 45 | N17: 60 | O17: 0.8 | S17: BOLSA | T17: 100 | V17: 45 | W17: 60 | X17: 0.8
A18: HILO | B18: 350 | D18: 0.35 | E18: 0.5 | F18: 0.8 | J18: HILO | K18: 350 | M18: =K21*1.45 -> 6.7425 | N18: =K21*1.6 -> 7.44 | O18: =K21*2.3 -> 10.695 | S18: HILO | T18: 350 | V18: =T21*1.45 -> 28.751974 | W18: =T21*1.6 -> 31.726316 | X18: =T21*2.3 -> 45.606579
A19: MARQUILLA | B19: 400 | D19: =B21*1.45 -> 6.4677632 | E19: =B21*1.6 -> 7.1368421 | F19: =B21*1.99 -> 8.8764474 | J19: MARQUILLA | K19: 400 | N19: 30000 | O19: 45000 | S19: MARQUILLA | T19: 400 | W19: =W18*3700 -> 117387.37
A20: GASTOS OPERATIVOS | B20: 4000 | J20: GASTOS OPERATIVOS | K20: 3700 | S20: GASTOS OPERATIVOS | T20: 4000
B21: =SUM(B8:B20)/F3 -> 4.4605263 | K21: =SUM(K8:K20)/F3 -> 4.65 | T21: =SUM(T8:T20)/F3 -> 19.828947
J25: PANTALON LICRA
M26: DAMA
J27: TELA | K27: =0.9*4*4200/3*2 -> 10080
A28: PANTALON LICRA | J28: CAUCHO | K28: 1000
D29: CABALLERO | J29: CORTE | K29: 500
A30: TELA | B30: =1.1*2.5*4000/1.5 -> 7333.3333 | D30: TALLAS 16-S-M-L | J30: COSTURA | K30: 4500
A31: CAUCHO | B31: 1500 | J31: PLANCHA | K31: 500
A32: CORTE | B32: 700 | J32: VINIL | K32: 500 | M32: LICRA DAMA
A33: COSTURA | B33: 4000 | J33: CORTE DEL PLOTTER | K33: 100 | M33: +5 DOC | N33: 1 A 5 DOC | O33: DETAL
A34: PLANCHA | B34: 500 | J34: DEPILADA | K34: 100 | M34: =M38 -> 8.5206579 | N34: =N38 -> 9.4021053 | O34: =O38 -> 12.340263
A35: VINIL | B35: 500 | D35: LICRA CABALLERO | J35: ETIQUETA | K35: 200
A36: CORTE DEL PLOTTER | B36: 200 | D36: +5 DOC | E36: 1 A 5 DOC | F36: DETAL | J36: BOLSA | K36: 0
A37: DEPILADA | B37: 200 | D37: =D40 -> 7.739693 | E37: =E40 -> 8.5403509 | F37: =F40 -> 12.810526 | J37: HILO | K37: 350 | M37: 45 | N37: 0.6 | O37: 0.8
A38: ETIQUETA | B38: 500 | J38: MARQUILLA | K38: 500 | M38: =K40*1.45 -> 8.5206579 | N38: =K40*1.6 -> 9.4021053 | O38: =K40*2.1 -> 12.340263
A39: BOLSA | B39: 100 | D39: 45 | E39: 0.6 | F39: 0.8 | J39: GASTOS OPERATIVOS | K39: 4000
A40: HILO | B40: 350 | D40: =B43*1.45 -> 7.739693 | E40: =B43*1.6 -> 8.5403509 | F40: =B43*2.4 -> 12.810526 | K40: =SUM(K27:K39)/F3 -> 5.8763158
A41: MARQUILLA | B41: 400
A42: GASTOS OPERATIVOS | B42: 4000
B43: =SUM(B30:B42)/F3 -> 5.3377193
F49: 3800 | G49: DÓLAR | J49: SHORT LICRA
J50: CABALLERO
A51: SHORT LICRA | J51: TELA | K51: =0.8*4*3800/2 -> 6080 | M51: TALLAS 16-S-M-L
J52: CAUCHO | K52: 2000
A53: NIÑO | D53: TODAS LAS TALLAS | J53: CORTE | K53: 700
A54: CAUCHO | B54: 1000 | E54: 4-6-8-10-12 | J54: COSTURA | K54: 2500
A55: TELA | B55: =0.5*4.2*F3/2 -> 3990 | J55: PLANCHA | K55: 200
A56: CORTE | B56: 1000 | J56: DISEÑO | K56: 0 | M56: SHORT LICRA NIÑOS 14-16
A57: COSTURA | B57: 2500 | J57: CORTE DEL PLOTTER | K57: 200 | M57: +5 DOC | N57: 1 A 5 DOC | O57: DETAL
A58: PLANCHA | B58: 1000 | J58: DEPILADA | K58: 200 | M58: =M62 -> 6.4792105 | N58: =N62 -> 7.1494737 | O58: =O62 -> 10.724211
A59: VINIL | B59: 1000 | D59: SHORT LICRA NIÑOS | J59: ETIQUETA | K59: 500
A60: CORTE DEL PLOTTER | B60: 200 | D60: +5 DOC | E60: 1 A 5 DOC | F60: DETAL | J60: BOLSA | K60: 100
A61: DEPILADA | B61: 200 | D61: =D65 -> 6.0861842 | E61: =E65 -> 7.3453947 | F61: =F65 -> 8.3527632 | J61: HILO | K61: 100 | M61: 45 | N61: 60 | O61: 2.1
A62: ETIQUETA | B62: 500 | J62: MARQUILLA | K62: 400 | M62: =K64*1.45 -> 6.4792105 | N62: =K64*1.6 -> 7.1494737 | O62: =K64*2.4 -> 10.724211
A63: BOLSA | B63: 60 | J63: GASTOS OPERATIVOS | K63: 4000
A64: HILO | B64: 100 | D64: 0.35 | E64: 0.5 | F64: 0.8 | K64: =SUM(K51:K63)/F3 -> 4.4684211
A65: MARQUILLA | B65: 400 | D65: =B67*1.45 -> 6.0861842 | E65: =B67*1.75 -> 7.3453947 | F65: =B67*1.99 -> 8.3527632
A66: GASTOS OPERATIVOS | B66: 4000
B67: =SUM(B54:B66)/F3 -> 4.1973684
A72: SHORT LICRA | C72: PRECIO SOLO PARA ESCUELAS | J72: FRANELILLA LICRA | L72: PRECIO SOLO PARA ESCUELAS
A73: TALLAS DAMA | J73: T8 A T16
A74: TELA | B74: =0.65*7/1.5*F49 -> 11526.667 | C74: todas las tallas SUBLIMACION TOTAL | J74: TELA | K74: =0.7*3*4000/1.5 -> 5600 | L74: todas las tallas SUBLIMACION TOTAL
A75: SUBLIMACION COMPLETA | B75: =14000*0.65/1.5 -> 6066.6667 | J75: SUBLIMACION COMPLETA | K75: =14000*0.7/1.5 -> 6533.3333
A76: PLANCHA | B76: 500 | J76: PLANCHA | K76: =3000 -> 3000
A77: CAUCHO | B77: 0 | J77: CORTE | K77: 700
A78: CORTE | B78: 700 | J78: COSTURA | K78: 2500 | M78: FRANELILLA LICRA
A79: COSTURA | B79: 2000 | J79: DISEÑO | K79: 1000 | M79: NJ | N79: VENDEDOR | O79: DETAL
A80: DISEÑO | B80: 2000 | D80: SHORT LICRA NIÑOS T8 a T16 | J80: CORTE DEL PLOTTER | K80: 200 | M80: =M84 -> 8.6974561 | N80: =N84 -> 10.49693 | O80: =O84 -> 11.936509
A81: CORTE DEL PLOTTER | B81: 0 | D81: NJ | E81: VENDEDOR | F81: DETAL | J81: DEPILADA | K81: 200
A82: DEPILADA | B82: 0 | D82: =D86 -> 9.8269298 | E82: =E86 -> 11.860088 | F82: =F86 -> 13.486614 | J82: ETIQUETA CARTON | K82: 100
A83: ETIQUETA CARTON | B83: 0 | J83: BOLSA | K83: 100 | M83: 0.35 | N83: 0.45 | O83: 0.7
A84: BOLSA | B84: 100 | J84: HILO | K84: 100 | M84: =K87*1.45 -> 8.6974561 | N84: =K87*1.75 -> 10.49693 | O84: =K87*1.99 -> 11.936509
A85: HILO | B85: 100 | D85: 0.35 | E85: 0.45 | F85: 0.7 | J85: MARQUILLA | K85: 760
A86: MARQUILLA | B86: 760 | D86: =B88*1.45 -> 9.8269298 | E86: =B88*1.75 -> 11.860088 | F86: =B88*1.99 -> 13.486614 | J86: GASTOS OPERATIVOS | K86: 2000
A87: GASTOS OPERATIVOS | B87: 2000 | K87: =SUM(K74:K86)/F3 -> 5.9982456
B88: =SUM(B74:B87)/F3 -> 6.777193
A93: TOP LICRA | C93: PRECIO SOLO PARA ESCUELAS | J93: CORTA VIENTO | M93: CON VINIL PÑO
A94: T8 A T16 | J94: TELA TASLAN | K94: =1.5*3*4000 -> 18000
A95: TELA | B95: =0.5*7/2*F49 -> 6650 | C95: todas las tallas SUBLIMACION TOTAL | J95: CORTE | K95: 1000
A96: SUBLIMACION COMPLETA | B96: =14000*0.5/2 -> 3500 | J96: COSTURA | K96: 4000
A97: PLANCHA | B97: 500 | J97: CIERRE | K97: 2500 | M97: CORTA VIENTO DE CABALLERO IMPERMEABLE
A98: CAUCHO | B98: 1000 | J98: PLANCHA | K98: =K81 -> 200
A99: CORTE | B99: 700 | J99: VINIL 15 CMS | K99: 1000 | M99: +5 DOC | N99: 1 A 5 DOC | O99: DETAL
A100: COSTURA | B100: 2500 | J100: DISEÑO | K100: 1000 | M100: =M104 -> 12.157105 | N100: =N104 -> 14.672368 | O100: =O104 -> 16.684579
A101: DISEÑO | B101: 2000 | D101: FRANELILLA LICRA | J101: CORTE DEL PLOTTER | K101: 200
A102: CORTE DEL PLOTTER | B102: 0 | D102: NJ | E102: VENDEDOR | F102: DETAL | J102: DEPILADA | K102: 200
A103: DEPILADA | B103: 0 | D103: =D107 -> 8.1467105 | E103: =E107 -> 9.2703947 | F103: =F107 -> 11.180658 | J103: ETIQUETA | K103: 200 | M103: 0.4 | N103: 0.65 | O103: 0.9
A104: DTF | B104: 0 | J104: BOLSA | K104: 100 | M104: =K108*1.45 -> 12.157105 | N104: =K108*1.75 -> 14.672368 | O104: =K108*1.99 -> 16.684579
A105: BOLSA | B105: 100 | J105: HILO | K105: 100
A106: HILO | B106: 100 | D106: 0.35 | E106: 0.45 | F106: 0.7 | J106: MARQUILLA | K106: 360
A107: MARQUILLA | B107: 500 | D107: =B109*1.45 -> 8.1467105 | E107: =B109*1.65 -> 9.2703947 | F107: =B109*1.99 -> 11.180658 | J107: GASTOS OPERATIVOS | K107: 3000
A108: GASTOS OPERATIVOS | B108: 3800 | K108: =SUM(K94:K107)/F3 -> 8.3842105
B109: =SUM(B95:B108)/F3 -> 5.6184211
A114: SHORT LICRA | C114: PRECIO SOLO PARA ESCUELAS | J114: FRANELILLA LICRA | L114: PRECIO SOLO PARA ESCUELAS
A115: TALLAS 8-16 | J115: T8 A T16
A116: TELA | B116: =0.65*3*4000/1.5 -> 5200 | C116: todas las tallas LOGO VINIL | J116: TELA | K116: =0.7*2*4000/1.5 -> 3733.3333 | L116: todas las tallas LOGO SUBLIMADO
A117: PLANCHA | B117: 1000 | J117: PLANCHA | K117: 1500
A118: CAUCHO | B118: =2000*0.7 -> 1400 | J118: SUBLIMACION LOGO | K118: 1000
A119: CORTE | B119: 700 | J119: CORTE | K119: 700
A120: SUBLIMACION | B120: 6000
A121: COSTURA | B121: 2500 | J121: COSTURA | K121: 2500 | M121: FRANELILLA LICRA
A122: DISEÑO | B122: 1000 | D122: SHORT LICRA NIÑOS T8 a T16 | J122: DISEÑO | K122: 1000 | M122: NJ | N122: VENDEDOR | O122: DETAL
A123: CORTE DEL PLOTTER | B123: 200 | D123: NJ | E123: VENDEDOR | F123: DETAL | J123: CORTE DEL PLOTTER | K123: 200 | M123: =M127 -> 5.3014035 | N123: =N127 -> 6.3982456 | O123: =O127 -> 7.2757193
...

Sheet PIJAMAS 
A1: MICRO
A2: niños pijama buzo | F2: 3800
A3: TELA | B3: =0.9*1.7*F2 -> 5814
A4: CORTE | B4: 700
A5: COSTURA | B5: 2000
A6: SUBLIMACION | B6: 7500
A7: PLANCHA | B7: 1000 | D7: +5 DOC | E7: 1 A 5 DOC | F7: DETAL
A8: DISEÑO | B8: 0 | D8: =D13 -> 7.4239874 | E8: =E13 -> 7.6891298 | F8: =F13 -> 10.552668 | H8: PIJAMAS
A9: CORTE DEL PLOTTER | B9: 0 | H9: +5 DOC | I9: 1 A 5 DOC | J9: DETAL
A10: DEPILADA | B10: 0 | H10: =D8+D27 -> 13.036963 | I10: =E8+E27 -> 13.495657 | J10: =F8+F27 -> 18.255993 | K10: $
A11: MARQUILLA 1 TALLA DTF | B11: 0 | H11: =H10*4800 -> 62577.424 | I11: =I10*4800 -> 64779.151 | J11: =J10*4800 -> 87628.768 | K11: &
A12: MARQUILLA 2 DTF | B12: =41000/256 -> 160.15625 | D12: 0.4 | E12: 0.6 | F12: 0.9
A13: DTF ESCUDO | B13: 50 | D13: =B18*1.4 -> 7.4239874 | E13: =B18*1.45 -> 7.6891298 | F13: =B18*1.99 -> 10.552668
A14: LOGO EN VINIL | B14: =14000/210 -> 66.666667 | H14: Equipo | I14: Talla | J14: Cantidad | L14: Equipo | M14: Talla | N14: Cantidad | P14: Equipo | Q14: Talla | R14: Cantidad
A15: BOLSA | B15: 60 | H15: Brasil | I15: 8 | J15: 2 | L15: Alemania | M15: 8 | N15: 2 | P15: Portugal | Q15: 8 | R15: 2
A16: HILO | B16: 300 | H16: Brasil | I16: 10 | J16: 3 | L16: Alemania | M16: 10 | N16: 3 | P16: Portugal | Q16: 10 | R16: 3
A17: GASTOS OPERATIVOS | B17: 2500 | H17: Brasil | I17: 12 | J17: 4 | L17: Alemania | M17: 12 | N17: 4 | P17: Portugal | Q17: 12 | R17: 4
B18: =SUM(B3:B17)/F2 -> 5.3028481 | H18: Brasil | I18: 14 | J18: 4 | L18: Alemania | M18: 14 | N18: 3 | P18: Portugal | Q18: 14 | R18: 3
H19: Brasil | I19: 16 | J19: 2 | L19: Alemania | M19: 16 | N19: 2 | P19: Portugal | Q19: 16 | R19: 2
J20: =SUM(J15:J19) -> 15 | N20: =SUM(N15:N19) -> 11 | R20: =SUM(R15:R19) -> 11
A21: MICRO
A22: niños pijama pantalon | F22: 3800
A23: TELA | B23: =1.2*1.7*F22 -> 7752
A24: CORTE | B24: 500
A25: COSTURA | B25: 1500 | H25: Equipo | I25: Talla | J25: Cantidad | L25: Equipo | M25: Talla | N25: Cantidad
A26: PLANCHA | B26: 750 | D26: +5 DOC | E26: 1 A 5 DOC | F26: DETAL | H26: Argentina | I26: 8 | J26: 2 | L26: España | M26: 8 | N26: 2 | P26: total | Q26: 63 | R26: =Q26*14.5 -> 913.5
A27: DISEÑO | B27: 0 | D27: =D32 -> 5.6129758 | E27: =E32 -> 5.8065267 | F27: =F32 -> 7.7033255 | H27: Argentina | I27: 10 | J27: 3 | L27: España | M27: 10 | N27: 3
A28: CORTE DEL PLOTTER | B28: 200 | H28: Argentina | I28: 12 | J28: 4 | L28: España | M28: 12 | N28: 4
A29: DEPILADA | B29: 200 | H29: Argentina | I29: 14 | J29: 4 | L29: España | M29: 14 | N29: 3
A30: MARQUILLA 1 TALLA DTF | B30: =43000/220 -> 195.45455 | H30: Argentina | I30: 16 | J30: 2 | L30: España | M30: 16 | N30: 2
A31: MARQUILLA 2 DTF | B31: =43000/256 -> 167.96875 | D31: 0.4 | E31: 0.6 | F31: 0.9 | J31: =SUM(J26:J30) -> 15 | N31: =SUM(N26:N30) -> 11
A32: DTF ESCUDO | B32: =43000/90 -> 477.77778 | D32: =B37*1.45 -> 5.6129758 | E32: =B37*1.5 -> 5.8065267 | F32: =B37*1.99 -> 7.7033255
A33: LOGO EN VINIL | B33: =14000/210 -> 66.666667
A34: BOLSA | B34: 100
A35: HILO | B35: 300 | E35: =18*60% -> 10.8
A36: GASTOS OPERATIVOS | B36: 2500
B37: =SUM(B23:B36)/F22 -> 3.8710178

Sheet CANILLERAS 
G3: 3800
A4: CANILLERAS CON BOLSO | E4: CANILLERAS EN BLANCO | J4: CANILLERAS SIN BOLSO | M4: CANILLERAS EN BLANCO
A5: CANILLERAS | B5: 10000 | E5: CANILLERAS | F5: 10000 | J5: CANILLERAS | K5: 10000 | M5: CANILLERAS | N5: 10000
A6: FLETE | B6: 500 | E6: FLETE | F6: =110000/250 -> 440 | J6: FLETE | K6: 500 | M6: FLETE | N6: =110000/250 -> 440
A7: TELA BAHAMAS 1,35 | B7: =3.7*1.35/80*4900 -> 305.94375 | F7: =F6+F5 -> 10440 | J7: TELA BAHAMAS 1,35 | K7: 0 | N7: =N6+N5 -> 10440
A8: COSTURA Y CORTE | B8: 1500 | J8: COSTURA Y CORTE | K8: 0
A9: TELA MALLA FASHION MIX SPT (1,45) | B9: =3.4*1.45/80*4900 -> 301.9625 | E9: CANILLERAS EN BLANCO | J9: TELA MALLA FASHION MIX SPT (1,45) | K9: 0 | M9: CANILLERAS EN BLANCO
A10: SUBLIMACION | B10: =300*2 -> 600 | F10: +5 DOC | J10: SUBLIMACION | K10: =300*2 -> 600 | N10: +5 DOC
A11: PLANCHA | B11: 1000 | F11: 0.45 | J11: PLANCHA | K11: 1000 | N11: 0.45
A12: DISEÑO | B12: 1000 | F12: =F7*1.65/G3 -> 4.5331579 | J12: DISEÑO | K12: 1000 | N12: =N7*1.65/G3 -> 4.5331579
A13: CORTE DEL PLOTTER | B13: 100 | J13: CORTE DEL PLOTTER | K13: 0
A14: DEPILADA | B14: 0 | E14: CANILLERAS C/ BOLSO | J14: DEPILADA | K14: 0 | M14: CANILLERAS SUBLIMADAS C/ BOLSO
A15: MARQUILLA 1 TALLA DTF | B15: 0 | E15: +5 DOC | F15: 1 A 5 DOC | G15: DETAL | J15: MARQUILLA 1 TALLA DTF | K15: 0 | M15: +5 DOC | N15: 1 A 5 DOC | O15: DETAL
A16: MARQUILLA 2 DTF | B16: =41000/256 -> 160.15625 | E16: 0.45 | F16: 0.65 | G16: 0.99 | J16: MARQUILLA 2 DTF | K16: =41000/256 -> 160.15625 | M16: 0.45 | N16: 0.65 | O16: 0.99
A17: LOGO EN VINIL | B17: 0 | E17: =B21*1.3 -> 25893.481 | F17: =B21*1.65 -> 32864.803 | G17: =B21*2.28 -> 45413.182 | J17: LOGO EN VINIL | K17: 0 | M17: =K21*1.45 -> 25679.727 | N17: =K21*1.65 -> 29221.758 | O17: =K21*2.28 -> 40379.156
A18: BOLSA | B18: 100 | E18: =E17/G3 -> 6.814074 | F18: =F17/G3 -> 8.6486324 | G18: =G17/G3 -> 11.950837 | J18: BOLSA | K18: 100 | M18: =M17/G3 -> 6.7578228 | N18: =N17/G3 -> 7.6899363 | O18: =O17/G3 -> 10.626094
A19: HILO | B19: 350 | J19: HILO | K19: 350
A20: GASTOS OPERATIVOS | B20: 4000 | J20: GASTOS OPERATIVOS | K20: 4000
B21: =SUM(B5:B20) -> 19918.062 | K21: =SUM(K5:K20) -> 17710.156
A24: CANILLERAS PERSONALIZADA CON BOLSO | J24: CANILLERAS PERSONALIZADA SIN BOLSO
A25: CANILLERAS | B25: 10000 | J25: CANILLERAS | K25: 10000
A26: FLETE | B26: =110000/250 -> 440 | J26: FLETE | K26: =110000/250 -> 440
A27: COSTURA Y CORTE | B27: 1500 | J27: COSTURA Y CORTE | K27: 0
A28: TELA BAHAMAS 1,35 | B28: =3.7*1.35/80*4900 -> 305.94375 | J28: TELA BAHAMAS 1,35 | K28: 0 | L28: CANILLERAS SUBLIMADAS PERSONALIZADA SIN BOLSO
A29: TELA MALLA FASHION MIX SPT (1,45) | B29: =3.4*1.45/80*4900 -> 301.9625 | D29: CANILLERAS PERSONALIZADA C/ BOLSO | J29: TELA MALLA FASHION MIX SPT (1,45) | K29: 0
A30: SUBLIMACION | B30: =300*2 -> 600 | E30: +5 DOC | F30: 1 A 5 DOC | G30: DETAL | J30: SUBLIMACION | K30: =300*2 -> 600 | M30: +5 DOC | N30: 1 A 5 DOC | O30: DETAL
A31: PLANCHA | B31: 1000 | E31: 0.45 | F31: 0.65 | G31: 0.99 | J31: PLANCHA | K31: 1000 | M31: 0.45 | N31: 0.65 | O31: 0.99
A32: DISEÑO PERSONALIZADO | B32: 10000 | E32: =B42*1.45/G3 -> 10.973471 | F32: =B42*1.65/G3 -> 12.487053 | G32: =B42*2.28/G3 -> 17.254837 | J32: DISEÑO PERSONALIZADO | K32: 10000 | M32: =K42*1.45/G3 -> 10.169139 | N32: =K42*1.65/G3 -> 11.571778 | O32: =K42*2.28/G3 -> 15.990094
A33: CORTE DEL PLOTTER | B33: 0 | J33: CORTE DEL PLOTTER | K33: 0
A34: DEPILADA | B34: 0 | J34: DEPILADA | K34: 0
A35: MARQUILLA 1 TALLA DTF | B35: 0 | J35: MARQUILLA 1 TALLA DTF | K35: 0
A36: MARQUILLA 2 DTF | B36: =41000/256 -> 160.15625 | J36: MARQUILLA 2 DTF | K36: =41000/256 -> 160.15625
A37: DTF ESCUDO | B37: 0 | J37: DTF ESCUDO | K37: 0
A38: LOGO EN VINIL | B38: 0 | J38: LOGO EN VINIL | K38: 0
A39: BOLSA | B39: 100 | J39: BOLSA | K39: 100
A40: HILO | B40: 350 | J40: HILO | K40: 350
A41: GASTOS OPERATIVOS | B41: 4000 | J41: GASTOS OPERATIVOS | K41: 4000
B42: =SUM(B25:B41) -> 28758.062 | K42: =SUM(K25:K41) -> 26650.156

Sheet FUNDACANILLERA
A3: FUNDA CANILLERA
F4: 3800
A5: TELA BAHAMAS 1,35 | B5: =3.7*1.35/80*4900 -> 305.94375
A6: TELA MALLA FASHION MIX SPT (1,45) | B6: =3.4*1.45/80*4900 -> 301.9625
A7: COSTURA Y CORTE | B7: 1500
A8: CORDON | B8: 200
A9: PISA CORDON | B9: 300
A10: SUBLIMACION | B10: =300*2 -> 600
A11: PLANCHA | B11: 1000 | D11: +5 DOC | E11: 1 A 5 DOC | F11: DETAL
A12: DISEÑO | B12: 1000 | D12: 0.4 | E12: 0.6 | F12: 210
A13: CORTE DEL PLOTTER | B13: 200 | D13: =B21*1.55/3800 -> 4.6445726 | E13: =B21*1.75/4900 -> 4.0666765 | F13: =B21*2.4/4900 -> 5.5771563 | G13: dólar
A14: DEPILADA | B14: 200
A15: MARQUILLA 1 TALLA DTF | B15: =43000/220 -> 195.45455
A16: CORTE LASER | B16: 1000
A17: LOGO EN VINIL | B17: =28000/210 -> 133.33333
A18: BOLSA | B18: 100
A19: HILO | B19: 350
A20: GASTOS OPERATIVOS | B20: 4000
B21: =SUM(B4:B20) -> 11386.694
B22: =B21/F4 -> 2.9964985

Sheet TULA 
A1: TAFETA
A2: TULAS DELANTERO SUBLIMADO | F2: 3800
A3: TELA | B3: =1*0.9/3 -> 0.3
A4: CORTE | B4: =300/F2 -> 0.078947368
A5: COSTURA | B5: =1000/3800 -> 0.26315789 | D5: tulas con delantero sublimado
A6: sublimacion | B6: =2000/F2 -> 0.52631579
A7: PLANCHA | B7: =700/2/F2 -> 0.092105263 | D7: +5 DOC | E7: 1 A 5 DOC | F7: DETAL
A8: DISEÑO | B8: =1000/F2 -> 0.26315789 | D8: =D13 -> 3.4631579 | E8: =E13 -> 3.9578947 | F8: =F13 -> 4.9226316
A9: CORTE DEL PLOTTER | B9: 0
A10: REATA | B10: =160/F2 -> 0.042105263
A11: CORDON | B11: =800/F2 -> 0.21052632
A12: METIDA DE CORDON | B12: =300/F2 -> 0.078947368 | D12: 0.4 | E12: 0.6 | F12: 0.9
A13: HILO | B13: =350/F2 -> 0.092105263 | D13: =B15*1.4 -> 3.4631579 | E13: =B15*1.6 -> 3.9578947 | F13: =B15*1.99 -> 4.9226316
A14: GASTOS OPERATIVOS | B14: =2000/F2 -> 0.52631579
B15: =SUM(B3:B14) -> 2.4736842
A17: TAFETA
A18: TULAS DELANTERO SUBLIMADO
A19: TELA | B19: 100
A20: CINTA GROP | B20: 10 | D20: PAGOS
A21: CORDON | B21: 90 | D21: MARIA | E21: 150
A22: IMPRESIÓN DTF | B22: =23*30000/3800 -> 181.57895 | D22: JESUS | E22: =B26+B27+B28 -> 92.368421
A23: sublimacion | B23: 40 | D23: METIDA CORDON | E23: 50
A24: HILO | B24: 20
A25: COSTURA | B25: =150 -> 150
A26: CORTE | B26: =200*900/3800 -> 47.368421
A27: PLANCHA | B27: =90*900/3800 -> 21.315789
A28: PEGADA DTF | B28: =100*900/3800 -> 23.684211
A29: METIDA DEL CORDON | B29: =200*900/3800 -> 47.368421
A30: GASTOS OPERATIVOS | B30: 0
B31: =SUM(B19:B30) -> 731.31579

Sheet CHEMIS 
A2: CON VINIL | I2: CON VINIL
A3: CHEMIS | D3: FRANELAS | F3: 3800 | G3: DÓLAR | I3: CHEMIS | L3: FRANELAS | N3: 3800 | O3: DÓLAR
A4: DAMA | I4: NIÑO | N4: 3800
A5: TELA | B5: =0.8*3.5*F3 -> 10640 | I5: TELA | J5: =0.9*5*N3 -> 17100
A6: CUELLO Y PUÑOS | B6: 0 | I6: CUELLO Y PUÑOS | J6: 3500
A7: DISEÑO | B7: 1000 | I7: DISEÑO | J7: 2000
A8: VINIL | B8: 3000 | I8: VINIL | J8: 6000
A9: CORTE | B9: 1000 | D9: CHEMISS DAMA CUELLO MAO | I9: CORTE | J9: 1000 | L9: CHEMISS
A10: COSTURA | B10: 4500 | D10: +5 DOC | E10: 1 A 5 DOC | F10: DETAL | I10: COSTURA | J10: 4500 | L10: +5 DOC | M10: 1 A 5 DOC | N10: DETAL
A11: PLANCHA | B11: 1000 | D11: =D15 -> 10.088947 | E11: =E15 -> 12.176316 | F11: =F15 -> 13.846211 | I11: PLANCHA | J11: 2000 | L11: =L15 -> 15.682895 | M11: =M15 -> 17.846053 | N11: =N15 -> 21.523421
A12: ETIQUETA | B12: 200 | I12: ETIQUETA | J12: 200
A13: BOLSA | B13: 100 | E13: MUSELINA | I13: BOLSA | J13: 100 | M13: MUSELINA
A14: MARQUILLA | B14: 750 | D14: 0.4 | E14: 0.55 | F14: 0.85 | I14: MARQUILLA | J14: 750 | L14: 0.4 | M14: 0.55 | N14: 0.85
A15: HILO | B15: 250 | D15: =B17*1.45 -> 10.088947 | E15: =B17*1.75 -> 12.176316 | F15: =B17*1.99 -> 13.846211 | I15: HILO | J15: 250 | L15: =J17*1.45 -> 15.682895 | M15: =J17*1.65 -> 17.846053 | N15: =J17*1.99 -> 21.523421
A16: GASTOS OPERATIVOS | B16: 4000 | I16: GASTOS OPERATIVOS | J16: 3700
B17: =SUM(B5:B16)/F3 -> 6.9578947 | J17: =SUM(J5:J16)/F3 -> 10.815789
A19: CON BORDADO | I19: CON BORDADO
A20: CHEMIS | D20: FRANELAS | F20: 3800 | G20: DÓLAR | I20: CHEMIS | L20: FRANELAS | N20: 3800 | O20: DÓLAR
A21: DAMA | I21: NIÑO | N21: 3800
A22: TELA | B22: =0.9*4*F20 -> 13680 | I22: TELA | J22: =0.6*4.5*N20 -> 10260
A23: CUELLO Y PUÑOS | B23: 3000 | I23: CUELLO Y PUÑOS | J23: 3500
A24: DISEÑO | B24: 1000 | I24: DISEÑO | J24: 1000
A25: BORDADO | B25: 0 | I25: BORDADO | J25: 10000
A26: CORTE | B26: 700 | D26: CHEMISS | I26: CORTE | J26: 1000 | L26: CHEMISS
A27: COSTURA | B27: 4000 | D27: +5 DOC | E27: 1 A 5 DOC | F27: DETAL | I27: COSTURA | J27: 4500 | L27: +5 DOC | M27: 1 A 5 DOC | N27: DETAL
A28: PLANCHA | B28: 0 | D28: =D33 -> 9.5317105 | E28: =E33 -> 10.237763 | F28: =F33 -> 14.050447 | I28: PLANCHA | J28: 1000 | L28: =L32 -> 13.950526 | M28: =M32 -> 16.836842 | N28: =N32 -> 19.145895
A29: ETIQUETA | B29: 0 | I29: ETIQUETA | J29: 200
A30: BOLSA | B30: 100 | I30: BOLSA | J30: 100 | M30: MUSELINA
A31: MARQUILLA | B31: 0 | E31: MUSELINA | I31: MARQUILLA | J31: 750 | L31: 0.4 | M31: 0.55 | N31: 0.85
A32: HILO | B32: 350 | D32: 0.4 | E32: 0.55 | F32: 0.85 | I32: HILO | J32: 250 | L32: =J34*1.45 -> 13.950526 | M32: =J34*1.75 -> 16.836842 | N32: =J34*1.99 -> 19.145895
A33: GASTOS OPERATIVOS | B33: 4000 | D33: =B34*1.35 -> 9.5317105 | E33: =B34*1.45 -> 10.237763 | F33: =B34*1.99 -> 14.050447 | I33: GASTOS OPERATIVOS | J33: 4000
B34: =SUM(B22:B33)/F20 -> 7.0605263 | J34: =SUM(J22:J33)/F20 -> 9.6210526
A36: CHEMIS | C36: CON VINIL | I36: CHEMIS | K36: CON BORDADO
A37: CABALLERO | D37: FRANELAS | I37: CABALLERO | L37: FRANELAS
A38: TELA | B38: =1*3*F3 -> 11400 | I38: TELA | J38: =0.9*3*F3 -> 10260
A39: CUELLO Y PUÑOS | B39: 3000 | I39: CUELLO Y PUÑOS | J39: 0
A40: DISEÑO | B40: 1000 | D40: CHEMISS CABALLERO CUELLO MAO | I40: DISEÑO | J40: 2500 | L40: Muselina en blanco CABALLERO
A41: VINIL | B41: 0 | D41: +5 DOC | E41: 1 A 5 DOC | F41: DETAL | I41: SUBLIMACION | J41: =1.5*11000 -> 16500 | L41: +5 DOC | M41: 1 A 5 DOC | N41: DETAL
A42: CORTE | B42: 700 | D42: =D47 -> 9.7684211 | E42: =E47 -> 11.452632 | F42: =F47 -> 12.8 | I42: CORTE | J42: 700 | L42: =L47 -> 15.035263 | M42: =M47 -> 17.183158 | N42: =N47 -> 21.371553
A43: PLANCHADA | B43: 1000 | I43: PLANCHADA | J43: 2000
A44: COSTURA | B44: 4000 | I44: COSTURA | J44: 5000
A45: MARQUILLA | B45: 0 | E45: CHEMISS | I45: MARQUILLA | J45: 50 | M45: MUSELINA
A46: ETIQUETA | B46: 0 | D46: 0.4 | E46: 0.55 | F46: 0.85 | I46: ETIQUETA | J46: 50 | L46: 0.4 | M46: 0.55 | N46: 0.85
A47: BOLSA | B47: 0 | D47: =B50*1.45 -> 9.7684211 | E47: =B50*1.7 -> 11.452632 | F47: =B50*1.9 -> 12.8 | I47: BROCHES | J47: 500 | L47: =J50*1.4 -> 15.035263 | M47: =J50*1.6 -> 17.183158 | N47: =J50*1.99 -> 21.371553
A48: HILO | B48: 500 | D48: =D47*3800 -> 37120 | E48: =E47*3800 -> 43520 | F48: =F47*3800 -> 48640 | I48: HILO | J48: 250
A49: GASTOS OPERATIVOS | B49: 4000 | I49: GASTOS OPERATIVOS | J49: 3000
B50: =SUM(B38:B49)/F3 -> 6.7368421 | J50: =SUM(J38:J49)/F3 -> 10.739474
L51: =4*3700 -> 14800
A52: CHEMIS | C52: TODA SUBLIMADA
A53: CABALLERO | D53: ATLETICA
A54: TELA | B54: =0.9*3*F3 -> 10260
A55: CUELLO Y PUÑOS | B55: 0
A56: DISEÑO | B56: 2000 | D56: CHEMISS CABALLERO CUELLO MAO | I56: COSTURA KELLY | J56: 6500
A57: SUBLIMACION | B57: 11000 | D57: +5 DOC | E57: 1 A 5 DOC | F57: DETAL
A58: CORTE | B58: 700 | D58: =D63 -> 13.733816 | E58: =E63 -> 15.505921 | F58: =F63 -> 16.835
A59: PLANCHADA | B59: 2000
A60: COSTURA | B60: 3500
A61: MARQUILLA | B61: 60 | E61: CHEMISS
A62: ETIQUETA | B62: 0 | D62: 0.4 | E62: 0.55 | F62: 0.85
A63: BOLSA | B63: 100 | D63: =B66*1.55 -> 13.733816 | E63: =B66*1.75 -> 15.505921 | F63: =B66*1.9 -> 16.835
A64: HILO | B64: 350
A65: GASTOS OPERATIVOS | B65: 3700
B66: =SUM(B54:B65)/F3 -> 8.8605263

Sheet BRAGA 
A5: BRAGA | D5: BATA
A7: BRAGA | B7: =2.5*2.3*3800 -> 21850 | D7: BATA | E7: =2*1.3*3800 -> 9880
A8: CIERRE | B8: 1800 | D8: BOTONES | E8: 2000
A9: DISEÑO | B9: 1500 | D9: DISEÑO | E9: 0
A10: PLOTTER | B10: 0 | D10: PLOTTER | E10: 0
A11: VINIL | B11: 11000 | D11: VINIL | E11: 0
A12: BORDADOS | B12: 2500 | D12: BORDADOS | E12: 10000
A13: CORTE | B13: 700 | D13: CORTE | E13: 700
A14: COSTURA | B14: 9000 | D14: COSTURA | E14: 4000
A15: PLANCHA | B15: 0 | D15: PLANCHA | E15: 0
A16: ETIQUETA | B16: 0 | D16: ETIQUETA | E16: 0
A17: BOLSA | B17: 0 | D17: BOLSA | E17: 0
A18: MARQUILLA | B18: 0 | D18: MARQUILLA | E18: 100
A19: HILO | B19: 250 | D19: HILO | E19: 250
A20: GASTOS OPERATIVOS | B20: 2500 | D20: GASTOS OPERATIVOS | E20: 2500
B21: =SUM(B7:B20)/3800 -> 13.447368 | E21: =SUM(E7:E20)/3800 -> 7.7447368
B22: =B21*1.35 -> 18.153947 | E22: =E21*1.35 -> 10.455395

Sheet BEISBOL
A2: CON VINIL
A3: BEISBOL | D3: FRANELAS | F3: 3800 | G3: DÓLAR
A5: TELA ATLETICA | B5: =1.2*1.6*F3 -> 7296
A6: BOTONES | B6: =0.5*F3 -> 1900 | F6: ojo para 30 franelas
A7: DISEÑO | B7: 2000
A8: PLOTTER | B8: 0
A9: VINIL | B9: 0
A10: SUBLIMACION | B10: =1.5*13000 -> 19500
A11: CORTE | B11: 700 | D11: BEISBOL
A12: COSTURA | B12: 4000 | D12: +5 DOC | E12: 1 A 5 DOC | F12: DETAL
A13: PLANCHA | B13: 2000 | D13: =D17 -> 15.453789 | E13: =E17 -> 17.661474 | F13: =F17 -> 21.966458
A14: ETIQUETA | B14: 200
A15: BOLSA | B15: 100
A16: MARQUILLA | B16: 0 | D16: 0.4 | E16: 0.55 | F16: 0.85
A17: HILO | B17: 250 | D17: =B19*1.4 -> 15.453789 | E17: =B19*1.6 -> 17.661474 | F17: =B19*1.99 -> 21.966458
A18: GASTOS OPERATIVOS | B18: 4000
B19: =SUM(B5:B18)/F3 -> 11.038421
A22: GORRA | B22: =25000+8000*1.7 -> 38600 | C22: =B22/3800 -> 10.157895

Sheet VELAS 
D2: 3800
A3: VELAS
A4: TELA | B4: =2.5*2*D2/2 -> 9500 | H4: PRECIO DE TELA MALLA
A5: TELA ORILLO | B5: =3*1.8/12*D2 -> 1710 | H5: 1.5
A6: TUBO | B6: 15000 | D6: Velas 1 cara con tubo
A7: IMPRESIÓN | B7: =2.2*13000/2 -> 14300 | D7: =D12 -> 22.154474 | E7: =E12 -> 25.974211 | F7: =F12 -> 27.502105
A8: COSTURA | B8: 3500
A9: CORTE | B9: 700
A10: PLANCHA | B10: 4000
A11: DISEÑO | B11: 5000 | D11: +5 DOC | E11: 1 A 5 DOC | F11: DETAL
A12: BOLSA | B12: 0 | D12: =B15*1.45/D2 -> 22.154474 | E12: =B15*1.7/D2 -> 25.974211 | F12: =B15*1.8/D2 -> 27.502105
A13: HILO | B13: 350
A14: GASTOS OPERATIVOS | B14: 4000
B15: =SUM(B4:B14) -> 58060
A18: VELAS
A19: TELA | B19: =3*1.5*D2 -> 17100
A20: TELA ORILLO | B20: =3*1.7/12*D2 -> 1615
A21: TUBO | B21: 8000 | D21: Velas 2 cara con tubo
A22: IMPRESIÓN | B22: =17000*3/2 -> 25500 | D22: =D27 -> 22.645 | E22: =E27 -> 27.4975 | F22: =F27 -> 32.18825
A23: COSTURA | B23: 4500
A24: CORTE | B24: 700
A25: PLANCHA | B25: 0
A26: DISEÑO | B26: 0 | D26: +5 DOC | E26: 1 A 5 DOC | F26: DETAL
A27: BOLSA | B27: 0 | D27: =B30*1.4 -> 22.645 | E27: =B30*1.7 -> 27.4975 | F27: =B30*1.99 -> 32.18825
A28: HILO | B28: 350
A29: GASTOS OPERATIVOS | B29: 3700
B30: =SUM(B19:B29)/D2 -> 16.175
B33: =14*2.05 -> 28.7 | C33: =B33*13000 -> 373100 | D33: =C33/4000 -> 93.275 | E33: impresión
B34: =28*3*500 -> 42000 | D34: =B34/4000 -> 10.5 | E34: plancha
B35: =14*2.05 -> 28.7 | D35: =B35*1.5 -> 43.05 | E35: tela
D36: =3*1.6 -> 4.8 | E36: orillo
D37: =SUM(D33:D36) -> 151.625

Sheet BOLSAS POP
D2: 3800
A3: BOLSAS POP | G3: BOLSAS | H3: LOGO | I3: 100 UNIDAD
A4: TELA POP | B4: =1*1*D2/3 -> 1266.6667 | G4: 30*40 | H4: UN COLOR | I4: 160
A5: TELA ORILLO | B5: =1*1.8/18*D2 -> 380 | H5: DOS COLORES | I5: 200
A6: DTF | B6: 800 | D6: BOLSAS POP CON DTF
A7: COSTURA | B7: 1000 | D7: +5 DOC | E7: 1 A 5 DOC | F7: DETAL | G7: 25*30 | H7: UN COLOR | I7: 120
A8: CORTE | B8: 700 | D8: =B14*1.45 -> 4.5776754 | E8: =B14*1.6 -> 5.0512281 | F8: =B14*1.8 -> 5.6826316 | H8: DOS COLORES | I8: 160
A9: PLANCHA | B9: 1500
A10: DISEÑO | B10: 2000 | G10: 20*20 | H10: UN COLOR | I10: 90
A11: BOLSA | B11: 0 | H11: DOS COLORES | I11: 130
A12: HILO | B12: 350
A13: GASTOS OPERATIVOS | B13: 4000
B14: =SUM(B4:B13)/D2 -> 3.1570175
D15: TAMAÑO | E15: PRECIO $ | F15: 100 BOLSAS 1 TINTA | G15: DOLARES
D16: 30*40 | E16: 1800 | F16: =E16*100 -> 180000 | G16: =F16/4000 -> 45
D17: 25*30 | E17: 1600 | F17: =E17*100 -> 160000 | G17: =F17/4000 -> 40
D18: 20*20 | E18: 1400 | F18: =E18*100 -> 140000 | G18: =F18/4000 -> 35
D20: TAMAÑO | E20: PRECIO $ | F20: 100 BOLSAS 2 TINTA | G20: DOLARES
D21: 30*40 | E21: =1800+400 -> 2200 | F21: =E21*100 -> 220000 | G21: =F21/4000 -> 55
D22: 25*30 | E22: =1600+400 -> 2000 | F22: =E22*100 -> 200000 | G22: =F22/4000 -> 50
D23: 20*20 | E23: =1400+400 -> 1800 | F23: =E23*100 -> 180000 | G23: =F23/4000 -> 45

Sheet CAMISAS 
A2: CAMISA TIPO COLUMBIA MANGA CORTA | I2: CAMISA TIPO COLUMBIA MANGA CORTA | Q2: CAMISA TIPO COLUMBIA MANGA LARGA | Y2: CAMISA TIPO COLUMBIA MANGA LARGA
A3: CABALLERO | D3: FRANELAS | F3: 3800 | I3: CABALLERO | L3: FRANELAS | N3: 3800 | Q3: CABALLERO | T3: FRANELAS | V3: 4000 | Y3: CABALLERO | AB3: FRANELAS | AD3: 4500
A4: TELA OXFORD | B4: =1.4*4*F3 -> 21280 | I4: TELA ALGODÓN EGIPCIO | J4: =1.1*3.95*N3 -> 16511 | Q4: TELA oxford | R4: =1.8*4.5*V3 -> 32400 | Y4: TELA MICRO FIBRA | Z4: =1.8*1.95*AD3 -> 15795
A5: CORTE | B5: 1000 | I5: CORTE | J5: 1000 | Q5: CORTE | R5: 1000 | Y5: CORTE | Z5: 1000
A6: BOTONES | B6: =150*7 -> 1050 | D6: BORDADA | I6: BOTONES | J6: 3000 | M6: VINIL | Q6: BOTONES | R6: =500*8 -> 4000 | T6: BORDADA | Y6: BOTONES | Z6: =500*8 -> 4000 | AC6: VINIL
A7: COSTURA | B7: 5000 | I7: COSTURA | J7: 6000 | Q7: COSTURA | R7: 6000 | Y7: COSTURA | Z7: 6000
A8: LOGO VINIL | B8: 5000 | E8: CABALLERO | I8: VINIL | J8: 3000 | M8: CABALLERO | Q8: BORDADO | R8: 6000 | U8: CABALLERO | Y8: VINIL | Z8: 5000 | AC8: CABALLERO
A9: PLANCHA | B9: 500 | D9: +5 DOC | E9: 1 A 5 DOC | F9: DETAL | I9: MALLA | J9: =0.3*2.5*N3/2 -> 1425 | L9: +5 DOC | M9: 1 A 5 DOC | N9: DETAL | Q9: MALLA | R9: =0.3*2.5*V3/2 -> 1500 | T9: +5 DOC | U9: 1 A 5 DOC | V9: DETAL | Y9: MALLA | Z9: =0.3*2.5*AD3/2 -> 1687.5 | AB9: +5 DOC | AC9: 1 A 5 DOC | AD9: DETAL
A10: CORTE DEL PLOTTER | B10: 200 | D10: =D13 -> 15.026579 | E10: =E13 -> 18.135526 | F10: =F13 -> 20.622684 | I10: PLANCHA | J10: 1000 | L10: =L13 -> 13.200474 | M10: =M13 -> 16.754447 | N10: =N13 -> 18.277579 | Q10: PLANCHA | R10: 1000 | T10: =T13 -> 21.985625 | U10: =U13 -> 26.534375 | V10: =V13 -> 30.173375 | Y10: PLANCHA | Z10: 2000 | AB10: =AB13 -> 13.576028 | AC10: =AC13 -> 16.384861 | AD10: =AD13 -> 18.631928
A11: PELON | B11: 300 | I11: DISEÑO | J11: 1000 | Q11: DIGITALIZACION | R11: 3000 | Y11: DISEÑO | Z11: 1000
A12: ETIQUETA | B12: 200 | D12: 0.4 | E12: 0.55 | F12: 0.85 | I12: CORTE DEL PLOTTER | J12: 400 | L12: 0.4 | M12: 0.55 | N12: 0.85 | Q12: CORTE DEL PLOTTER | R12: 400 | T12: 0.4 | U12: 0.55 | V12: 0.85 | Y12: CORTE DEL PLOTTER | Z12: 400 | AB12: 0.4 | AC12: 0.55 | AD12: 0.85
A13: BOLSA | B13: 100 | D13: =B17*1.45 -> 15.026579 | E13: =B17*1.75 -> 18.135526 | F13: =B17*1.99 -> 20.622684 | I13: DEPILADA | J13: 500 | L13: =J19*1.3 -> 13.200474 | M13: =J19*1.65 -> 16.754447 | N13: =J19*1.8 -> 18.277579 | Q13: DEPILADA | R13: 500 | T13: =R19*1.45 -> 21.985625 | U13: =R19*1.75 -> 26.534375 | V13: =R19*1.99 -> 30.173375 | Y13: DEPILADA | Z13: 500 | AB13: =Z19*1.45 -> 13.576028 | AC13: =Z19*1.75 -> 16.384861 | AD13: =Z19*1.99 -> 18.631928
A14: HILO | B14: 250 | I14: ETIQUETA | J14: 200 | Q14: ETIQUETA | R14: 200 | Y14: ETIQUETA | Z14: 200
A15: MARQUILLA | B15: 500 | I15: BOLSA | J15: 0 | Q15: BOLSA | R15: 100 | Y15: BOLSA | Z15: 0
A16: GASTOS OPERATIVOS | B16: 4000 | I16: HILO | J16: 250 | Q16: HILO | R16: 250 | Y16: HILO | Z16: 250
B17: =SUM(B4:B16)/F3 -> 10.363158 | I17: MARQUILLA | J17: 300 | Q17: MARQUILLA | R17: 300 | Y17: MARQUILLA | Z17: 300
I18: GASTOS OPERATIVOS | J18: 4000 | Q18: GASTOS OPERATIVOS | R18: 4000 | Y18: GASTOS OPERATIVOS | Z18: 4000
J19: =SUM(J4:J18)/N3 -> 10.154211 | R19: =SUM(R4:R18)/V3 -> 15.1625 | Z19: =SUM(Z4:Z18)/AD3 -> 9.3627778
A21: CAMISA BASICA | I21: CAMISA BASICA | Q21: CAMISA basica MANGA LARGA
A22: CABALLERO | D22: FRANELAS | F22: 3800 | I22: CABALLERO | L22: FRANELAS | N22: 3800 | Q22: CABALLERO | T22: FRANELAS | V22: 3800
A23: TELA MICRO FIBRA | B23: =1.6*1.3*F22 -> 7904 | I23: TELA MICRO FIBRA | J23: =2*1.95*N22 -> 14820 | Q23: TELA oxford | R23: =1.3*2*V22 -> 9880
A24: CORTE | B24: 1400 | I24: CORTE | J24: 700 | Q24: CORTE | R24: 3000
A25: BOTONES | B25: =6*400 -> 2400 | E25: BORDADA | I25: BOTONES | J25: 2500 | M25: VINIL | Q25: BOTONES | R25: 3000 | T25: BORDADA
A26: COSTURA | B26: 15000 | I26: COSTURA | J26: 12000 | Q26: COSTURA | R26: 7000
A27: BORDADO | B27: 0 | E27: CABALLERO | I27: VINIL | J27: 2000 | M27: CABALLERO | Q27: BORDADO | R27: 14000 | U27: CABALLERO
A28: DIGITALIZACION | B28: 0 | D28: +5 DOC | E28: 1 A 5 DOC | F28: DETAL | I28: DISEÑO | J28: 1000 | L28: +5 DOC | M28: 1 A 5 DOC | N28: DETAL | Q28: PELON | R28: 500 | T28: +5 DOC | U28: 1 A 5 DOC | V28: DETAL
A29: PLANCHA | B29: 0 | D29: =D32 -> 11.946526 | E29: =E32 -> 12.297895 | F29: =F32 -> 13.984463 | I29: PLANCHA | J29: 2000 | L29: =L32 -> 15.480658 | M29: =M32 -> 18.683553 | N29: =N32 -> 21.245868 | Q29: ETIQUETA | R29: 80 | T29: =T32 -> 14.081053 | U29: =U32 -> 18.955263 | V29: =V32 -> 21.554842
A30: CORTE DEL PLOTTER | B30: 0 | I30: CORTE DEL PLOTTER | J30: 200 | Q30: BOLSA y doblado | R30: 500
A31: DEPILADA | B31: 0 | D31: 0.4 | E31: 0.55 | F31: 0.85 | I31: DEPILADA | J31: 500 | L31: 0.4 | M31: 0.55 | N31: 0.85 | Q31: HILO | R31: 500 | T31: 0.4 | U31: 0.55 | V31: 0.85
A32: ETIQUETA | B32: 0 | D32: =B37*1.7 -> 11.946526 | E32: =B37*1.75 -> 12.297895 | F32: =B37*1.99 -> 13.984463 | I32: ETIQUETA | J32: 200 | L32: =J37*1.45 -> 15.480658 | M32: =J37*1.75 -> 18.683553 | N32: =J37*1.99 -> 21.245868 | Q32: MARQUILLA | R32: 0 | T32: =R34*1.3 -> 14.081053 | U32: =R34*1.75 -> 18.955263 | V32: =R34*1.99 -> 21.554842
A33: BOLSA | B33: 0 | I33: BOLSA | J33: 100 | Q33: GASTOS OPERATIVOS | R33: 2700
A34: HILO | B34: 0 | I34: HILO | J34: 250 | R34: =SUM(R23:R33)/V22 -> 10.831579
A35: MARQUILLA | B35: 0 | I35: MARQUILLA | J35: 300
A36: GASTOS OPERATIVOS | B36: 0 | I36: GASTOS OPERATIVOS | J36: 4000
B37: =SUM(B23:B36)/F22 -> 7.0273684 | J37: =SUM(J23:J36)/N22 -> 10.676316
A39: CAMISA BASICA SUBLIMADA TODA
D40: FRANELAS | F40: 4000
A41: TELA MICRO FIBRA | B41: =1.3*2*F40 -> 10400
A42: CORTE | B42: 1000
A43: BOTONES | B43: 2000 | E43: BORDADA
A44: COSTURA | B44: 8000
A45: PELON | B45: =1000 -> 1000 | E45: CABALLERO
A46: PLANCHA | B46: 0 | D46: +5 DOC | E46: 1 A 5 DOC | F46: DETAL
A47: DISEÑO | B47: 0 | D47: =D50 -> 6.625 | E47: =E50 -> 11.2625 | F47: =F50 -> 12.5875
B48: 0
A49: BOLSA | B49: 100 | D49: 0.4 | E49: 0.55 | F49: 0.85
A50: HILO | B50: 250 | D50: =B53*1 -> 6.625 | E50: =B53*1.7 -> 11.2625 | F50: =B53*1.9 -> 12.5875
A51: MARQUILLA | B51: 50
A52: GASTOS OPERATIVOS | B52: 3700
B53: =SUM(B41:B52)/F40 -> 6.625

Sheet FILIPINA
A2: CAMISA BASICA SUBLIMADA TODA
D3: FRANELAS | F3: 4000
A4: TELA MICRO FIBRA | B4: =1.5*3.5*F3 -> 21000
A5: CORTE | B5: 3000
A6: BOTONES | B6: 2800
A7: COSTURA | B7: 8000
A8: IMPRESIÓN | B8: =1.7*10000 -> 17000 | E8: CABALLERO
A9: PLANCHA | B9: 2500 | D9: +5 DOC | E9: 1 A 5 DOC | F9: DETAL
A10: DISEÑO | B10: 1500 | D10: =D13 -> 21.14 | E10: =E13 -> 27.18 | F10: =F13 -> 28.69
A11: PELON | B11: 500
A12: BOLSA | B12: 100 | D12: 0.4 | E12: 0.55 | F12: 0.85
A13: HILO | B13: 250 | D13: =B16*1.4 -> 21.14 | E13: =B16*1.8 -> 27.18 | F13: =B16*1.9 -> 28.69
A14: MARQUILLA | B14: 50
A15: GASTOS OPERATIVOS | B15: 3700
B16: =SUM(B4:B15)/F3 -> 15.1

Sheet VINILES 
B4: PRECIO | C4: IMPRESION | D4: TOTAL | E4: 0.7 | F4: PRECIO DEL METRO
A5: VINIL IMPRIMIBLE | B5: 9 | C5: 5 | D5: =C5+B5 -> 14 | E5: =D5*1.7 -> 23.8 | F5: 24
A6: VINIL SUBLIMABLE | B6: 11 | C6: 5 | D6: =C6+B6 -> 16 | E6: =D6*1.7 -> 27.2 | F6: 28

Sheet MONO QUIRURGICO
A2: MONO QUIRURGICO
F3: 3800
A4: TELA MICRO FIBRA | B4: =2*1.95*F3 -> 14820
A5: CORTE | B5: 700 | E5: CABALLERO
A6: COSTURA | B6: 6000 | D6: 0.4 | E6: 0.55 | F6: 0.85
A7: HILO | B7: 250 | D7: =B10*1.5 -> 10.290789 | E7: =B10*1.7 -> 11.662895 | F7: =B10*1.99 -> 13.652447
A8: MARQUILLA | B8: 300
A9: GASTOS OPERATIVOS | B9: 4000
B10: =SUM(B4:B9)/F3 -> 6.8605263

Sheet TUTU 
F3: 4500
A5: TULL | H5: TOP MICRO
A6: DAMA | D6: 14-16-XS-S | H6: DAMA | K6: 14-16-XS-S
A8: TELA TULL | B8: =4.5*1.8/3*F3 -> 12150 | E8: TUTU TULL | H8: TELA TULL | I8: =0.7*3/3*F3 -> 3150 | L8: TUTU TULL
A9: LICRA PRETINA | B9: =0.2*2.5/3*F3 -> 750 | D9: +5 DOC | E9: 1 A 5 DOC | F9: DETAL | H9: CORTE | I9: 1000 | K9: +5 DOC | L9: 1 A 5 DOC | M9: DETAL
A10: CORTE | B10: 1000 | D10: =D14 -> 7.0566667 | E10: =E14 -> 8.5166667 | F10: =F14 -> 9.6846667 | H10: COSTURA | I10: 2500 | K10: =K14 -> 3.5927778 | L10: =L14 -> 4.3361111 | M10: =M14 -> 4.9307778
A11: COSTURA | B11: 3500 | H11: HILO | I11: 500
A12: HILO | B12: 500 | H12: GASTOS OPERATIVOS | I12: 4000
A13: GASTOS OPERATIVOS | B13: 4000 | D13: 0.35 | E13: 0.5 | F13: 0.8 | I13: =SUM(I8:I12)/F3 -> 2.4777778 | K13: 0.35 | L13: 0.5 | M13: 0.8
B14: =SUM(B8:B13)/F3 -> 4.8666667 | D14: =B14*1.45 -> 7.0566667 | E14: =B14*1.75 -> 8.5166667 | F14: =B14*1.99 -> 9.6846667 | K14: =I13*1.45 -> 3.5927778 | L14: =I13*1.75 -> 4.3361111 | M14: =I13*1.99 -> 4.9307778
A18: MUSELINA
A19: JUVENIL
A20: TELA | B20: =0.35*1.8*4000/3 -> 840 | D20: TALLAS 14-16-XS-S
A21: CORTE | B21: 1000
A22: COSTURA | B22: 2500
A23: BOLSA | B23: 100 | D23: SHORT LICRA NIÑOS 14-16
A24: HILO | B24: 750 | D24: +5 DOC | E24: 1 A 5 DOC | F24: DETAL
A25: GASTOS OPERATIVOS | B25: 4000 | D25: =D29 -> 2.9612222 | E25: =E29 -> 3.5738889 | F25: =F29 -> 4.0640222
B26: =SUM(B20:B25)/F3 -> 2.0422222
D28: 0.35 | E28: 0.5 | F28: 0.8
D29: =B26*1.45 -> 2.9612222 | E29: =B26*1.75 -> 3.5738889 | F29: =B26*1.99 -> 4.0640222

Sheet DELANTAL 
A1: DELANTAL
A2: UNISEX | F2: 3800
A3: TELA | B3: =0.9*4.5/2 -> 2.025
A4: CORTE | B4: =700/F2 -> 0.18421053 | D4: +5 DOC | E4: 1 A 5 DOC | F4: DETAL
A5: COSTURA | B5: =3000/F2 -> 0.78947368 | D5: =D8 -> 9.9639474 | E5: =E8 -> 10.675658 | F5: =F8 -> 14.163039
A6: SUBLIMACION | B6: 1
A7: PLANCHA | B7: =500/F2 -> 0.13157895 | D7: 45 | E7: 75 | F7: 99
A8: DISEÑO | B8: =1500/F2 -> 0.39473684 | D8: =B13*1.4 -> 9.9639474 | E8: =B13*1.5 -> 10.675658 | F8: =B13*1.99 -> 14.163039
A9: CORTE DEL PLOTTER | B9: =500/F2 -> 0.13157895
A10: HERRAJES | B10: =5000/F2 -> 1.3157895
A11: HILO | B11: =350/F2 -> 0.092105263
A12: GASTOS OPERATIVOS | B12: =4000/F2 -> 1.0526316
B13: =SUM(B3:B12) -> 7.1171053

Sheet FRANELILLAS 
A2: FRANELiLLAS EN BLANCO
A3: MUSELINA | E3: 4000 | F3: MICRO
A4: DAMA
A5: TELA | B5: =0.7*1.8/3*2*E3 -> 3360 | F5: DAMA
A6: CORTE | B6: 700 | F6: TELA | G6: =0.7*3/3*2*E3 -> 5600
A7: COSTURA | B7: 3000 | C7: +5 DOC | D7: 1 A 5 DOC | E7: DETAL | F7: CORTE | G7: 700
A8: ETIQUETA | B8: 200 | C8: =C13 -> 4.76875 | D8: =D13 -> 6.29475 | E8: =E13 -> 7.59185 | F8: COSTURA | G8: 2500 | H8: +5 DOC | I8: 1 A 5 DOC | J8: DETAL
A9: BOLSA | B9: 3000 | F9: ETIQUETA | G9: 200 | H9: =H12 -> 5.11125 | I9: =I12 -> 6.16875 | J9: =J12 -> 7.01475
A10: MARQUILLA | B10: 750 | F10: BOLSA | G10: 100
A11: HILO | B11: 250 | D11: MUSELINA | F11: MARQUILLA | G11: 750 | H11: 0.4 | I11: 0.55 | J11: 0.85
A12: GASTOS OPERATIVOS | B12: 4000 | C12: 0.4 | D12: 0.65 | E12: 0.99 | F12: HILO | G12: =B11 -> 250 | H12: =G14*1.45 -> 5.11125 | I12: =G14*1.75 -> 6.16875 | J12: =G14*1.99 -> 7.01475
B13: =SUM(B5:B12)/E3 -> 3.815 | C13: =B13*1.25 -> 4.76875 | D13: =B13*1.65 -> 6.29475 | E13: =B13*1.99 -> 7.59185 | F13: GASTOS OPERATIVOS | G13: =B12 -> 4000
G14: =SUM(G6:G13)/E3 -> 3.525
A18: MUSELINA | E18: 4000 | F18: MICRO
A19: NIÑO | E19: 4000 | F19: NIÑO
A20: TELA | B20: =0.6*1.5*E18 -> 3600 | F20: TELA | G20: =0.5*3/4*2*E3 -> 3000
A21: CORTE | B21: 700 | F21: CORTE | G21: 700
A22: COSTURA | B22: 3000 | C22: +5 DOC | D22: 1 A 5 DOC | E22: DETAL | F22: COSTURA | G22: 2500 | H22: +5 DOC | I22: 1 A 5 DOC | J22: DETAL
A23: ETIQUETA | B23: 200 | C23: =C28 -> 4.5675 | D23: =D28 -> 5.5125 | E23: =E28 -> 6.2685 | F23: ETIQUETA | G23: 200 | H23: =H27 -> 4.16875 | I23: =I27 -> 5.03125 | J23: =J27 -> 5.72125
A24: BOLSA | B24: 100 | F24: BOLSA | G24: 100
A25: MARQUILLA | B25: 750 | F25: MARQUILLA | G25: 750
A26: HILO | B26: 250 | F26: HILO | G26: 250 | H26: 0.4 | I26: 0.55 | J26: 0.85
A27: GASTOS OPERATIVOS | B27: 4000 | C27: 0.4 | D27: 0.55 | E27: 0.85 | F27: GASTOS OPERATIVOS | G27: 4000 | H27: =G28*1.45 -> 4.16875 | I27: =G28*1.75 -> 5.03125 | J27: =G28*1.99 -> 5.72125
B28: =SUM(B20:B27)/E3 -> 3.15 | C28: =B28*1.45 -> 4.5675 | D28: =B28*1.75 -> 5.5125 | E28: =B28*1.99 -> 6.2685 | G28: =SUM(G20:G27)/E3 -> 2.875
A31: MUSELINA | F31: MICRO
A32: CABALLERO | F32: CABALLERO
A33: TELA | B33: =0.8*1.8/3*2*E3 -> 3840 | F33: TELA | G33: =0.8*3/3*2*E3 -> 6400
A34: CORTE | B34: 700 | F34: CORTE | G34: 700
A35: COSTURA | B35: 2500 | C35: +5 DOC | D35: 1 A 5 DOC | E35: DETAL | F35: COSTURA | G35: 2500
A36: MARQUILLA | B36: 750 | C36: =C40 -> 4.47325 | D36: =D40 -> 5.39875 | E36: =E40 -> 6.13915 | F36: MARQUILLA | G36: 750 | H36: +5 DOC | I36: 1 A 5 DOC | J36: DETAL
A37: ETIQUETA | B37: 200 | F37: ETIQUETA | G37: 200 | H37: =H40 -> 5.40125 | I37: =I40 -> 6.51875 | J37: =J40 -> 7.41275
A38: BOLSA | B38: 100 | D38: MUSELINA | F38: BOLSA | G38: 100
A39: HILO | B39: 250 | C39: 0.4 | D39: 0.55 | E39: 0.85 | F39: HILO | G39: =B39 -> 250 | H39: 0.4 | I39: 0.55 | J39: 0.85
A40: GASTOS OPERATIVOS | B40: 4000 | C40: =B41*1.45 -> 4.47325 | D40: =B41*1.75 -> 5.39875 | E40: =B41*1.99 -> 6.13915 | F40: GASTOS OPERATIVOS | G40: =B40 -> 4000 | H40: =G41*1.45 -> 5.40125 | I40: =G41*1.75 -> 6.51875 | J40: =G41*1.99 -> 7.41275
B41: =SUM(B33:B40)/E3 -> 3.085 | G41: =SUM(G33:G40)/E3 -> 3.725
A44: CON DISEÑO EN VINIL PÑO
A45: MUSELINA | F45: MUSELINA
A46: DAMA | F46: NIÑO
A47: TELA | B47: =0.7*1.8/3*2*E3 -> 3360
A48: CORTE | B48: 700 | F48: TELA | G48: =0.5*1.8/4*2*E19 -> 1800
A49: COSTURA | B49: 2500 | F49: CORTE | G49: 700
A50: PLANCHA | B50: 1000 | F50: COSTURA | G50: 2500
A51: VINIL 15 CMS | B51: 1000 | F51: PLANCHA | G51: 1000
A52: DISEÑO | B52: 1000 | C52: +5 DOC | D52: 1 A 5 DOC | E52: DETAL | F52: VINIL 15 CMS | G52: 1000
A53: CORTE DEL PLOTTER | B53: 200 | C53: =C58 -> 5.53175 | D53: =D58 -> 6.67625 | E53: =E58 -> 7.59185 | F53: DISEÑO | G53: 1000 | H53: +5 DOC | I53: 1 A 5 DOC | J53: DETAL
A54: DEPILADA | B54: 200 | F54: CORTE DEL PLOTTER | G54: 200 | H54: =H60 -> 4.96625 | I54: =I60 -> 5.99375 | J54: =J60 -> 6.81575
A55: ETIQUETA | B55: 200 | F55: DEPILADA | G55: 200
A56: BOLSA | B56: 100 | D56: MUSELINA | F56: ETIQUETA | G56: 200
A57: HILO | B57: 250 | C57: 0.4 | D57: 0.55 | E57: 0.85 | F57: BOLSA | G57: 100
A58: MARQUILLA | B58: 750 | C58: =B60*1.45 -> 5.53175 | D58: =B60*1.75 -> 6.67625 | E58: =B60*1.99 -> 7.59185 | F58: HILO | G58: 250 | I58: MUSELINA
A59: GASTOS OPERATIVOS | B59: 4000 | F59: MARQUILLA | G59: 750 | H59: 0.4 | I59: 0.55 | J59: 0.85
B60: =SUM(B47:B59)/E3 -> 3.815 | F60: GASTOS OPERATIVOS | G60: 4000 | H60: =G61*1.45 -> 4.96625 | I60: =G61*1.75 -> 5.99375 | J60: =G61*1.99 -> 6.81575
G61: =SUM(G48:G60)/E3 -> 3.425
A64: MICRO DAMA | F64: MICRO NIÑO
A65: TELA | B65: =0.7*1.8*E3 -> 5040
A66: CORTE | B66: 700 | F66: TELA | G66: =0.5*3/4*2*E19 -> 3000
A67: COSTURA | B67: 2500 | F67: CORTE | G67: 700
A68: PLANCHA | B68: 2000 | F68: COSTURA | G68: 2500
A69: VINIL 15 CMS | B69: 2500 | F69: PLANCHA | G69: 1000
A70: DISEÑO | B70: =B52 -> 1000 | F70: VINIL 15 CMS | G70: =G52 -> 1000
A71: CORTE DEL PLOTTER | B71: =B53 -> 200 | C71: +5 DOC | D71: 1 A 5 DOC | E71: DETAL | F71: DISEÑO | G71: =G53 -> 1000
A72: DEPILADA | B72: 1000 | C72: =C75 -> 7.2645 | D72: =D75 -> 9.519 | E72: =E75 -> 9.9699 | F72: CORTE DEL PLOTTER | G72: =G54 -> 200 | H72: +5 DOC | I72: 1 A 5 DOC | J72: DETAL
A73: ETIQUETA | B73: 1000 | F73: DEPILADA | G73: =G55 -> 200 | H73: =H76 -> 5.40125 | I73: =I76 -> 6.51875 | J73: =J76 -> 7.41275
A74: BOLSA | B74: 100 | C74: 0.4 | D74: 0.55 | E74: 0.85 | F74: ETIQUETA | G74: 200
A75: HILO | B75: =B57 -> 250 | C75: =B78*1.45 -> 7.2645 | D75: =B78*1.9 -> 9.519 | E75: =B78*1.99 -> 9.9699 | F75: BOLSA | G75: 100 | H75: 0.4 | I75: 0.55 | J75: 0.85
A76: MARQUILLA | B76: =B58 -> 750 | F76: HILO | G76: =G58 -> 250 | H76: =G79*1.45 -> 5.40125 | I76: =G79*1.75 -> 6.51875 | J76: =G79*1.99 -> 7.41275
A77: GASTOS OPERATIVOS | B77: 3000 | F77: MARQUILLA | G77: =G59 -> 750
B78: =SUM(B65:B77)/E3 -> 5.01 | F78: GASTOS OPERATIVOS | G78: =G60 -> 4000
G79: =SUM(G66:G78)/E3 -> 3.725
A81: CABALLERO
A82: MUSE | F82: MICRO
A83: TELA | B83: =0.8*1.8*3800 -> 5472 | F83: CABALLERO
A84: CORTE | B84: 700 | F84: TELA | G84: =0.8*3/3*2*E3 -> 6400
A85: COSTURA | B85: 2500 | F85: CORTE | G85: 700
A86: PLANCHA | B86: 1000 | F86: COSTURA | G86: 2500
A87: VINIL 15 CMS | B87: 2000 | C87: +5 DOC | D87: 1 A 5 DOC | E87: DETAL | F87: VINIL | G87: 1000
A88: DISEÑO | B88: 1000 | C88: =C92 -> 6.65985 | D88: =D92 -> 8.03775 | E88: =E92 -> 9.14007 | F88: PLANCHA | G88: 1000
A89: CORTE DEL PLOTTER | B89: 200 | F89: DISEÑO | G89: 1000
A90: DEPILADA | B90: 200 | D90: MUSELINA | F90: CORTE DEL PLOTTER | G90: 200 | H90: +5 DOC | I90: 1 A 5 DOC | J90: DETAL
A91: ETIQUETA | B91: 200 | C91: 0.4 | D91: 0.55 | E91: 0.85 | F91: DEPILADA | G91: =B89 -> 200 | H91: =H94 -> 6.63375 | I91: =I94 -> 8.00625 | J91: =J94 -> 9.10425
A92: BOLSA | B92: 100 | C92: =B96*1.45 -> 6.65985 | D92: =B96*1.75 -> 8.03775 | E92: =B96*1.99 -> 9.14007 | F92: ETIQUETA | G92: 200
A93: HILO | B93: 250 | F93: BOLSA | G93: 100 | H93: 0.4 | I93: 0.55 | J93: 0.85
A94: MARQUILLA | B94: 750 | F94: HILO | G94: 250 | H94: =G97*1.45 -> 6.63375 | I94: =G97*1.75 -> 8.00625 | J94: =G97*1.99 -> 9.10425
A95: GASTOS OPERATIVOS | B95: 4000 | F95: MARQUILLA | G95: 750
B96: =SUM(B83:B95)/E3 -> 4.593 | F96: GASTOS OPERATIVOS | G96: 4000
G97: =SUM(G84:G96)/E3 -> 4.575
A101: MUSE | F101: MUSE
A102: DAMA | F102: NIÑO
A103: TELA | B103: =0.7*1.8/3*2*E3 -> 3360 | F103: TELA | G103: =0.5*1.8/3*2*E18 -> 2400
A104: CORTE | B104: 700 | F104: CORTE | G104: 700
A105: COSTURA | B105: 2500 | C105: +5 DOC | D105: 1 A 5 DOC | E105: DETAL | F105: COSTURA | G105: 2500 | H105: +5 DOC | I105: 1 A 5 DOC | J105: DETAL
A106: SUBLIMACION CARTA | B106: =15000/20 -> 750 | C106: =C109 -> 5.332375 | D106: =D109 -> 6.435625 | E106: =E109 -> 7.318225 | F106: SUBLIMACION CARTA | G106: 750 | H106: =H111 -> 4.984375 | I106: =I111 -> 6.015625 | J106: =J111 -> 6.840625
A107: DISEÑO | B107: 1000 | F107: DISEÑO | G107: 1000
A108: PLANCHA | B108: 1000 | C108: 0.4 | D108: 0.55 | E108: 0.85 | F108: PLANCHA | G108: 1000
A109: ETIQUETA | B109: 200 | C109: =B114*1.45 -> 5.332375 | D109: =B114*1.75 -> 6.435625 | E109: =B114*1.99 -> 7.318225 | F109: ETIQUETA | G109: 200
A110: BOLSA | B110: 100 | F110: BOLSA | G110: 100 | H110: 0.4 | I110: 0.55 | J110: 0.85
A111: MARQUILLA | B111: 750 | F111: MARQUILLA | G111: 750 | H111: =G114*1.45 -> 4.984375 | I111: =G114*1.75 -> 6.015625 | J111: =G114*1.99 -> 6.840625
A112: HILO | B112: 350 | F112: HILO | G112: 350
A113: GASTOS OPERATIVOS | B113: 4000 | F113: GASTOS OPERATIVOS | G113: 4000
B114: =SUM(B103:B113)/E3 -> 3.6775 | G114: =SUM(G103:G113)/E3 -> 3.4375
...

Sheet MANGAS 
A2: SUBLIMADAS TODAS | F2: 3700
A3: PAR DE MANGAS
A4: TELA | B4: =0.6*6*3700/5 -> 2664
A5: IMPRESIÓN | B5: =0.6*13000/5 -> 1560
A6: PLANCHADA | B6: 1500
A7: DISEÑO | B7: 1000
A8: CORTE | B8: 700
A9: COSTURA | B9: 4000 | D9: +5 DOC | E9: 1 a 5 | F9: DETAL
A10: ETIQUETA | B10: 0 | D10: 45 | E10: 75 | F10: 99
A11: CAUCHO | B11: 200 | D11: =B15*1.45 -> 6.0053514 | E11: =B15*1.7 -> 7.0407568 | F11: =B15*1.9 -> 7.8690811
A12: MARQUILLA | B12: 0
A13: HILO | B13: 0
A14: GASTOS OPERATIVOS | B14: 3700
B15: =SUM(B4:B14)/F2 -> 4.1416216
A18: CON LOGO EN VINIL | F18: 3900
A19: PAR DE MANGAS
A20: TELA | B20: =1.8/6*F18 -> 1170
A21: PLANCHADA | B21: 500
A22: VINIL | B22: 1500
A23: CORTE | B23: 300
A24: COSTURA | B24: 2000 | D24: +5 DOC | E24: 1 a 5 | F24: DETAL
A25: ETIQUETA | B25: 200 | D25: 45 | E25: 75 | F25: 99
A26: BOLSA | B26: 100 | D26: =B30*1.45 -> 3.5580769 | E26: =B30*1.75 -> 4.2942308 | F26: =B30*1.99 -> 4.8831538
A27: MARQUILLA | B27: 500
A28: HILO | B28: 300
A29: GASTOS OPERATIVOS | B29: 3000
B30: =SUM(B20:B29)/F18 -> 2.4538462

Sheet GORRA 
A2: GORRA DE MALLA | F2: 4000
A4: GORRA | B4: 9500
A5: PLANCHADA | B5: 500
A6: DTF | B6: 1500
A7: VINIL | B7: 500
A8: ETIQUETA | B8: 200
A9: BOLSA | B9: 100 | D9: +5 DOC | E9: 1 a 5 | F9: DETAL
A10: MARQUILLA | B10: 200 | D10: 40 | E10: 75 | F10: 99
A11: HILO | B11: 300 | D11: =B13*1.65 -> 6.39375 | F11: =B13*1.99 -> 7.71125
A12: GASTOS OPERATIVOS | B12: 2700
B13: =SUM(B4:B12)/F2 -> 3.875

Sheet TOP DAMA
A1: FRANELiLLAS EN BLANCO
A2: MUSELINA | F2: 4500 | H2: MICRO | J2: EN BLANCO
A3: DAMA
A4: TELA | B4: =0.7*1.8/3*2*F2 -> 3780 | H4: DAMA
A5: CORTE | B5: 700 | H5: TELA | I5: =0.7*3/3*2*F2 -> 6300
A6: COSTURA | B6: 2500 | D6: +5 DOC | E6: 1 A 5 DOC | F6: DETAL | H6: CORTE | I6: 700
A7: ETIQUETA | B7: 200 | D7: =D12 -> 3.9568889 | E7: =E12 -> 4.7755556 | F7: =F12 -> 5.4304889 | H7: COSTURA | I7: 2500 | K7: +5 DOC | L7: 1 A 5 DOC | M7: DETAL
A8: BOLSA | B8: 100 | H8: ETIQUETA | I8: 200 | K8: =K11 -> 4.7688889 | L8: =L11 -> 5.7555556 | M8: =M11 -> 6.5448889
A9: MARQUILLA | B9: 750 | H9: BOLSA | I9: 100
A10: HILO | B10: 250 | H10: MARQUILLA | I10: 750 | K10: 0.4 | L10: 0.55 | M10: 0.85
A11: GASTOS OPERATIVOS | B11: 4000 | D11: 0.4 | E11: 0.65 | F11: 0.99 | H11: HILO | I11: =B10 -> 250 | K11: =I13*1.45 -> 4.7688889 | L11: =I13*1.75 -> 5.7555556 | M11: =I13*1.99 -> 6.5448889
B12: =SUM(B4:B11)/F2 -> 2.7288889 | D12: =B12*1.45 -> 3.9568889 | E12: =B12*1.75 -> 4.7755556 | F12: =B12*1.99 -> 5.4304889 | H12: GASTOS OPERATIVOS | I12: =B11 -> 4000
I13: =SUM(I5:I12)/F2 -> 3.2888889
A17: MUSELINA | F17: 4500 | H17: MICRO
A18: NIÑO | F18: 4500 | H18: NIÑO
A19: TELA | B19: =0.5*1.8/4*2*F17 -> 2025 | H19: TELA | I19: =0.5*3/4*2*F2 -> 3375
A20: CORTE | B20: 700 | H20: CORTE | I20: 700
A21: COSTURA | B21: 2500 | D21: +5 DOC | E21: 1 A 5 DOC | F21: DETAL | H21: COSTURA | I21: 2500 | K21: +5 DOC | L21: 1 A 5 DOC | M21: DETAL
A22: ETIQUETA | B22: 200 | D22: =D27 -> 3.3913889 | E22: =E27 -> 4.0930556 | F22: =F27 -> 4.6543889 | H22: ETIQUETA | I22: 200 | K22: =K26 -> 3.8263889 | L22: =L26 -> 4.6180556 | M22: =M26 -> 5.2513889
A23: BOLSA | B23: 100 | H23: BOLSA | I23: 100
A24: MARQUILLA | B24: 750 | H24: MARQUILLA | I24: 750
A25: HILO | B25: 250 | H25: HILO | I25: 250 | K25: 0.4 | L25: 0.55 | M25: 0.85
A26: GASTOS OPERATIVOS | B26: 4000 | D26: 0.4 | E26: 0.55 | F26: 0.85 | H26: GASTOS OPERATIVOS | I26: 4000 | K26: =I27*1.45 -> 3.8263889 | L26: =I27*1.75 -> 4.6180556 | M26: =I27*1.99 -> 5.2513889
B27: =SUM(B19:B26)/F2 -> 2.3388889 | D27: =B27*1.45 -> 3.3913889 | E27: =B27*1.75 -> 4.0930556 | F27: =B27*1.99 -> 4.6543889 | I27: =SUM(I19:I26)/F2 -> 2.6388889
A30: MUSELINA | C30: EN BLANCO | H30: MICRO | J30: EN BLANCO
A31: CABALLERO | H31: CABALLERO
A32: TELA | B32: =0.8*1.8/3*2*F2 -> 4320 | H32: TELA | I32: =0.8*3/3*2*F2 -> 7200
A33: CORTE | B33: 700 | H33: CORTE | I33: 700
A34: COSTURA | B34: 2500 | D34: +5 DOC | E34: 1 A 5 DOC | F34: DETAL | H34: COSTURA | I34: 2500
A35: MARQUILLA | B35: 750 | D35: =D39 -> 4.1308889 | E35: =E39 -> 4.9855556 | F35: =F39 -> 5.6692889 | H35: MARQUILLA | I35: 750 | K35: +5 DOC | L35: 1 A 5 DOC | M35: DETAL
A36: ETIQUETA | B36: 200 | H36: ETIQUETA | I36: 200 | K36: =K39 -> 5.0588889 | L36: =L39 -> 6.1055556 | M36: =M39 -> 6.9428889
A37: BOLSA | B37: 100 | E37: MUSELINA | H37: BOLSA | I37: 100
A38: HILO | B38: 250 | D38: 0.4 | E38: 0.55 | F38: 0.85 | H38: HILO | I38: =B38 -> 250 | K38: 0.4 | L38: 0.55 | M38: 0.85
A39: GASTOS OPERATIVOS | B39: 4000 | D39: =B40*1.45 -> 4.1308889 | E39: =B40*1.75 -> 4.9855556 | F39: =B40*1.99 -> 5.6692889 | H39: GASTOS OPERATIVOS | I39: =B39 -> 4000 | K39: =I40*1.45 -> 5.0588889 | L39: =I40*1.75 -> 6.1055556 | M39: =I40*1.99 -> 6.9428889
B40: =SUM(B32:B39)/F2 -> 2.8488889 | I40: =SUM(I32:I39)/F2 -> 3.4888889
